Workbook

Sheet 00_README
A1: Starseed v4.4 Production Phase 6B Scoring Engine — Public Wording Final
A2: Canon/Ontology, key, codebook, weights, pair geometry and Phase 6B formulas unchanged. v4.4 replaces all 80 respondent-facing items with the approved public wording set.
A3: Active instrument version | B3: starseed-v4.4-phase6b-prod-20260905
A4: Active wording QA | B4: 43_V44_WORDING_QA | C4: Meaning
A5: Codebook | B5: FROZEN v4 candidate | C5: 23×80 canonical expected responses are fully rebuilt from v4 semantic matrices.
A6: Respondent calibration | B6: NONE | C6: This is expert/semantic prototype geometry, not an empirical probability model.
A7: Production scoring | B7: WEIGHTS REBUILT — weighted Phase 6B structural re-certification PASS | C7: Final weights are in 24_FINAL_ITEM_WEIGHTS; admin-order weights are appended to 09_ADMIN_ORDER_CODEBOOK.
A8: Thresholds | B8: 0.15 / 0.40 / 0.70 | C8: Transparent semantic bands; sensitivity-tested rather than optimized for maximum separation.
A9: Direct-target centering | B9: YES — gain 1.70 | C9: Named target items are centered at target-group midpoint; 1.70 is the minimum gain passing all direct-code gates and is not a calibration parameter.
A10: Exact prototype classification | B10: 23/23 | C10: Equal-weight spherical/cosine.
A11: One-item corruption | B11: 11040/11040 | C11: All six alternate legal answers per item.
A12: High-risk code gates | B12: 28/28 | C12: All CRITICAL/SEVERE/HIGH edges meet v4 code-stage gate.
A13: Final item weights | B13: 24_FINAL_ITEM_WEIGHTS | C13: Mean 1.0; bounded semantic-confidence prior; no risk/layer multiplier.

Sheet 01_CANON_MATRIX
A1: Source — v4 23×22 Canon Matrix
A2: Copied values from the frozen v4 matrix rebuild used for codebook generation.
A4: # | B4: 中文 | C4: English | D4: D01 | E4: D02 | F4: D03 | G4: D04 | H4: D05 | I4: D06 | J4: D07 | K4: D08 | L4: D09 | M4: D10 | N4: D11 | O4: D12 | P4: D13 | Q4: D14 | R4: D15 | S4: D16 | T4: D17 | U4: D18 | V4: D19 | W4: D20 | X4: D21 | Y4: D22
A5: 1 | B5: 昴宿星人 | C5: Pleiadian | D5: 2 | E5: 1 | F5: 0 | G5: -1 | H5: -1 | I5: 0 | J5: 0 | K5: 0 | L5: 0 | M5: 0 | N5: -1 | O5: -2 | P5: -1 | Q5: 1 | R5: -1 | S5: 2 | T5: 0 | U5: 0 | V5: 1 | W5: 0 | X5: 0 | Y5: 0
A6: 2 | B6: 大角星人 | C6: Arcturian | D6: -1 | E6: -1 | F6: 0 | G6: 0 | H6: 1 | I6: 0 | J6: 1 | K6: 0 | L6: 1 | M6: 0 | N6: 1 | O6: 0 | P6: 0 | Q6: 0 | R6: 0 | S6: 2 | T6: 0 | U6: 1 | V6: 0 | W6: 1 | X6: 1 | Y6: 0
A7: 3 | B7: 天狼星人 | C7: Sirian | D7: 0 | E7: 1 | F7: 0 | G7: 0 | H7: 0 | I7: 2 | J7: 0 | K7: 2 | L7: -1 | M7: 0 | N7: 0 | O7: -1 | P7: 2 | Q7: 0 | R7: 1 | S7: 1 | T7: 2 | U7: 1 | V7: 1 | W7: -1 | X7: 0 | Y7: 0
A8: 4 | B8: 仙女座人 | C8: Andromedan | D8: 0 | E8: 0 | F8: 0 | G8: 0 | H8: -1 | I8: -1 | J8: 2 | K8: 0 | L8: 2 | M8: -1 | N8: 1 | O8: 0 | P8: 0 | Q8: 0 | R8: 0 | S8: 1 | T8: 0 | U8: 0 | V8: 1 | W8: 2 | X8: 0 | Y8: 0
A9: 5 | B9: 天琴座人 | C9: Lyran | D9: -1 | E9: 0 | F9: 0 | G9: 0 | H9: 0 | I9: 0 | J9: 1 | K9: 0 | L9: 2 | M9: 0 | N9: 2 | O9: 1 | P9: 0 | Q9: -1 | R9: 0 | S9: 0 | T9: 1 | U9: 2 | V9: 0 | W9: 0 | X9: -1 | Y9: 0
A10: 6 | B10: 獵戶座人 | C10: Orion | D10: -1 | E10: -1 | F10: 0 | G10: 2 | H10: 0 | I10: 0 | J10: 1 | K10: 0 | L10: 0 | M10: 0 | N10: -1 | O10: 1 | P10: 1 | Q10: 0 | R10: 1 | S10: 0 | T10: 0 | U10: 0 | V10: 2 | W10: 0 | X10: 2 | Y10: 0
A11: 7 | B11: 明塔卡星人 | C11: Mintakan | D11: 0 | E11: 1 | F11: 0 | G11: -1 | H11: -1 | I11: 0 | J11: 0 | K11: 0 | L11: 0 | M11: 0 | N11: -1 | O11: -2 | P11: -1 | Q11: 1 | R11: -1 | S11: 2 | T11: 0 | U11: 0 | V11: 1 | W11: -1 | X11: 0 | Y11: -2
A12: 8 | B12: 金星人 | C12: Venusian | D12: 0 | E12: 1 | F12: 2 | G12: -1 | H12: -1 | I12: 0 | J12: 0 | K12: 0 | L12: 0 | M12: 0 | N12: 0 | O12: -2 | P12: -1 | Q12: 1 | R12: 0 | S12: 2 | T12: 0 | U12: 0 | V12: 0 | W12: 0 | X12: 0 | Y12: 0
A13: 9 | B13: 哈達爾星人 | C13: Hadarian | D13: 0 | E13: 2 | F13: 0 | G13: -1 | H13: -1 | I13: 1 | J13: -1 | K13: 0 | L13: 0 | M13: 0 | N13: 0 | O13: -2 | P13: -2 | Q13: 0 | R13: -1 | S13: 2 | T13: 0 | U13: 0 | V13: 0 | W13: 0 | X13: 0 | Y13: 0
A14: 10 | B14: 北極星人 | C14: Polarian | D14: 0 | E14: 1 | F14: 0 | G14: 0 | H14: 0 | I14: 2 | J14: 0 | K14: 0 | L14: -1 | M14: 0 | N14: -1 | O14: -1 | P14: 0 | Q14: 1 | R14: 2 | S14: 0 | T14: 0 | U14: 1 | V14: 0 | W14: -2 | X14: 0 | Y14: 0
A15: 11 | B15: 半人馬座α星人 | C15: Alpha Centaurian | D15: -1 | E15: 0 | F15: -1 | G15: 1 | H15: 2 | I15: 1 | J15: 0 | K15: 0 | L15: -1 | M15: 0 | N15: -1 | O15: -1 | P15: 0 | Q15: 0 | R15: 0 | S15: 0 | T15: 1 | U15: 2 | V15: 0 | W15: 0 | X15: 0 | Y15: 0
A16: 12 | B16: 織女星人 | C16: Vegan | D16: 0 | E16: -1 | F16: 1 | G16: 1 | H16: 0 | I16: -1 | J16: 1 | K16: 0 | L16: 2 | M16: 0 | N16: 1 | O16: 0 | P16: 1 | Q16: -1 | R16: 0 | S16: 1 | T16: 0 | U16: 0 | V16: 1 | W16: 2 | X16: 1 | Y16: 0
... A27: 23 | B27: 地球源靈魂 | C27: Earth-Origin Soul | D27: 0 | E27: 1 | F27: 0 | G27: 0 | H27: 0 | I27: 1 | J27: -1 | K27: 0 | L27: -1 | M27: 0 | N27: 0 | O27: 0 | P27: 0 | Q27: 1 | R27: 1 | S27: 1 | T27: 1 | U27: 2 | V27: 0 | W27: -2 | X27: 0 | Y27: 2

Sheet 02_MOTIF_MATRIX
A1: Source — v4 23×19 Motif Matrix
A2: Copied values from the frozen v4 matrix rebuild used for codebook generation.
A4: # | B4: 中文 | C4: English | D4: M01 | E4: M02 | F4: M03 | G4: M04 | H4: M05 | I4: M06 | J4: M07 | K4: M08 | L4: M09 | M4: M10 | N4: M11 | O4: M12 | P4: M13 | Q4: M14 | R4: M15 | S4: M16 | T4: M17 | U4: M18 | V4: M19
A5: 1 | B5: 昴宿星人 | C5: Pleiadian | D5: 0 | E5: 0 | F5: 0 | G5: 0 | H5: 0 | I5: 0 | J5: 0 | K5: 0 | L5: 0 | M5: 0 | N5: 0 | O5: 0 | P5: 0 | Q5: 0 | R5: 0 | S5: 0 | T5: 0 | U5: 0 | V5: 0
A6: 2 | B6: 大角星人 | C6: Arcturian | D6: 0 | E6: 0 | F6: 0 | G6: 0 | H6: 0 | I6: 2 | J6: 0 | K6: 0 | L6: 0 | M6: 0 | N6: 0 | O6: 0 | P6: 0 | Q6: 0 | R6: 0 | S6: 0 | T6: 0 | U6: 0 | V6: 0
A7: 3 | B7: 天狼星人 | C7: Sirian | D7: 0 | E7: 0 | F7: 1 | G7: 0 | H7: 0 | I7: 0 | J7: 0 | K7: 0 | L7: 0 | M7: 0 | N7: 0 | O7: 0 | P7: 0 | Q7: 0 | R7: 0 | S7: 0 | T7: 0 | U7: 0 | V7: 2
A8: 4 | B8: 仙女座人 | C8: Andromedan | D8: 0 | E8: 0 | F8: 0 | G8: 0 | H8: 0 | I8: 0 | J8: 0 | K8: 0 | L8: 0 | M8: 0 | N8: 0 | O8: 0 | P8: 2 | Q8: 0 | R8: 0 | S8: 0 | T8: 0 | U8: 0 | V8: 0
A9: 5 | B9: 天琴座人 | C9: Lyran | D9: 0 | E9: 0 | F9: 0 | G9: 1 | H9: 0 | I9: 0 | J9: 0 | K9: 0 | L9: 0 | M9: 0 | N9: 0 | O9: 0 | P9: 0 | Q9: 0 | R9: 1 | S9: 0 | T9: 0 | U9: 0 | V9: 0
A10: 6 | B10: 獵戶座人 | C10: Orion | D10: 0 | E10: 0 | F10: 0 | G10: 0 | H10: 0 | I10: 0 | J10: 0 | K10: 0 | L10: 0 | M10: 0 | N10: 0 | O10: 2 | P10: 0 | Q10: 0 | R10: 0 | S10: 0 | T10: 0 | U10: 0 | V10: 0
A11: 7 | B11: 明塔卡星人 | C11: Mintakan | D11: 2 | E11: 0 | F11: 2 | G11: 0 | H11: 0 | I11: 0 | J11: 0 | K11: 0 | L11: 0 | M11: 0 | N11: 0 | O11: 0 | P11: 0 | Q11: 0 | R11: 0 | S11: 0 | T11: 0 | U11: 0 | V11: 0
A12: 8 | B12: 金星人 | C12: Venusian | D12: 0 | E12: 0 | F12: 0 | G12: 0 | H12: 0 | I12: 0 | J12: 0 | K12: 2 | L12: 0 | M12: 0 | N12: 0 | O12: 0 | P12: 0 | Q12: 0 | R12: 0 | S12: 0 | T12: 0 | U12: 1 | V12: 0
A13: 9 | B13: 哈達爾星人 | C13: Hadarian | D13: 0 | E13: 0 | F13: 0 | G13: 0 | H13: 0 | I13: 0 | J13: 0 | K13: 0 | L13: 2 | M13: 0 | N13: 0 | O13: 0 | P13: 0 | Q13: 0 | R13: 0 | S13: 0 | T13: 0 | U13: 0 | V13: 0
A14: 10 | B14: 北極星人 | C14: Polarian | D14: 0 | E14: 0 | F14: 0 | G14: 0 | H14: 0 | I14: 0 | J14: 0 | K14: 0 | L14: 0 | M14: 2 | N14: 0 | O14: 0 | P14: 0 | Q14: 0 | R14: 0 | S14: 0 | T14: 0 | U14: 0 | V14: 0
A15: 11 | B15: 半人馬座α星人 | C15: Alpha Centaurian | D15: 0 | E15: 0 | F15: 0 | G15: 0 | H15: 0 | I15: 0 | J15: 0 | K15: 0 | L15: 0 | M15: 0 | N15: 0 | O15: 0 | P15: 0 | Q15: 0 | R15: 0 | S15: 0 | T15: 0 | U15: 0 | V15: 0
A16: 12 | B16: 織女星人 | C16: Vegan | D16: 0 | E16: 0 | F16: 0 | G16: 0 | H16: 0 | I16: 0 | J16: 0 | K16: 0 | L16: 0 | M16: 0 | N16: 0 | O16: 0 | P16: 2 | Q16: 0 | R16: 0 | S16: 0 | T16: 0 | U16: 2 | V16: 0
... A27: 23 | B27: 地球源靈魂 | C27: Earth-Origin Soul | D27: 0 | E27: 0 | F27: 0 | G27: 0 | H27: 0 | I27: 0 | J27: 0 | K27: 0 | L27: 0 | M27: 0 | N27: 0 | O27: 0 | P27: 0 | Q27: 2 | R27: 0 | S27: 0 | T27: 0 | U27: 0 | V27: 0

Sheet 03_FINAL_ITEMS
A1: Source — v4.4 PUBLIC WORDING FINAL — 80 Final Items
A2: 80/80 respondent-facing items replaced with approved public wording. Frozen semantic cuts, Pole A/B direction, keys, codebook and final weights unchanged.
A4: Slot | B4: Layer | C4: Contrast | D4: Direct target | E4: Mechanism | F4: Features | G4: Stem | H4: Pole A | I4: Pole B | J4: Key | K4: Admin # | L4: Status | M4: Mode
A5: G01 | B5: GLOBAL | C5: 情緒場滲透 ↔ 證據驗證 | D5: — | E5: Affect vs verification | F5: D01,D04 | G5: 面對一段同時帶有情緒和資訊的分享，你第一個自然反應比較像…… | H5: 先留意其中的情緒變化和彼此的關係，再形成自己的理解 | I5: 先看看說法有沒有道理、前後有沒有矛盾，再形成自己的理解 | J5: 1 | K5: 7 | L5: KEEP | M5: ABSOLUTE SEMANTIC
A6: G02 | B6: GLOBAL | C6: 深度關係投入 ↔ 自主決策 | D6: — | E6: Bond depth vs autonomy | F6: D02,D09 | G6: 一個對你很重要的決定，也會明顯影響親近的人時，你比較自然會…… | H6: 把彼此的關係和共同承諾當成最重要的考量之一 | I6: 先確定這仍是自己真正想走的方向，再想怎樣和對方協調 | J6: -1 | K6: 9 | L6: KEEP | M6: ABSOLUTE SEMANTIC
A7: G03 | B7: GLOBAL | C7: 審美感官介入 ↔ 機制系統解法 | D7: — | E7: Aesthetic interface vs mechanism | F7: D03,D05 | G7: 想改善一個使用起來不太順的空間或服務時，你比較傾向…… | H7: 調整光線、聲音、材質、節奏或擺設，改變整體感受 | I7: 找出流程和使用方式哪裡有問題，再調整得更好用 | J7: -1 | K7: 67 | L7: KEEP | M7: ABSOLUTE SEMANTIC
A8: G04 | B8: GLOBAL | C8: 高驗證需求 ↔ 先採用暫時性直覺/經驗 | D8: — | E8: Verification continuum | F8: D04 | G8: 遇到一個對你有意義、但還不能完全確定的說法時，你比較傾向…… | H8: 先找理由、證據和可能推翻它的例子，再決定相信多少 | I8: 先把直覺或親身經驗當成一個暫時方向，邊使用邊修正 | J8: 1 | K8: 29 | L8: KEEP | M8: ABSOLUTE SEMANTIC
A9: G05 | B9: GLOBAL | C9: 機制系統建模 ↔ 情緒場讀取 | D9: — | E9: Mechanism vs affect | F9: D05,D01 | G9: 當一個團隊讓你覺得「哪裡不對」，但原因還不清楚時，你比較容易先從…… | H9: 流程、分工和各環節怎樣互相影響去找問題 | I9: 現場的情緒變化和大家的互動氣氛去感受問題 | J9: 1 | K9: 35 | L9: REPOINT | M9: ABSOLUTE SEMANTIC
A10: G06 | B10: GLOBAL | C10: 長期持續 ↔ 快速啟動 | D10: — | E10: Horizon vs initiation | F10: D06,D11 | G10: 遇到一個值得投入、但還不知道會怎麼發展的新方向時，你比較像…… | H10: 選擇穩定投入，慢慢累積和加深 | I10: 趁還有空間時先開始，讓行動告訴自己下一步怎麼走 | J10: -1 | K10: 19 | L10: KEEP | M10: ABSOLUTE SEMANTIC
A11: G07 | B11: GLOBAL | C11: 宏觀視角 ↔ 局部/地面視角 | D11: — | E11: Perspective scope | F11: D07 | G11: 要理解一個複雜問題時，你比較自然把注意力放在哪裡？ | H11: 先看整體、各部分怎樣連起來，以及可能有什麼長遠影響 | I11: 先看眼前的細節和實際正在發生什麼 | J11: 1 | K11: 43 | L11: REBUILD | M11: ABSOLUTE SEMANTIC
A12: G08 | B12: GLOBAL | C12: 探索移動 ↔ 扎根延續 | D12: — | E12: Mobility continuum | F12: D20 | G12: 面對一段沒有外在限制的生活安排，你比較喜歡…… | H12: 在不同地方、路線或活動之間移動，透過變化增加經驗 | I12: 在熟悉的地方或路線上一直累積，讓生活越來越有延續感 | J12: 1 | K12: 57 | L12: REBUILD | M12: ABSOLUTE SEMANTIC
A13: G09 | B13: GLOBAL | C13: 自主決策 ↔ 接受協調約束/角色義務 | D13: — | E13: Autonomy under constraint | F13: D09 | G13: 加入一個已有清楚規則和分工的合作時，你比較自然會…… | H13: 保留重新談條件和自己決定做法的空間 | I13: 接受大家共同定下的規則和角色，在範圍內做好自己的部分 | J13: 1 | K13: 23 | L13: REBUILD | M13: ABSOLUTE SEMANTIC
A14: G10 | B14: GLOBAL | C14: 集中指揮 ↔ 分散共治 | D14: — | E14: Authority architecture | F14: D10 | G14: 很多人需要一起做決定時，你比較偏好…… | H14: 由一個人或少數人做最後決定，再把工作分配下去 | I14: 讓相關的人一起討論、一起決定 | J14: -1 | K14: 39 | L14: KEEP | M14: ABSOLUTE SEMANTIC
A15: G11 | B15: GLOBAL | C15: 立即啟動 ↔ 先觀察延後 | D15: — | E15: Initiation latency | F15: D11 | G15: 一個新機會看起來有潛力，但還有不少未知時，你通常會…… | H15: 先開始做，再一邊行動一邊補足資訊 | I15: 先繼續觀察，等了解得更清楚再開始 | J15: -1 | K15: 25 | L15: KEEP | M15: ABSOLUTE SEMANTIC
A16: G12 | B16: GLOBAL | C16: 直接處理衝突 ↔ 間接/降溫處理 | D16: — | E16: Conflict engagement | F16: D12 | G16: 當分歧已經很明顯，雙方也知道彼此不同意時，你通常會…… | H16: 把最主要的不同直接說清楚，當面處理要決定的事 | I16: 先降低張力或用比較間接的方式，等情況緩和後再處理 | J16: 1 | K16: 45 | L16: KEEP | M16: ABSOLUTE SEMANTIC
... A84: A12 | B84: ANCHOR | C84: operational command ↔ civilization-scale institution architecture | D84: Draconian ↔ Anunnaki / Nibiruan | E84: Command scale vs governance scale | F84: D17,D18,D07,D05 | G84: 當同一套規則在不同地方遇到不同例外時，你比較自然會設計哪種做法？ | H84: 讓各地方有清楚的負責人，遇到例外時可以直接判斷和處理 | I84: 先訂一套所有地方都適用的例外處理原則和資源安排 | J84: -1 | K84: 69 | L84: REBUILD | M84: COMPARATIVE CENTERED

Sheet 04_CODEBOOK_CONTROL
A1: Codebook Generation Rules
A2: Scale-aware semantic projection. Salience zero is neutral/no evidence, never a negative pole.
A4: Component | B4: Rule | C4: Formula / value | D4: Why | E4: Status | F4: Notes
A5: Feature scale | B5: All matrix values divide by 2 | C5: bipolar → [-1,1]; salience/motif → [0,1] | D5: Common evidence scale without pretending salience is bipolar. | E5: FROZEN
A6: Global direction | B6: Signed semantic coefficients, L1 normalized | C6: raw=Σw_f z_lf | D6: Uses only blueprint-listed features. | E6: FROZEN
A7: Direct item direction | B7: Target A centroid − target B centroid, L1 normalized | C7: w ∝ μA−μB | D7: Uses Canon geometry to specify comparative semantic direction. | E7: FROZEN
A8: Comparative center | B8: Midpoint centering with conservative gain | C8: s=clip(1.70(raw−m),−1,1) | D8: 1.70 is the smallest simple gain that passes all v4 direct-code gates; weak differences remain weaker and are not forced to ±3. | E8: FROZEN
A9: Absolute Global | B9: No target midpoint | C9: s=clip(raw,−1,1) | D9: Preserves ontology absolute polarity. | E9: FROZEN
A10: Quantization | B10: 0/.15/.40/.70 bands | C10: 0 if |s|<.15; ±1<.40; ±2<.70; else ±3 | D10: Simple interpretable bands; not selected by maximizing distance. | E10: FROZEN
A11: Canonical UI transform | B11: Pole A is positive | C11: x=raw_response×key | D11: Key remains from final-item left/right balance. | E11: FROZEN
A14: Numeric controls
A15: Neutral threshold | B15: 0.15
A16: ±1→±2 threshold | B16: 0.4
A17: ±2→±3 threshold | B17: 0.7
A18: Comparative gain | B18: 1.7

Sheet 05_FEATURE_MODEL
A1: Standardized 41-Feature Lineage Model
A2: Bipolar D values /2 → [-1,1]. D08/D16-D19 and all motifs /2 → [0,1].
A4: # | B4: 中文 | C4: English | D4: D01 | E4: D02 | F4: D03 | G4: D04 | H4: D05 | I4: D06 | J4: D07 | K4: D08 | L4: D09 | M4: D10 | N4: D11 | O4: D12 | P4: D13 | Q4: D14 | R4: D15 | S4: D16 | T4: D17 | U4: D18 | V4: D19 | W4: D20 | X4: D21 | Y4: D22 | Z4: M01 | AA4: M02 | AB4: M03 | AC4: M04 | AD4: M05 | AE4: M06 | AF4: M07 | AG4: M08 | AH4: M09 | AI4: M10 | AJ4: M11 | AK4: M12 | AL4: M13 | AM4: M14 | AN4: M15 | AO4: M16 | AP4: M17 | AQ4: M18 | AR4: M19
A5: 1 | B5: 昴宿星人 | C5: Pleiadian | D5: 1 | E5: 0.5 | F5: 0 | G5: -0.5 | H5: -0.5 | I5: 0 | J5: 0 | K5: 0 | L5: 0 | M5: 0 | N5: -0.5 | O5: -1 | P5: -0.5 | Q5: 0.5 | R5: -0.5 | S5: 1 | T5: 0 | U5: 0 | V5: 0.5 | W5: 0 | X5: 0 | Y5: 0 | Z5: 0 | AA5: 0 | AB5: 0 | AC5: 0 | AD5: 0 | AE5: 0 | AF5: 0 | AG5: 0 | AH5: 0 | AI5: 0 | AJ5: 0 | AK5: 0 | AL5: 0 | AM5: 0 | AN5: 0 | AO5: 0 | AP5: 0 | AQ5: 0 | AR5: 0
A6: 2 | B6: 大角星人 | C6: Arcturian | D6: -0.5 | E6: -0.5 | F6: 0 | G6: 0 | H6: 0.5 | I6: 0 | J6: 0.5 | K6: 0 | L6: 0.5 | M6: 0 | N6: 0.5 | O6: 0 | P6: 0 | Q6: 0 | R6: 0 | S6: 1 | T6: 0 | U6: 0.5 | V6: 0 | W6: 0.5 | X6: 0.5 | Y6: 0 | Z6: 0 | AA6: 0 | AB6: 0 | AC6: 0 | AD6: 0 | AE6: 1 | AF6: 0 | AG6: 0 | AH6: 0 | AI6: 0 | AJ6: 0 | AK6: 0 | AL6: 0 | AM6: 0 | AN6: 0 | AO6: 0 | AP6: 0 | AQ6: 0 | AR6: 0
A7: 3 | B7: 天狼星人 | C7: Sirian | D7: 0 | E7: 0.5 | F7: 0 | G7: 0 | H7: 0 | I7: 1 | J7: 0 | K7: 1 | L7: -0.5 | M7: 0 | N7: 0 | O7: -0.5 | P7: 1 | Q7: 0 | R7: 0.5 | S7: 0.5 | T7: 1 | U7: 0.5 | V7: 0.5 | W7: -0.5 | X7: 0 | Y7: 0 | Z7: 0 | AA7: 0 | AB7: 0.5 | AC7: 0 | AD7: 0 | AE7: 0 | AF7: 0 | AG7: 0 | AH7: 0 | AI7: 0 | AJ7: 0 | AK7: 0 | AL7: 0 | AM7: 0 | AN7: 0 | AO7: 0 | AP7: 0 | AQ7: 0 | AR7: 1
A8: 4 | B8: 仙女座人 | C8: Andromedan | D8: 0 | E8: 0 | F8: 0 | G8: 0 | H8: -0.5 | I8: -0.5 | J8: 1 | K8: 0 | L8: 1 | M8: -0.5 | N8: 0.5 | O8: 0 | P8: 0 | Q8: 0 | R8: 0 | S8: 0.5 | T8: 0 | U8: 0 | V8: 0.5 | W8: 1 | X8: 0 | Y8: 0 | Z8: 0 | AA8: 0 | AB8: 0 | AC8: 0 | AD8: 0 | AE8: 0 | AF8: 0 | AG8: 0 | AH8: 0 | AI8: 0 | AJ8: 0 | AK8: 0 | AL8: 1 | AM8: 0 | AN8: 0 | AO8: 0 | AP8: 0 | AQ8: 0 | AR8: 0
A9: 5 | B9: 天琴座人 | C9: Lyran | D9: -0.5 | E9: 0 | F9: 0 | G9: 0 | H9: 0 | I9: 0 | J9: 0.5 | K9: 0 | L9: 1 | M9: 0 | N9: 1 | O9: 0.5 | P9: 0 | Q9: -0.5 | R9: 0 | S9: 0 | T9: 0.5 | U9: 1 | V9: 0 | W9: 0 | X9: -0.5 | Y9: 0 | Z9: 0 | AA9: 0 | AB9: 0 | AC9: 0.5 | AD9: 0 | AE9: 0 | AF9: 0 | AG9: 0 | AH9: 0 | AI9: 0 | AJ9: 0 | AK9: 0 | AL9: 0 | AM9: 0 | AN9: 0.5 | AO9: 0 | AP9: 0 | AQ9: 0 | AR9: 0
A10: 6 | B10: 獵戶座人 | C10: Orion | D10: -0.5 | E10: -0.5 | F10: 0 | G10: 1 | H10: 0 | I10: 0 | J10: 0.5 | K10: 0 | L10: 0 | M10: 0 | N10: -0.5 | O10: 0.5 | P10: 0.5 | Q10: 0 | R10: 0.5 | S10: 0 | T10: 0 | U10: 0 | V10: 1 | W10: 0 | X10: 1 | Y10: 0 | Z10: 0 | AA10: 0 | AB10: 0 | AC10: 0 | AD10: 0 | AE10: 0 | AF10: 0 | AG10: 0 | AH10: 0 | AI10: 0 | AJ10: 0 | AK10: 1 | AL10: 0 | AM10: 0 | AN10: 0 | AO10: 0 | AP10: 0 | AQ10: 0 | AR10: 0
A11: 7 | B11: 明塔卡星人 | C11: Mintakan | D11: 0 | E11: 0.5 | F11: 0 | G11: -0.5 | H11: -0.5 | I11: 0 | J11: 0 | K11: 0 | L11: 0 | M11: 0 | N11: -0.5 | O11: -1 | P11: -0.5 | Q11: 0.5 | R11: -0.5 | S11: 1 | T11: 0 | U11: 0 | V11: 0.5 | W11: -0.5 | X11: 0 | Y11: -1 | Z11: 1 | AA11: 0 | AB11: 1 | AC11: 0 | AD11: 0 | AE11: 0 | AF11: 0 | AG11: 0 | AH11: 0 | AI11: 0 | AJ11: 0 | AK11: 0 | AL11: 0 | AM11: 0 | AN11: 0 | AO11: 0 | AP11: 0 | AQ11: 0 | AR11: 0
A12: 8 | B12: 金星人 | C12: Venusian | D12: 0 | E12: 0.5 | F12: 1 | G12: -0.5 | H12: -0.5 | I12: 0 | J12: 0 | K12: 0 | L12: 0 | M12: 0 | N12: 0 | O12: -1 | P12: -0.5 | Q12: 0.5 | R12: 0 | S12: 1 | T12: 0 | U12: 0 | V12: 0 | W12: 0 | X12: 0 | Y12: 0 | Z12: 0 | AA12: 0 | AB12: 0 | AC12: 0 | AD12: 0 | AE12: 0 | AF12: 0 | AG12: 1 | AH12: 0 | AI12: 0 | AJ12: 0 | AK12: 0 | AL12: 0 | AM12: 0 | AN12: 0 | AO12: 0 | AP12: 0 | AQ12: 0.5 | AR12: 0
A13: 9 | B13: 哈達爾星人 | C13: Hadarian | D13: 0 | E13: 1 | F13: 0 | G13: -0.5 | H13: -0.5 | I13: 0.5 | J13: -0.5 | K13: 0 | L13: 0 | M13: 0 | N13: 0 | O13: -1 | P13: -1 | Q13: 0 | R13: -0.5 | S13: 1 | T13: 0 | U13: 0 | V13: 0 | W13: 0 | X13: 0 | Y13: 0 | Z13: 0 | AA13: 0 | AB13: 0 | AC13: 0 | AD13: 0 | AE13: 0 | AF13: 0 | AG13: 0 | AH13: 1 | AI13: 0 | AJ13: 0 | AK13: 0 | AL13: 0 | AM13: 0 | AN13: 0 | AO13: 0 | AP13: 0 | AQ13: 0 | AR13: 0
A14: 10 | B14: 北極星人 | C14: Polarian | D14: 0 | E14: 0.5 | F14: 0 | G14: 0 | H14: 0 | I14: 1 | J14: 0 | K14: 0 | L14: -0.5 | M14: 0 | N14: -0.5 | O14: -0.5 | P14: 0 | Q14: 0.5 | R14: 1 | S14: 0 | T14: 0 | U14: 0.5 | V14: 0 | W14: -1 | X14: 0 | Y14: 0 | Z14: 0 | AA14: 0 | AB14: 0 | AC14: 0 | AD14: 0 | AE14: 0 | AF14: 0 | AG14: 0 | AH14: 0 | AI14: 1 | AJ14: 0 | AK14: 0 | AL14: 0 | AM14: 0 | AN14: 0 | AO14: 0 | AP14: 0 | AQ14: 0 | AR14: 0
A15: 11 | B15: 半人馬座α星人 | C15: Alpha Centaurian | D15: -0.5 | E15: 0 | F15: -0.5 | G15: 0.5 | H15: 1 | I15: 0.5 | J15: 0 | K15: 0 | L15: -0.5 | M15: 0 | N15: -0.5 | O15: -0.5 | P15: 0 | Q15: 0 | R15: 0 | S15: 0 | T15: 0.5 | U15: 1 | V15: 0 | W15: 0 | X15: 0 | Y15: 0 | Z15: 0 | AA15: 0 | AB15: 0 | AC15: 0 | AD15: 0 | AE15: 0 | AF15: 0 | AG15: 0 | AH15: 0 | AI15: 0 | AJ15: 0 | AK15: 0 | AL15: 0 | AM15: 0 | AN15: 0 | AO15: 0 | AP15: 0 | AQ15: 0 | AR15: 0
A16: 12 | B16: 織女星人 | C16: Vegan | D16: 0 | E16: -0.5 | F16: 0.5 | G16: 0.5 | H16: 0 | I16: -0.5 | J16: 0.5 | K16: 0 | L16: 1 | M16: 0 | N16: 0.5 | O16: 0 | P16: 0.5 | Q16: -0.5 | R16: 0 | S16: 0.5 | T16: 0 | U16: 0 | V16: 0.5 | W16: 1 | X16: 0.5 | Y16: 0 | Z16: 0 | AA16: 0 | AB16: 0 | AC16: 0 | AD16: 0 | AE16: 0 | AF16: 0 | AG16: 0 | AH16: 0 | AI16: 0 | AJ16: 0 | AK16: 0 | AL16: 1 | AM16: 0 | AN16: 0 | AO16: 0 | AP16: 0 | AQ16: 1 | AR16: 0
... A27: 23 | B27: 地球源靈魂 | C27: Earth-Origin Soul | D27: 0 | E27: 0.5 | F27: 0 | G27: 0 | H27: 0 | I27: 0.5 | J27: -0.5 | K27: 0 | L27: -0.5 | M27: 0 | N27: 0 | O27: 0 | P27: 0 | Q27: 0.5 | R27: 0.5 | S27: 0.5 | T27: 0.5 | U27: 1 | V27: 0 | W27: -1 | X27: 0 | Y27: 1 | Z27: 0 | AA27: 0 | AB27: 0 | AC27: 0 | AD27: 0 | AE27: 0 | AF27: 0 | AG27: 0 | AH27: 0 | AI27: 0 | AJ27: 0 | AK27: 0 | AL27: 0 | AM27: 1 | AN27: 0 | AO27: 0 | AP27: 0 | AQ27: 0 | AR27: 0

Sheet 06_ITEM_POLE_MODEL
A1: 80-Item Pole Direction Model
A2: Positive coefficient means higher feature value supports Pole A. Local/anchor directions are Canon-target centroid differences; G30 is also centered because it is a named CRITICAL separator.
A4: Slot | B4: Layer | C4: Contrast | D4: Target | E4: Mode | F4: A target | G4: B target | H4: Raw A | I4: Raw B | J4: Midpoint | K4: Raw gap | L4: D01 | M4: D02 | N4: D03 | O4: D04 | P4: D05 | Q4: D06 | R4: D07 | S4: D08 | T4: D09 | U4: D10 | V4: D11 | W4: D12 | X4: D13 | Y4: D14 | Z4: D15 | AA4: D16 | AB4: D17 | AC4: D18 | AD4: D19 | AE4: D20 | AF4: D21 | AG4: D22 | AH4: M01 | AI4: M02 | AJ4: M03 | AK4: M04 | AL4: M05 | AM4: M06 | AN4: M07 | AO4: M08 | AP4: M09 | AQ4: M10 | AR4: M11 | AS4: M12 | AT4: M13 | AU4: M14 | AV4: M15 | AW4: M16 | AX4: M17 | AY4: M18 | AZ4: M19
A5: G01 | B5: GLOBAL | C5: 情緒場滲透 ↔ 證據驗證 | D5: — | E5: ABSOLUTE SEMANTIC | F5: — | G5: — | J5: 0 | L5: 0.5 | M5: 0 | N5: 0 | O5: -0.5 | P5: 0 | Q5: 0 | R5: 0 | S5: 0 | T5: 0 | U5: 0 | V5: 0 | W5: 0 | X5: 0 | Y5: 0 | Z5: 0 | AA5: 0 | AB5: 0 | AC5: 0 | AD5: 0 | AE5: 0 | AF5: 0 | AG5: 0 | AH5: 0 | AI5: 0 | AJ5: 0 | AK5: 0 | AL5: 0 | AM5: 0 | AN5: 0 | AO5: 0 | AP5: 0 | AQ5: 0 | AR5: 0 | AS5: 0 | AT5: 0 | AU5: 0 | AV5: 0 | AW5: 0 | AX5: 0 | AY5: 0 | AZ5: 0
A6: G02 | B6: GLOBAL | C6: 深度關係投入 ↔ 自主決策 | D6: — | E6: ABSOLUTE SEMANTIC | F6: — | G6: — | J6: 0 | L6: 0 | M6: 0.5 | N6: 0 | O6: 0 | P6: 0 | Q6: 0 | R6: 0 | S6: 0 | T6: -0.5 | U6: 0 | V6: 0 | W6: 0 | X6: 0 | Y6: 0 | Z6: 0 | AA6: 0 | AB6: 0 | AC6: 0 | AD6: 0 | AE6: 0 | AF6: 0 | AG6: 0 | AH6: 0 | AI6: 0 | AJ6: 0 | AK6: 0 | AL6: 0 | AM6: 0 | AN6: 0 | AO6: 0 | AP6: 0 | AQ6: 0 | AR6: 0 | AS6: 0 | AT6: 0 | AU6: 0 | AV6: 0 | AW6: 0 | AX6: 0 | AY6: 0 | AZ6: 0
A7: G03 | B7: GLOBAL | C7: 審美感官介入 ↔ 機制系統解法 | D7: — | E7: ABSOLUTE SEMANTIC | F7: — | G7: — | J7: 0 | L7: 0 | M7: 0 | N7: 0.5 | O7: 0 | P7: -0.5 | Q7: 0 | R7: 0 | S7: 0 | T7: 0 | U7: 0 | V7: 0 | W7: 0 | X7: 0 | Y7: 0 | Z7: 0 | AA7: 0 | AB7: 0 | AC7: 0 | AD7: 0 | AE7: 0 | AF7: 0 | AG7: 0 | AH7: 0 | AI7: 0 | AJ7: 0 | AK7: 0 | AL7: 0 | AM7: 0 | AN7: 0 | AO7: 0 | AP7: 0 | AQ7: 0 | AR7: 0 | AS7: 0 | AT7: 0 | AU7: 0 | AV7: 0 | AW7: 0 | AX7: 0 | AY7: 0 | AZ7: 0
A8: G04 | B8: GLOBAL | C8: 高驗證需求 ↔ 先採用暫時性直覺/經驗 | D8: — | E8: ABSOLUTE SEMANTIC | F8: — | G8: — | J8: 0 | L8: 0 | M8: 0 | N8: 0 | O8: 1 | P8: 0 | Q8: 0 | R8: 0 | S8: 0 | T8: 0 | U8: 0 | V8: 0 | W8: 0 | X8: 0 | Y8: 0 | Z8: 0 | AA8: 0 | AB8: 0 | AC8: 0 | AD8: 0 | AE8: 0 | AF8: 0 | AG8: 0 | AH8: 0 | AI8: 0 | AJ8: 0 | AK8: 0 | AL8: 0 | AM8: 0 | AN8: 0 | AO8: 0 | AP8: 0 | AQ8: 0 | AR8: 0 | AS8: 0 | AT8: 0 | AU8: 0 | AV8: 0 | AW8: 0 | AX8: 0 | AY8: 0 | AZ8: 0
A9: G05 | B9: GLOBAL | C9: 機制系統建模 ↔ 情緒場讀取 | D9: — | E9: ABSOLUTE SEMANTIC | F9: — | G9: — | J9: 0 | L9: -0.5 | M9: 0 | N9: 0 | O9: 0 | P9: 0.5 | Q9: 0 | R9: 0 | S9: 0 | T9: 0 | U9: 0 | V9: 0 | W9: 0 | X9: 0 | Y9: 0 | Z9: 0 | AA9: 0 | AB9: 0 | AC9: 0 | AD9: 0 | AE9: 0 | AF9: 0 | AG9: 0 | AH9: 0 | AI9: 0 | AJ9: 0 | AK9: 0 | AL9: 0 | AM9: 0 | AN9: 0 | AO9: 0 | AP9: 0 | AQ9: 0 | AR9: 0 | AS9: 0 | AT9: 0 | AU9: 0 | AV9: 0 | AW9: 0 | AX9: 0 | AY9: 0 | AZ9: 0
A10: G06 | B10: GLOBAL | C10: 長期持續 ↔ 快速啟動 | D10: — | E10: ABSOLUTE SEMANTIC | F10: — | G10: — | J10: 0 | L10: 0 | M10: 0 | N10: 0 | O10: 0 | P10: 0 | Q10: 0.5 | R10: 0 | S10: 0 | T10: 0 | U10: 0 | V10: -0.5 | W10: 0 | X10: 0 | Y10: 0 | Z10: 0 | AA10: 0 | AB10: 0 | AC10: 0 | AD10: 0 | AE10: 0 | AF10: 0 | AG10: 0 | AH10: 0 | AI10: 0 | AJ10: 0 | AK10: 0 | AL10: 0 | AM10: 0 | AN10: 0 | AO10: 0 | AP10: 0 | AQ10: 0 | AR10: 0 | AS10: 0 | AT10: 0 | AU10: 0 | AV10: 0 | AW10: 0 | AX10: 0 | AY10: 0 | AZ10: 0
A11: G07 | B11: GLOBAL | C11: 宏觀視角 ↔ 局部/地面視角 | D11: — | E11: ABSOLUTE SEMANTIC | F11: — | G11: — | J11: 0 | L11: 0 | M11: 0 | N11: 0 | O11: 0 | P11: 0 | Q11: 0 | R11: 1 | S11: 0 | T11: 0 | U11: 0 | V11: 0 | W11: 0 | X11: 0 | Y11: 0 | Z11: 0 | AA11: 0 | AB11: 0 | AC11: 0 | AD11: 0 | AE11: 0 | AF11: 0 | AG11: 0 | AH11: 0 | AI11: 0 | AJ11: 0 | AK11: 0 | AL11: 0 | AM11: 0 | AN11: 0 | AO11: 0 | AP11: 0 | AQ11: 0 | AR11: 0 | AS11: 0 | AT11: 0 | AU11: 0 | AV11: 0 | AW11: 0 | AX11: 0 | AY11: 0 | AZ11: 0
A12: G08 | B12: GLOBAL | C12: 探索移動 ↔ 扎根延續 | D12: — | E12: ABSOLUTE SEMANTIC | F12: — | G12: — | J12: 0 | L12: 0 | M12: 0 | N12: 0 | O12: 0 | P12: 0 | Q12: 0 | R12: 0 | S12: 0 | T12: 0 | U12: 0 | V12: 0 | W12: 0 | X12: 0 | Y12: 0 | Z12: 0 | AA12: 0 | AB12: 0 | AC12: 0 | AD12: 0 | AE12: 1 | AF12: 0 | AG12: 0 | AH12: 0 | AI12: 0 | AJ12: 0 | AK12: 0 | AL12: 0 | AM12: 0 | AN12: 0 | AO12: 0 | AP12: 0 | AQ12: 0 | AR12: 0 | AS12: 0 | AT12: 0 | AU12: 0 | AV12: 0 | AW12: 0 | AX12: 0 | AY12: 0 | AZ12: 0
A13: G09 | B13: GLOBAL | C13: 自主決策 ↔ 接受協調約束/角色義務 | D13: — | E13: ABSOLUTE SEMANTIC | F13: — | G13: — | J13: 0 | L13: 0 | M13: 0 | N13: 0 | O13: 0 | P13: 0 | Q13: 0 | R13: 0 | S13: 0 | T13: 1 | U13: 0 | V13: 0 | W13: 0 | X13: 0 | Y13: 0 | Z13: 0 | AA13: 0 | AB13: 0 | AC13: 0 | AD13: 0 | AE13: 0 | AF13: 0 | AG13: 0 | AH13: 0 | AI13: 0 | AJ13: 0 | AK13: 0 | AL13: 0 | AM13: 0 | AN13: 0 | AO13: 0 | AP13: 0 | AQ13: 0 | AR13: 0 | AS13: 0 | AT13: 0 | AU13: 0 | AV13: 0 | AW13: 0 | AX13: 0 | AY13: 0 | AZ13: 0
A14: G10 | B14: GLOBAL | C14: 集中指揮 ↔ 分散共治 | D14: — | E14: ABSOLUTE SEMANTIC | F14: — | G14: — | J14: 0 | L14: 0 | M14: 0 | N14: 0 | O14: 0 | P14: 0 | Q14: 0 | R14: 0 | S14: 0 | T14: 0 | U14: 1 | V14: 0 | W14: 0 | X14: 0 | Y14: 0 | Z14: 0 | AA14: 0 | AB14: 0 | AC14: 0 | AD14: 0 | AE14: 0 | AF14: 0 | AG14: 0 | AH14: 0 | AI14: 0 | AJ14: 0 | AK14: 0 | AL14: 0 | AM14: 0 | AN14: 0 | AO14: 0 | AP14: 0 | AQ14: 0 | AR14: 0 | AS14: 0 | AT14: 0 | AU14: 0 | AV14: 0 | AW14: 0 | AX14: 0 | AY14: 0 | AZ14: 0
A15: G11 | B15: GLOBAL | C15: 立即啟動 ↔ 先觀察延後 | D15: — | E15: ABSOLUTE SEMANTIC | F15: — | G15: — | J15: 0 | L15: 0 | M15: 0 | N15: 0 | O15: 0 | P15: 0 | Q15: 0 | R15: 0 | S15: 0 | T15: 0 | U15: 0 | V15: 1 | W15: 0 | X15: 0 | Y15: 0 | Z15: 0 | AA15: 0 | AB15: 0 | AC15: 0 | AD15: 0 | AE15: 0 | AF15: 0 | AG15: 0 | AH15: 0 | AI15: 0 | AJ15: 0 | AK15: 0 | AL15: 0 | AM15: 0 | AN15: 0 | AO15: 0 | AP15: 0 | AQ15: 0 | AR15: 0 | AS15: 0 | AT15: 0 | AU15: 0 | AV15: 0 | AW15: 0 | AX15: 0 | AY15: 0 | AZ15: 0
A16: G12 | B16: GLOBAL | C16: 直接處理衝突 ↔ 間接/降溫處理 | D16: — | E16: ABSOLUTE SEMANTIC | F16: — | G16: — | J16: 0 | L16: 0 | M16: 0 | N16: 0 | O16: 0 | P16: 0 | Q16: 0 | R16: 0 | S16: 0 | T16: 0 | U16: 0 | V16: 0 | W16: 1 | X16: 0 | Y16: 0 | Z16: 0 | AA16: 0 | AB16: 0 | AC16: 0 | AD16: 0 | AE16: 0 | AF16: 0 | AG16: 0 | AH16: 0 | AI16: 0 | AJ16: 0 | AK16: 0 | AL16: 0 | AM16: 0 | AN16: 0 | AO16: 0 | AP16: 0 | AQ16: 0 | AR16: 0 | AS16: 0 | AT16: 0 | AU16: 0 | AV16: 0 | AW16: 0 | AX16: 0 | AY16: 0 | AZ16: 0
... A33: G29 | B33: GLOBAL | C33: 協作/整合 ↔ 直接衝突 | D33: — | E33: ABSOLUTE SEMANTIC | F33: — | G33: — | J33: 0 | L33: 0 | M33: 0 | N33: 0 | O33: 0 | P33: 0 | Q33: 0 | R33: 0 | S33: 0 | T33: 0 | U33: 0 | V33: 0 | W33: -0.33333333 | X33: 0 | Y33: 0.33333333 | Z33: 0 | AA33: 0 | AB33: 0 | AC33: 0 | AD33: 0 | AE33: 0 | AF33: 0.33333333 | AG33: 0 | AH33: 0 | AI33: 0 | AJ33: 0 | AK33: 0 | AL33: 0 | AM33: 0 | AN33: 0 | AO33: 0 | AP33: 0 | AQ33: 0 | AR33: 0 | AS33: 0 | AT33: 0 | AU33: 0 | AV33: 0 | AW33: 0 | AX33: 0 | AY33: 0 | AZ33: 0
A34: G30 | B34: GLOBAL | C34: 立即啟動/正面破局 ↔ 先掃描風險並情境適應 | D34: Martian ↔ Reptilian | E34: COMPARATIVE CENTERED | F34: Martian | G34: Reptilian | H34: 0.66666667 | I34: 0 | J34: 0.33333333 | K34: 0.66666667 | L34: 0 | M34: 0 | N34: 0 | O34: 0 | P34: 0 | Q34: 0 | R34: 0 | S34: 0 | T34: 0 | U34: 0 | V34: 0.33333333 | W34: 0.33333333 | X34: -0.33333333 | Y34: 0 | Z34: 0 | AA34: 0 | AB34: 0 | AC34: 0 | AD34: 0 | AE34: 0 | AF34: 0 | AG34: 0 | AH34: 0 | AI34: 0 | AJ34: 0 | AK34: 0 | AL34: 0 | AM34: 0 | AN34: 0 | AO34: 0 | AP34: 0 | AQ34: 0 | AR34: 0 | AS34: 0 | AT34: 0 | AU34: 0 | AV34: 0 | AW34: 0 | AX34: 0 | AY34: 0 | AZ34: 0
A35: L01 | B35: LOCAL | C35: 情緒場 holding ↔ 美感/氛圍介入 | D35: Pleiadian ↔ Venusian | E35: COMPARATIVE CENTERED | F35: Pleiadian | G35: Venusian | H35: 0.5 | I35: -0.5 | J35: 0 | K35: 1 | L35: 0.5 | M35: 0 | N35: -0.5 | O35: 0 | P35: 0 | Q35: 0 | R35: 0 | S35: 0 | T35: 0 | U35: 0 | V35: 0 | W35: 0 | X35: 0 | Y35: 0 | Z35: 0 | AA35: 0 | AB35: 0 | AC35: 0 | AD35: 0 | AE35: 0 | AF35: 0 | AG35: 0 | AH35: 0 | AI35: 0 | AJ35: 0 | AK35: 0 | AL35: 0 | AM35: 0 | AN35: 0 | AO35: 0 | AP35: 0 | AQ35: 0 | AR35: 0 | AS35: 0 | AT35: 0 | AU35: 0 | AV35: 0 | AW35: 0 | AX35: 0 | AY35: 0 | AZ35: 0
A36: L02 | B36: LOCAL | C36: 廣域情緒場照護 ↔ 深度 dyadic trust/bond repair | D36: Pleiadian ↔ Hadarian | E36: COMPARATIVE CENTERED | F36: Pleiadian | G36: Hadarian | H36: 0.25 | I36: -0.5 | J36: -0.125 | K36: 0.75 | L36: 0.5 | M36: -0.25 | N36: 0 | O36: 0 | P36: 0 | Q36: 0 | R36: 0 | S36: 0 | T36: 0 | U36: 0 | V36: 0 | W36: 0 | X36: 0.25 | Y36: 0 | Z36: 0 | AA36: 0 | AB36: 0 | AC36: 0 | AD36: 0 | AE36: 0 | AF36: 0 | AG36: 0 | AH36: 0 | AI36: 0 | AJ36: 0 | AK36: 0 | AL36: 0 | AM36: 0 | AN36: 0 | AO36: 0 | AP36: 0 | AQ36: 0 | AR36: 0 | AS36: 0 | AT36: 0 | AU36: 0 | AV36: 0 | AW36: 0 | AX36: 0 | AY36: 0 | AZ36: 0
A37: L03 | B37: LOCAL | C37: 當下情緒場修復 ↔ lost-sanctuary / elsewhere-home restoration | D37: Pleiadian ↔ Mintakan | E37: COMPARATIVE CENTERED | F37: Pleiadian | G37: Mintakan | H37: 0.33333333 | I37: -0.66666667 | J37: -0.16666667 | K37: 1 | L37: 0.33333333 | M37: 0 | N37: 0 | O37: 0 | P37: 0 | Q37: 0 | R37: 0 | S37: 0 | T37: 0 | U37: 0 | V37: 0 | W37: 0 | X37: 0 | Y37: 0 | Z37: 0 | AA37: 0 | AB37: 0 | AC37: 0 | AD37: 0 | AE37: 0 | AF37: 0 | AG37: 0.33333333 | AH37: -0.33333333 | AI37: 0 | AJ37: 0 | AK37: 0 | AL37: 0 | AM37: 0 | AN37: 0 | AO37: 0 | AP37: 0 | AQ37: 0 | AR37: 0 | AS37: 0 | AT37: 0 | AU37: 0 | AV37: 0 | AW37: 0 | AX37: 0 | AY37: 0 | AZ37: 0
A38: L04 | B38: LOCAL | C38: 審美感官介入 ↔ 深度 devotion/trust repair | D38: Venusian ↔ Hadarian | E38: COMPARATIVE CENTERED | F38: Venusian | G38: Hadarian | H38: 0.25 | I38: -0.5 | J38: -0.125 | K38: 0.75 | L38: 0 | M38: -0.25 | N38: 0.5 | O38: 0 | P38: 0 | Q38: 0 | R38: 0 | S38: 0 | T38: 0 | U38: 0 | V38: 0 | W38: 0 | X38: 0.25 | Y38: 0 | Z38: 0 | AA38: 0 | AB38: 0 | AC38: 0 | AD38: 0 | AE38: 0 | AF38: 0 | AG38: 0 | AH38: 0 | AI38: 0 | AJ38: 0 | AK38: 0 | AL38: 0 | AM38: 0 | AN38: 0 | AO38: 0 | AP38: 0 | AQ38: 0 | AR38: 0 | AS38: 0 | AT38: 0 | AU38: 0 | AV38: 0 | AW38: 0 | AX38: 0 | AY38: 0 | AZ38: 0
A39: L05 | B39: LOCAL | C39: 審美感官豐富度 ↔ pristine/simple sanctuary restoration | D39: Mintakan ↔ Venusian | E39: COMPARATIVE CENTERED | F39: Venusian | G39: Mintakan | H39: 0.33333333 | I39: -0.66666667 | J39: -0.16666667 | K39: 1 | L39: 0 | M39: 0 | N39: 0.33333333 | O39: 0 | P39: 0 | Q39: 0 | R39: 0 | S39: 0 | T39: 0 | U39: 0 | V39: 0 | W39: 0 | X39: 0 | Y39: 0 | Z39: 0 | AA39: 0 | AB39: 0 | AC39: 0 | AD39: 0 | AE39: 0 | AF39: 0 | AG39: 0.33333333 | AH39: -0.33333333 | AI39: 0 | AJ39: 0 | AK39: 0 | AL39: 0 | AM39: 0 | AN39: 0 | AO39: 0 | AP39: 0 | AQ39: 0 | AR39: 0 | AS39: 0 | AT39: 0 | AU39: 0 | AV39: 0 | AW39: 0 | AX39: 0 | AY39: 0 | AZ39: 0
A40: L06 | B40: LOCAL | C40: 深度 dyadic devotion ↔ lost-sanctuary restoration | D40: Mintakan ↔ Hadarian | E40: COMPARATIVE CENTERED | F40: Hadarian | G40: Mintakan | H40: 0.2 | I40: -0.7 | J40: -0.25 | K40: 0.9 | L40: 0 | M40: 0.2 | N40: 0 | O40: 0 | P40: 0 | Q40: 0 | R40: 0 | S40: 0 | T40: 0 | U40: 0 | V40: 0 | W40: 0 | X40: 0 | Y40: 0 | Z40: 0 | AA40: 0 | AB40: 0 | AC40: 0 | AD40: 0 | AE40: 0 | AF40: 0 | AG40: 0.4 | AH40: -0.4 | AI40: 0 | AJ40: 0 | AK40: 0 | AL40: 0 | AM40: 0 | AN40: 0 | AO40: 0 | AP40: 0 | AQ40: 0 | AR40: 0 | AS40: 0 | AT40: 0 | AU40: 0 | AV40: 0 | AW40: 0 | AX40: 0 | AY40: 0 | AZ40: 0
A41: L07 | B41: LOCAL | C41: person/bond-centered ↔ aesthetic/sanctuary-centered | D41: Venusian ↔ Hadarian | E41: COMPARATIVE CENTERED | F41: Hadarian | G41: Venusian | H41: 0.33333333 | I41: -0.5 | J41: -0.083333333 | K41: 0.83333333 | L41: 0 | M41: 0.33333333 | N41: -0.66666667 | O41: 0 | P41: 0 | Q41: 0 | R41: 0 | S41: 0 | T41: 0 | U41: 0 | V41: 0 | W41: 0 | X41: 0 | Y41: 0 | Z41: 0 | AA41: 0 | AB41: 0 | AC41: 0 | AD41: 0 | AE41: 0 | AF41: 0 | AG41: 0 | AH41: 0 | AI41: 0 | AJ41: 0 | AK41: 0 | AL41: 0 | AM41: 0 | AN41: 0 | AO41: 0 | AP41: 0 | AQ41: 0 | AR41: 0 | AS41: 0 | AT41: 0 | AU41: 0 | AV41: 0 | AW41: 0 | AX41: 0 | AY41: 0 | AZ41: 0
A42: L08 | B42: LOCAL | C42: 改變/離開限制 frame 以獲得自由 ↔ 在開放空間中跨域創造/組合 | D42: Andromedan ↔ Vegan | E42: COMPARATIVE CENTERED | F42: Andromedan | G42: Vegan | H42: 0.25 | I42: -0.25 | J42: 0 | K42: 0.5 | L42: 0 | M42: 0 | N42: -0.25 | O42: -0.25 | P42: 0 | Q42: 0 | R42: 0.25 | S42: 0 | T42: 0 | U42: 0 | V42: 0 | W42: 0 | X42: 0 | Y42: 0 | Z42: 0 | AA42: 0 | AB42: 0 | AC42: 0 | AD42: 0 | AE42: 0 | AF42: -0.25 | AG42: 0 | AH42: 0 | AI42: 0 | AJ42: 0 | AK42: 0 | AL42: 0 | AM42: 0 | AN42: 0 | AO42: 0 | AP42: 0 | AQ42: 0 | AR42: 0 | AS42: 0 | AT42: 0 | AU42: 0 | AV42: 0 | AW42: 0 | AX42: 0 | AY42: 0 | AZ42: 0
A43: L09 | B43: LOCAL | C43: coherence restoration/結構介入 ↔ 自主 creative-intellectual exploration | D43: Arcturian ↔ Vegan | E43: COMPARATIVE CENTERED | F43: Arcturian | G43: Vegan | H43: 0.125 | I43: -0.375 | J43: -0.125 | K43: 0.5 | L43: 0 | M43: 0 | N43: 0 | O43: 0 | P43: 0 | Q43: 0 | R43: 0 | S43: 0 | T43: -0.25 | U43: 0 | V43: 0 | W43: 0 | X43: 0 | Y43: 0 | Z43: 0 | AA43: 0.25 | AB43: 0 | AC43: 0.25 | AD43: 0 | AE43: -0.25 | AF43: 0 | AG43: 0 | AH43: 0 | AI43: 0 | AJ43: 0 | AK43: 0 | AL43: 0 | AM43: 0 | AN43: 0 | AO43: 0 | AP43: 0 | AQ43: 0 | AR43: 0 | AS43: 0 | AT43: 0 | AU43: 0 | AV43: 0 | AW43: 0 | AX43: 0 | AY43: 0 | AZ43: 0
A44: L10 | B44: LOCAL | C44: 可靠 practical implementation ↔ skeptical risk-depth / hidden-failure stewardship | D44: Alpha Centaurian ↔ Maldekian | E44: COMPARATIVE CENTERED | F44: Alpha Centaurian | G44: Maldekian | H44: 0 | I44: -0.78571429 | J44: -0.39285714 | K44: 0.78571429 | L44: 0 | M44: 0 | N44: 0 | O44: -0.14285714 | P44: 0.14285714 | Q44: -0.14285714 | R44: 0 | S44: 0 | T44: 0 | U44: 0 | V44: 0 | W44: 0 | X44: -0.28571429 | Y44: 0 | Z44: -0.28571429 | AA44: 0 | AB44: 0 | AC44: 0 | AD44: 0 | AE44: 0 | AF44: 0 | AG44: 0 | AH44: 0 | AI44: 0 | AJ44: 0 | AK44: 0 | AL44: 0 | AM44: 0 | AN44: 0 | AO44: 0 | AP44: 0 | AQ44: 0 | AR44: 0 | AS44: 0 | AT44: 0 | AU44: 0 | AV44: 0 | AW44: 0 | AX44: 0 | AY44: 0 | AZ44: 0
A45: L11 | B45: LOCAL | C45: 證據/真理 interrogation ↔ 高 scope translation/messenger | D45: Orion ↔ Avian / Blue Avian | E45: COMPARATIVE CENTERED | F45: Orion | G45: Avian / Blue Avian | H45: 0.35714286 | I45: -0.57142857 | J45: -0.10714286 | K45: 0.92857143 | L45: 0 | M45: 0 | N45: 0 | O45: 0.28571429 | P45: 0 | Q45: 0 | R45: -0.14285714 | S45: 0 | T45: 0 | U45: 0 | V45: 0 | W45: 0.28571429 | X45: 0 | Y45: 0 | Z45: 0 | AA45: 0 | AB45: 0 | AC45: 0 | AD45: 0 | AE45: -0.28571429 | AF45: 0 | AG45: 0 | AH45: 0 | AI45: 0 | AJ45: 0 | AK45: 0 | AL45: 0 | AM45: 0 | AN45: 0 | AO45: 0 | AP45: 0 | AQ45: 0 | AR45: 0 | AS45: 0 | AT45: 0 | AU45: 0 | AV45: 0 | AW45: 0 | AX45: 0 | AY45: 0 | AZ45: 0
... A84: A12 | B84: ANCHOR | C84: operational command ↔ civilization-scale institution architecture | D84: Draconian ↔ Anunnaki / Nibiruan | E84: COMPARATIVE CENTERED | F84: Draconian | G84: Anunnaki / Nibiruan | H84: -0.125 | I84: -0.625 | J84: -0.375 | K84: 0.5 | L84: 0 | M84: 0 | N84: 0 | O84: 0 | P84: -0.25 | Q84: 0 | R84: -0.25 | S84: 0 | T84: 0 | U84: 0 | V84: 0 | W84: 0 | X84: 0 | Y84: 0 | Z84: 0 | AA84: 0 | AB84: 0.25 | AC84: -0.25 | AD84: 0 | AE84: 0 | AF84: 0 | AG84: 0 | AH84: 0 | AI84: 0 | AJ84: 0 | AK84: 0 | AL84: 0 | AM84: 0 | AN84: 0 | AO84: 0 | AP84: 0 | AQ84: 0 | AR84: 0 | AS84: 0 | AT84: 0 | AU84: 0 | AV84: 0 | AW84: 0 | AX84: 0 | AY84: 0 | AZ84: 0

Sheet 07_CONTINUOUS_CODEBOOK
A1: 23×80 Continuous Canonical Scores
A2: Pre-quantization values in [-1,+1]. These are the exact numeric outputs of the frozen pole model.
A4: # | B4: 中文 | C4: English | D4: G01 | E4: G02 | F4: G03 | G4: G04 | H4: G05 | I4: G06 | J4: G07 | K4: G08 | L4: G09 | M4: G10 | N4: G11 | O4: G12 | P4: G13 | Q4: G14 | R4: G15 | S4: G16 | T4: G17 | U4: G18 | V4: G19 | W4: G20 | X4: G21 | Y4: G22 | Z4: G23 | AA4: G24 | AB4: G25 | AC4: G26 | AD4: G27 | AE4: G28 | AF4: G29 | AG4: G30 | AH4: L01 | AI4: L02 | AJ4: L03 | AK4: L04 | AL4: L05 | AM4: L06 | AN4: L07 | AO4: L08 | AP4: L09 | AQ4: L10 | AR4: L11 | AS4: L12 | AT4: L13 | AU4: L14 | AV4: L15 | AW4: L16 | AX4: L17 | AY4: L18 | AZ4: L19 | BA4: L20 | BB4: L21 | BC4: L22 | BD4: L23 | BE4: L24 | BF4: L25 | BG4: L26 | BH4: L27 | BI4: L28 | BJ4: L29 | BK4: L30 | BL4: L31 | BM4: L32 | BN4: L33 | BO4: L34 | BP4: L35 | BQ4: L36 | BR4: L37 | BS4: L38 | BT4: A01 | BU4: A02 | BV4: A03 | BW4: A04 | BX4: A05 | BY4: A06 | BZ4: A07 | CA4: A08 | CB4: A09 | CC4: A10 | CD4: A11 | CE4: A12
A5: 1 | B5: 昴宿星人 | C5: Pleiadian | D5: 0.75 | E5: 0.25 | F5: 0.25 | G5: -0.5 | H5: -0.75 | I5: 0.25 | J5: 0 | K5: 0 | L5: 0 | M5: 0 | N5: -0.5 | O5: -1 | P5: -0.5 | Q5: 0.5 | R5: -0.5 | S5: 0.75 | T5: 0 | U5: 0 | V5: 0.25 | W5: 0 | X5: 0 | Y5: 0 | Z5: 0.25 | AA5: 0.5 | AB5: 0 | AC5: -0.25 | AD5: 0 | AE5: 0 | AF5: 0.5 | AG5: -1 | AH5: 0.85 | AI5: 0.6375 | AJ5: 0.85 | AK5: -0.2125 | AL5: 0.28333333 | AM5: 0.595 | AN5: 0.425 | AO5: 0.2125 | AP5: 0.6375 | AQ5: 1 | AR5: -0.54642857 | AS5: 0.85 | AT5: -0.060714286 | AU5: 0.56666667 | AV5: -0.30357143 | AW5: -0.10625 | AX5: -0.425 | AY5: 0.085 | AZ5: -0.14166667 | BA5: 0.085 | BB5: -0.425 | BC5: 0.14166667 | BD5: 0.30357143 | BE5: 0.85 | BF5: -0.18214286 | BG5: 0.30357143 | BH5: -0.255 | BI5: -0.14166667 | BJ5: 0.2125 | BK5: -0.935 | BL5: -0.56666667 | BM5: -0.060714286 | BN5: -0.425 | BO5: 0.2125 | BP5: -0.425 | BQ5: 0.425 | BR5: 0.255 | BS5: 0.70833333 | BT5: -0.85 | BU5: 1 | BV5: -0.425 | BW5: -0.56666667 | BX5: -1 | BY5: -0.85 | BZ5: -0.6375 | CA5: -0.28333333 | CB5: -1 | CC5: 0 | CD5: -0.44431818 | CE5: 0.85
A6: 2 | B6: 大角星人 | C6: Arcturian | D6: -0.25 | E6: -0.5 | F6: -0.25 | G6: 0 | H6: 0.5 | I6: -0.25 | J6: 0.5 | K6: 0.5 | L6: 0.5 | M6: 0 | N6: 0.5 | O6: 0 | P6: 0 | Q6: 0 | R6: 0 | S6: 0.25 | T6: -0.33333333 | U6: 0 | V6: -0.25 | W6: 0 | X6: 0.5 | Y6: 0 | Z6: -0.5 | AA6: -0.16666667 | AB6: -0.25 | AC6: 0.25 | AD6: -0.25 | AE6: 0.25 | AF6: 0.16666667 | AG6: -0.28333333 | AH6: -0.425 | AI6: 0 | AJ6: 0 | AK6: 0.425 | AL6: 0.28333333 | AM6: 0.255 | AN6: -0.14166667 | AO6: 0 | AP6: 0.425 | AQ6: 0.78928571 | AR6: -0.18214286 | AS6: 0.425 | AT6: -0.66785714 | AU6: 0.14166667 | AV6: -0.18214286 | AW6: 0.53125 | AX6: 0 | AY6: -0.595 | AZ6: 0 | BA6: -0.425 | BB6: -0.425 | BC6: 0.425 | BD6: -0.30357143 | BE6: 0 | BF6: -0.30357143 | BG6: -0.30357143 | BH6: -0.085 | BI6: -0.56666667 | BJ6: 0 | BK6: -0.765 | BL6: 4.7184479e-17 | BM6: -0.66785714 | BN6: 0.425 | BO6: 0 | BP6: 0.085 | BQ6: 0.255 | BR6: 0.765 | BS6: 0.99166667 | BT6: -0.85 | BU6: 0.935 | BV6: -0.425 | BW6: -0.28333333 | BX6: -0.60916667 | BY6: 0.425 | BZ6: 0 | CA6: -0.56666667 | CB6: -0.6375 | CC6: 0 | CD6: -0.67613636 | CE6: 0
A7: 3 | B7: 天狼星人 | C7: Sirian | D7: 0 | E7: 0.5 | F7: 0 | G7: 0 | H7: 0 | I7: 0.5 | J7: 0 | K7: -0.5 | L7: -0.5 | M7: 0 | N7: 0 | O7: -0.5 | P7: 1 | Q7: 0 | R7: 0.5 | S7: 0.25 | T7: 0.66666667 | U7: 0.5 | V7: 0 | W7: 0 | X7: 0 | Y7: 0.125 | Z7: 0.25 | AA7: -0.66666667 | AB7: 0.25 | AC7: 0 | AD7: 0.75 | AE7: -0.75 | AF7: 0.16666667 | AG7: -1 | AH7: 0 | AI7: 0.425 | AJ7: 0.28333333 | AK7: 0.425 | AL7: 0.28333333 | AM7: 0.595 | AN7: 0.425 | AO7: 0 | AP7: 1 | AQ7: -0.30357143 | AR7: 0.18214286 | AS7: 0.85 | AT7: 0.30357143 | AU7: 0.14166667 | AV7: 0.30357143 | AW7: -0.425 | AX7: -1 | AY7: 0.595 | AZ7: 0.70833333 | BA7: 0.255 | BB7: 0.6375 | BC7: -0.28333333 | BD7: -0.425 | BE7: 0.85 | BF7: 0.425 | BG7: -0.425 | BH7: -0.085 | BI7: 0.56666667 | BJ7: 0 | BK7: 0.765 | BL7: -0.56666667 | BM7: 0.30357143 | BN7: -0.85 | BO7: 0 | BP7: -0.425 | BQ7: 0.085 | BR7: 0.595 | BS7: 0.70833333 | BT7: -0.56666667 | BU7: -0.085 | BV7: 0.99166667 | BW7: 0.56666667 | BX7: -0.49583333 | BY7: 0 | BZ7: -0.425 | CA7: 0.425 | CB7: -1 | CC7: 0 | CD7: 0.096590909 | CE7: 0.85
A8: 4 | B8: 仙女座人 | C8: Andromedan | D8: 0 | E8: -0.5 | F8: 0.25 | G8: 0 | H8: -0.25 | I8: -0.5 | J8: 1 | K8: 1 | L8: 1 | M8: -0.5 | N8: 0.5 | O8: 0 | P8: 0 | Q8: 0 | R8: 0 | S8: 0.5 | T8: -0.66666667 | U8: -0.5 | V8: 0.25 | W8: 0 | X8: 0 | Y8: -0.125 | Z8: -0.5 | AA8: 0 | AB8: 0 | AC8: 0 | AD8: -0.75 | AE8: 0.5 | AF8: 0 | AG8: -0.28333333 | AH8: 0 | AI8: 0.2125 | AJ8: 0.28333333 | AK8: 0.2125 | AL8: 0.28333333 | AM8: 0.425 | AN8: 0.14166667 | AO8: 0.425 | AP8: -0.425 | AQ8: 0.66785714 | AR8: -0.54642857 | AS8: 0.425 | AT8: -0.30357143 | AU8: 0.28333333 | AV8: -0.18214286 | AW8: 0.31875 | AX8: 0 | AY8: -0.595 | AZ8: -0.70833333 | BA8: -0.595 | BB8: -1 | BC8: 0.14166667 | BD8: 0.18214286 | BE8: 0.425 | BF8: -0.425 | BG8: 0.18214286 | BH8: -0.425 | BI8: -0.70833333 | BJ8: 0.425 | BK8: -0.595 | BL8: 0.56666667 | BM8: -0.30357143 | BN8: 0.425 | BO8: 0.425 | BP8: 0.595 | BQ8: 0.595 | BR8: 0.595 | BS8: 1 | BT8: -0.85 | BU8: 0.935 | BV8: -0.425 | BW8: -0.85 | BX8: -0.60916667 | BY8: 0 | BZ8: -0.2125 | CA8: -0.56666667 | CB8: -0.88035714 | CC8: 0 | CD8: -0.52159091 | CE8: 0.425
A9: 5 | B9: 天琴座人 | C9: Lyran | D9: -0.25 | E9: -0.5 | F9: 0 | G9: 0 | H9: 0.25 | I9: -0.5 | J9: 0.5 | K9: 0 | L9: 1 | M9: 0 | N9: 1 | O9: 0.5 | P9: 0 | Q9: -0.5 | R9: 0 | S9: 0 | T9: -0.16666667 | U9: 0.5 | V9: -0.5 | W9: 0 | X9: -0.5 | Y9: 0.125 | Z9: -0.25 | AA9: -0.33333333 | AB9: -0.25 | AC9: 0 | AD9: 0 | AE9: 0.25 | AF9: -0.5 | AG9: 0.28333333 | AH9: -0.425 | AI9: -0.2125 | AJ9: 0 | AK9: 0.2125 | AL9: 0.28333333 | AM9: 0.425 | AN9: 0.14166667 | AO9: 0.425 | AP9: 0.2125 | AQ9: 0.66785714 | AR9: 0.30357143 | AS9: 0.425 | AT9: -0.30357143 | AU9: -0.14166667 | AV9: -0.18214286 | AW9: 0.95625 | AX9: 0.425 | AY9: -1 | AZ9: 0.70833333 | BA9: -0.595 | BB9: -0.6375 | BC9: 0.70833333 | BD9: 0.18214286 | BE9: 0.2125 | BF9: -0.425 | BG9: 0.18214286 | BH9: -0.085 | BI9: 0.425 | BJ9: 0.425 | BK9: -0.765 | BL9: 4.7184479e-17 | BM9: -0.30357143 | BN9: 0.85 | BO9: 0.425 | BP9: 0.085 | BQ9: 0.255 | BR9: 1 | BS9: 0.99166667 | BT9: -0.85 | BU9: 0.935 | BV9: -0.70833333 | BW9: -0.28333333 | BX9: -0.26916667 | BY9: 0.425 | BZ9: 0.2125 | CA9: 0.425 | CB9: -0.6375 | CC9: 0 | CD9: -0.98522727 | CE9: 0.2125
A10: 6 | B10: 獵戶座人 | C10: Orion | D10: -0.75 | E10: -0.25 | F10: 0 | G10: 1 | H10: 0.25 | I10: 0.25 | J10: 0.5 | K10: 0 | L10: 0 | M10: 0 | N10: -0.5 | O10: 0.5 | P10: 0.5 | Q10: 0 | R10: 0.5 | S10: 0 | T10: 0 | U10: 0 | V10: 0.5 | W10: 0 | X10: 1 | Y10: -0.125 | Z10: -0.5 | AA10: -0.33333333 | AB10: 0 | AC10: 0 | AD10: 0 | AE10: 0 | AF10: 0.16666667 | AG10: -0.85 | AH10: -0.425 | AI10: 0.2125 | AJ10: 0 | AK10: 0.6375 | AL10: 0.28333333 | AM10: 0.255 | AN10: -0.14166667 | AO10: -0.6375 | AP10: 0.2125 | AQ10: -0.060714286 | AR10: 0.78928571 | AS10: 0.425 | AT10: 0.18214286 | AU10: 0.56666667 | AV10: 0.425 | AW10: -0.53125 | AX10: -0.6375 | AY10: 0.765 | AZ10: -0.28333333 | BA10: 0.085 | BB10: 0 | BC10: -0.425 | BD10: -0.425 | BE10: 0.425 | BF10: 0.30357143 | BG10: -0.425 | BH10: 0.085 | BI10: -0.56666667 | BJ10: -0.6375 | BK10: -0.085 | BL10: 4.7184479e-17 | BM10: 0.18214286 | BN10: -0.85 | BO10: -0.6375 | BP10: 0.085 | BQ10: 0.765 | BR10: -0.425 | BS10: 0.99166667 | BT10: -0.85 | BU10: -0.085 | BV10: 0.70833333 | BW10: 0 | BX10: 0.2975 | BY10: 0.425 | BZ10: -0.2125 | CA10: -0.425 | CB10: -0.88035714 | CC10: 0 | CD10: 0.32840909 | CE10: 0.425
A11: 7 | B11: 明塔卡星人 | C11: Mintakan | D11: 0.25 | E11: 0.25 | F11: 0.25 | G11: -0.5 | H11: -0.25 | I11: 0.25 | J11: 0 | K11: -0.5 | L11: 0 | M11: 0 | N11: -0.5 | O11: -1 | P11: -0.5 | Q11: 0.5 | R11: -0.5 | S11: 0.75 | T11: 0.16666667 | U11: 0.25 | V11: 0.25 | W11: -1 | X11: 0 | Y11: -0.25 | Z11: 0.25 | AA11: 0.16666667 | AB11: 0 | AC11: -0.25 | AD11: 0.25 | AE11: 0 | AF11: 0.5 | AG11: -1 | AH11: 0 | AI11: -0.2125 | AJ11: -0.85 | AK11: -0.2125 | AL11: -0.85 | AM11: -0.765 | AN11: 0.425 | AO11: 0.2125 | AP11: 0.85 | AQ11: 1 | AR11: -0.30357143 | AS11: 0.85 | AT11: 0.18214286 | AU11: 0.56666667 | AV11: -0.30357143 | AW11: -0.10625 | AX11: -0.425 | AY11: 0.085 | AZ11: 0.14166667 | BA11: 0.085 | BB11: -0.425 | BC11: 0.14166667 | BD11: 0.30357143 | BE11: 0.85 | BF11: -0.18214286 | BG11: 0.30357143 | BH11: -0.255 | BI11: 0.14166667 | BJ11: 0.2125 | BK11: -0.935 | BL11: -0.85 | BM11: 0.18214286 | BN11: -0.425 | BO11: 0.2125 | BP11: -0.765 | BQ11: 1 | BR11: 0.255 | BS11: 1 | BT11: 0.85 | BU11: 1 | BV11: -0.425 | BW11: -0.56666667 | BX11: -1 | BY11: 0 | BZ11: 0.2125 | CA11: -4.7184479e-17 | CB11: -1 | CC11: -1 | CD11: -0.44431818 | CE11: 0.85
A12: 8 | B12: 金星人 | C12: Venusian | D12: 0.25 | E12: 0.25 | F12: 0.75 | G12: -0.5 | H12: -0.25 | I12: 0 | J12: 0 | K12: 0 | L12: 0 | M12: 0 | N12: 0 | O12: -1 | P12: -0.5 | Q12: 0.5 | R12: 0 | S12: 0.75 | T12: 0 | U12: 0 | V12: 0 | W12: 0 | X12: 0 | Y12: 0 | Z12: 0.25 | AA12: 0.16666667 | AB12: 0 | AC12: -0.25 | AD12: 0 | AE12: 0 | AF12: 0.5 | AG12: -0.85 | AH12: -0.85 | AI12: -0.2125 | AJ12: 0.28333333 | AK12: 0.6375 | AL12: 0.85 | AM12: 0.595 | AN12: -0.70833333 | AO12: -0.2125 | AP12: 0.6375 | AQ12: 0.91071429 | AR12: -0.54642857 | AS12: 0.85 | AT12: 0.18214286 | AU12: 0.28333333 | AV12: -0.30357143 | AW12: 0.2125 | AX12: -0.2125 | AY12: -0.425 | AZ12: 0 | BA12: -0.255 | BB12: -0.2125 | BC12: 0.28333333 | BD12: 0.18214286 | BE12: 0.85 | BF12: -0.18214286 | BG12: 0.18214286 | BH12: 0.085 | BI12: -0.14166667 | BJ12: -0.2125 | BK12: -1 | BL12: -0.70833333 | BM12: 0.18214286 | BN12: 0 | BO12: -0.2125 | BP12: -0.595 | BQ12: 0.425 | BR12: 0.765 | BS12: 0.70833333 | BT12: -0.85 | BU12: 1 | BV12: -0.70833333 | BW12: -0.28333333 | BX12: -1 | BY12: 0.85 | BZ12: 0.2125 | CA12: -0.14166667 | CB12: -1 | CC12: 0 | CD12: -0.44431818 | CE12: 0.85
A13: 9 | B13: 哈達爾星人 | C13: Hadarian | D13: 0.25 | E13: 0.5 | F13: 0.25 | G13: -0.5 | H13: -0.25 | I13: 0.25 | J13: -0.5 | K13: 0 | L13: 0 | M13: 0 | N13: 0 | O13: -1 | P13: -1 | Q13: 0 | R13: -0.5 | S13: 0.75 | T13: 0 | U13: 0 | V13: 0 | W13: 0 | X13: 0 | Y13: 0.125 | Z13: 0.75 | AA13: 0.33333333 | AB13: 0 | AC13: -0.25 | AD13: 0.25 | AE13: 0 | AF13: 0.33333333 | AG13: -0.56666667 | AH13: 0 | AI13: -0.6375 | AJ13: 0.28333333 | AK13: -0.6375 | AL13: 0.28333333 | AM13: 0.765 | AN13: 0.70833333 | AO13: 0 | AP13: 0.6375 | AQ13: 1 | AR13: -0.425 | AS13: 1 | AT13: -0.060714286 | AU13: 0.28333333 | AV13: -0.18214286 | AW13: 0.425 | AX13: 0.2125 | AY13: -0.765 | AZ13: 0 | BA13: 0.085 | BB13: -0.2125 | BC13: 0.56666667 | BD13: 0.54642857 | BE13: 1 | BF13: -0.18214286 | BG13: 0.54642857 | BH13: -0.085 | BI13: 0.14166667 | BJ13: 0 | BK13: -1 | BL13: -0.56666667 | BM13: -0.060714286 | BN13: 0 | BO13: 0 | BP13: -0.255 | BQ13: 0.425 | BR13: 0.935 | BS13: 0.425 | BT13: -0.85 | BU13: 1 | BV13: -1 | BW13: -0.28333333 | BX13: -1 | BY13: 0 | BZ13: 0.6375 | CA13: -0.14166667 | CB13: -1 | CC13: 0 | CD13: -0.83068182 | CE13: 1
A14: 10 | B14: 北極星人 | C14: Polarian | D14: 0 | E14: 0.5 | F14: 0 | G14: 0 | H14: 0 | I14: 0.75 | J14: 0 | K14: -1 | L14: -0.5 | M14: 0 | N14: -0.5 | O14: -0.5 | P14: 0 | Q14: 0.5 | R14: 1 | S14: 0 | T14: 0.5 | U14: 0.75 | V14: -0.25 | W14: 0 | X14: 0 | Y14: 0.125 | Z14: 0.25 | AA14: 0 | AB14: -0.25 | AC14: 0 | AD14: 1 | AE14: -0.25 | AF14: 0.33333333 | AG14: -1 | AH14: 0 | AI14: 0 | AJ14: 0.28333333 | AK14: 0 | AL14: 0.28333333 | AM14: 0.595 | AN14: 0.425 | AO14: 0 | AP14: 1 | AQ14: -0.060714286 | AR14: 0.425 | AS14: 0.85 | AT14: 0.78928571 | AU14: 0.70833333 | AV14: 0.060714286 | AW14: -0.10625 | AX14: -0.6375 | AY14: 0.425 | AZ14: 0.85 | BA14: 0.595 | BB14: 0.85 | BC14: -0.425 | BD14: -0.54642857 | BE14: 0.425 | BF14: 0.91071429 | BG14: -0.54642857 | BH14: 0.595 | BI14: 0.70833333 | BJ14: 0 | BK14: -0.765 | BL14: -1 | BM14: 0.78928571 | BN14: -0.425 | BO14: 0 | BP14: -1 | BQ14: 0.595 | BR14: 0.425 | BS14: 0.70833333 | BT14: -0.85 | BU14: 0.255 | BV14: 0.14166667 | BW14: 0.85 | BX14: -0.26916667 | BY14: 0 | BZ14: 0 | CA14: 0.70833333 | CB14: -1 | CC14: 0 | CD14: 0.56022727 | CE14: 0.425
A15: 11 | B15: 半人馬座α星人 | C15: Alpha Centaurian | D15: -0.5 | E15: 0.25 | F15: -0.75 | G15: 0.5 | H15: 0.75 | I15: 0.5 | J15: 0 | K15: 0 | L15: -0.5 | M15: 0 | N15: -0.5 | O15: -0.5 | P15: 0 | Q15: 0 | R15: 0 | S15: -0.5 | T15: 0.33333333 | U15: 0.5 | V15: -0.5 | W15: 0 | X15: 0 | Y15: 0.25 | Z15: 0 | AA15: -0.33333333 | AB15: -0.25 | AC15: 0.5 | AD15: 0.25 | AE15: -0.5 | AF15: 0.16666667 | AG15: -1 | AH15: 0 | AI15: -0.2125 | AJ15: 0 | AK15: -0.2125 | AL15: 0 | AM15: 0.425 | AN15: 0.70833333 | AO15: 0 | AP15: 0.85 | AQ15: 0.66785714 | AR15: 0.18214286 | AS15: 0.85 | AT15: -0.78928571 | AU15: 0.70833333 | AV15: 0.30357143 | AW15: 0 | AX15: -0.6375 | AY15: 0.425 | AZ15: 0.70833333 | BA15: 0.255 | BB15: 0.2125 | BC15: -0.14166667 | BD15: -0.78928571 | BE15: 0 | BF15: 0.18214286 | BG15: -0.78928571 | BH15: -0.085 | BI15: 0.14166667 | BJ15: 0 | BK15: -0.765 | BL15: -0.425 | BM15: -0.78928571 | BN15: -0.425 | BO15: 0 | BP15: -0.255 | BQ15: 0.255 | BR15: 0.425 | BS15: 0.70833333 | BT15: -0.85 | BU15: 0.765 | BV15: 0.14166667 | BW15: 0 | BX15: 0.24083333 | BY15: 0 | BZ15: 0.2125 | CA15: -4.7184479e-17 | CB15: -0.75892857 | CC15: 0 | CD15: -0.057954545 | CE15: 0
A16: 12 | B16: 織女星人 | C16: Vegan | D16: -0.25 | E16: -0.75 | F16: 0.25 | G16: 0.5 | H16: 0 | I16: -0.5 | J16: 0.5 | K16: 1 | L16: 1 | M16: 0 | N16: 0.5 | O16: 0 | P16: 0.5 | Q16: -0.5 | R16: 0 | S16: 0.25 | T16: -0.66666667 | U16: -0.5 | V16: 0.25 | W16: 0 | X16: 0.5 | Y16: -0.125 | Z16: -0.5 | AA16: -0.16666667 | AB16: 0 | AC16: 0 | AD16: -0.75 | AE16: 0.5 | AF16: 0 | AG16: -0.56666667 | AH16: -0.425 | AI16: 0.6375 | AJ16: 0.28333333 | AK16: 1 | AL16: 0.56666667 | AM16: 0.255 | AN16: -0.70833333 | AO16: -0.425 | AP16: -0.425 | AQ16: 0.425 | AR16: -0.18214286 | AS16: 0.425 | AT16: -0.54642857 | AU16: 4.7184479e-17 | AV16: 0.18214286 | AW16: 0.10625 | AX16: -0.425 | AY16: -0.255 | AZ16: -0.70833333 | BA16: -0.595 | BB16: -0.85 | BC16: 0.28333333 | BD16: 0.18214286 | BE16: 0.425 | BF16: -0.425 | BG16: 0.18214286 | BH16: -0.255 | BI16: -0.85 | BJ16: -0.425 | BK16: -0.255 | BL16: 0.70833333 | BM16: -0.54642857 | BN16: 0.425 | BO16: -0.425 | BP16: 0.935 | BQ16: 0.595 | BR16: 0.595 | BS16: 0.99166667 | BT16: -0.85 | BU16: 0.425 | BV16: 0.14166667 | BW16: -0.56666667 | BX16: -0.2125 | BY16: 0.425 | BZ16: -0.6375 | CA16: -0.70833333 | CB16: -0.88035714 | CC16: 0 | CD16: -0.59886364 | CE16: 0.425
... A27: 23 | B27: 地球源靈魂 | C27: Earth-Origin Soul | D27: 0 | E27: 0.5 | F27: 0 | G27: 0 | H27: 0 | I27: 0.25 | J27: -0.5 | K27: -1 | L27: -0.5 | M27: 0 | N27: 0 | O27: 0 | P27: 0 | Q27: 0.5 | R27: 0.5 | S27: 0.25 | T27: 0.66666667 | U27: 1 | V27: -0.5 | W27: 1 | X27: 0 | Y27: 0.625 | Z27: 0.5 | AA27: -0.16666667 | AB27: -0.25 | AC27: 0 | AD27: 0.75 | AE27: -0.5 | AF27: 0.16666667 | AG27: -0.56666667 | AH27: 0 | AI27: 0 | AJ27: 0.85 | AK27: 0 | AL27: 0.85 | AM27: 1 | AN27: 0.425 | AO27: -0.2125 | AP27: 1 | AQ27: 0.30357143 | AR27: 0.78928571 | AS27: 1 | AT27: 0.425 | AU27: 0.425 | AV27: 0.30357143 | AW27: 0.31875 | AX27: -0.2125 | AY27: -0.085 | AZ27: 1 | BA27: -0.085 | BB27: 0.425 | BC27: -2.3592239e-17 | BD27: -0.18214286 | BE27: 0.6375 | BF27: 0.18214286 | BG27: -0.18214286 | BH27: 0.255 | BI27: 0.56666667 | BJ27: -0.2125 | BK27: -0.765 | BL27: -1 | BM27: 0.425 | BN27: -0.425 | BO27: -0.2125 | BP27: -1 | BQ27: -0.595 | BR27: 0.935 | BS27: -0.70833333 | BT27: -1 | BU27: 0.595 | BV27: -0.14166667 | BW27: 0.28333333 | BX27: -0.49583333 | BY27: 0 | BZ27: 0 | CA27: 0.56666667 | CB27: -1 | CC27: 1 | CD27: -0.057954545 | CE27: 0.6375

Sheet 08_EXPECTED_CODEBOOK_V4
A1: FORMAL — v4 23×80 Expected Canonical Codebook
A2: Canonical expected response values -3…+3. Positive means Pole A. This is the source of truth for the next scoring-weight rebuild.
A4: # | B4: 中文 | C4: English | D4: G01 | E4: G02 | F4: G03 | G4: G04 | H4: G05 | I4: G06 | J4: G07 | K4: G08 | L4: G09 | M4: G10 | N4: G11 | O4: G12 | P4: G13 | Q4: G14 | R4: G15 | S4: G16 | T4: G17 | U4: G18 | V4: G19 | W4: G20 | X4: G21 | Y4: G22 | Z4: G23 | AA4: G24 | AB4: G25 | AC4: G26 | AD4: G27 | AE4: G28 | AF4: G29 | AG4: G30 | AH4: L01 | AI4: L02 | AJ4: L03 | AK4: L04 | AL4: L05 | AM4: L06 | AN4: L07 | AO4: L08 | AP4: L09 | AQ4: L10 | AR4: L11 | AS4: L12 | AT4: L13 | AU4: L14 | AV4: L15 | AW4: L16 | AX4: L17 | AY4: L18 | AZ4: L19 | BA4: L20 | BB4: L21 | BC4: L22 | BD4: L23 | BE4: L24 | BF4: L25 | BG4: L26 | BH4: L27 | BI4: L28 | BJ4: L29 | BK4: L30 | BL4: L31 | BM4: L32 | BN4: L33 | BO4: L34 | BP4: L35 | BQ4: L36 | BR4: L37 | BS4: L38 | BT4: A01 | BU4: A02 | BV4: A03 | BW4: A04 | BX4: A05 | BY4: A06 | BZ4: A07 | CA4: A08 | CB4: A09 | CC4: A10 | CD4: A11 | CE4: A12
A5: 1 | B5: 昴宿星人 | C5: Pleiadian | D5: 3 | E5: 1 | F5: 1 | G5: -2 | H5: -3 | I5: 1 | J5: 0 | K5: 0 | L5: 0 | M5: 0 | N5: -2 | O5: -3 | P5: -2 | Q5: 2 | R5: -2 | S5: 3 | T5: 0 | U5: 0 | V5: 1 | W5: 0 | X5: 0 | Y5: 0 | Z5: 1 | AA5: 2 | AB5: 0 | AC5: -1 | AD5: 0 | AE5: 0 | AF5: 2 | AG5: -3 | AH5: 3 | AI5: 2 | AJ5: 3 | AK5: -1 | AL5: 1 | AM5: 2 | AN5: 2 | AO5: 1 | AP5: 2 | AQ5: 3 | AR5: -2 | AS5: 3 | AT5: 0 | AU5: 2 | AV5: -1 | AW5: 0 | AX5: -2 | AY5: 0 | AZ5: 0 | BA5: 0 | BB5: -2 | BC5: 0 | BD5: 1 | BE5: 3 | BF5: -1 | BG5: 1 | BH5: -1 | BI5: 0 | BJ5: 1 | BK5: -3 | BL5: -2 | BM5: 0 | BN5: -2 | BO5: 1 | BP5: -2 | BQ5: 2 | BR5: 1 | BS5: 3 | BT5: -3 | BU5: 3 | BV5: -2 | BW5: -2 | BX5: -3 | BY5: -3 | BZ5: -2 | CA5: -1 | CB5: -3 | CC5: 0 | CD5: -2 | CE5: 3
A6: 2 | B6: 大角星人 | C6: Arcturian | D6: -1 | E6: -2 | F6: -1 | G6: 0 | H6: 2 | I6: -1 | J6: 2 | K6: 2 | L6: 2 | M6: 0 | N6: 2 | O6: 0 | P6: 0 | Q6: 0 | R6: 0 | S6: 1 | T6: -1 | U6: 0 | V6: -1 | W6: 0 | X6: 2 | Y6: 0 | Z6: -2 | AA6: -1 | AB6: -1 | AC6: 1 | AD6: -1 | AE6: 1 | AF6: 1 | AG6: -1 | AH6: -2 | AI6: 0 | AJ6: 0 | AK6: 2 | AL6: 1 | AM6: 1 | AN6: 0 | AO6: 0 | AP6: 2 | AQ6: 3 | AR6: -1 | AS6: 2 | AT6: -2 | AU6: 0 | AV6: -1 | AW6: 2 | AX6: 0 | AY6: -2 | AZ6: 0 | BA6: -2 | BB6: -2 | BC6: 2 | BD6: -1 | BE6: 0 | BF6: -1 | BG6: -1 | BH6: 0 | BI6: -2 | BJ6: 0 | BK6: -3 | BL6: 0 | BM6: -2 | BN6: 2 | BO6: 0 | BP6: 0 | BQ6: 1 | BR6: 3 | BS6: 3 | BT6: -3 | BU6: 3 | BV6: -2 | BW6: -1 | BX6: -2 | BY6: 2 | BZ6: 0 | CA6: -2 | CB6: -2 | CC6: 0 | CD6: -2 | CE6: 0
A7: 3 | B7: 天狼星人 | C7: Sirian | D7: 0 | E7: 2 | F7: 0 | G7: 0 | H7: 0 | I7: 2 | J7: 0 | K7: -2 | L7: -2 | M7: 0 | N7: 0 | O7: -2 | P7: 3 | Q7: 0 | R7: 2 | S7: 1 | T7: 2 | U7: 2 | V7: 0 | W7: 0 | X7: 0 | Y7: 0 | Z7: 1 | AA7: -2 | AB7: 1 | AC7: 0 | AD7: 3 | AE7: -3 | AF7: 1 | AG7: -3 | AH7: 0 | AI7: 2 | AJ7: 1 | AK7: 2 | AL7: 1 | AM7: 2 | AN7: 2 | AO7: 0 | AP7: 3 | AQ7: -1 | AR7: 1 | AS7: 3 | AT7: 1 | AU7: 0 | AV7: 1 | AW7: -2 | AX7: -3 | AY7: 2 | AZ7: 3 | BA7: 1 | BB7: 2 | BC7: -1 | BD7: -2 | BE7: 3 | BF7: 2 | BG7: -2 | BH7: 0 | BI7: 2 | BJ7: 0 | BK7: 3 | BL7: -2 | BM7: 1 | BN7: -3 | BO7: 0 | BP7: -2 | BQ7: 0 | BR7: 2 | BS7: 3 | BT7: -2 | BU7: 0 | BV7: 3 | BW7: 2 | BX7: -2 | BY7: 0 | BZ7: -2 | CA7: 2 | CB7: -3 | CC7: 0 | CD7: 0 | CE7: 3
A8: 4 | B8: 仙女座人 | C8: Andromedan | D8: 0 | E8: -2 | F8: 1 | G8: 0 | H8: -1 | I8: -2 | J8: 3 | K8: 3 | L8: 3 | M8: -2 | N8: 2 | O8: 0 | P8: 0 | Q8: 0 | R8: 0 | S8: 2 | T8: -2 | U8: -2 | V8: 1 | W8: 0 | X8: 0 | Y8: 0 | Z8: -2 | AA8: 0 | AB8: 0 | AC8: 0 | AD8: -3 | AE8: 2 | AF8: 0 | AG8: -1 | AH8: 0 | AI8: 1 | AJ8: 1 | AK8: 1 | AL8: 1 | AM8: 2 | AN8: 0 | AO8: 2 | AP8: -2 | AQ8: 2 | AR8: -2 | AS8: 2 | AT8: -1 | AU8: 1 | AV8: -1 | AW8: 1 | AX8: 0 | AY8: -2 | AZ8: -3 | BA8: -2 | BB8: -3 | BC8: 0 | BD8: 1 | BE8: 2 | BF8: -2 | BG8: 1 | BH8: -2 | BI8: -3 | BJ8: 2 | BK8: -2 | BL8: 2 | BM8: -1 | BN8: 2 | BO8: 2 | BP8: 2 | BQ8: 2 | BR8: 2 | BS8: 3 | BT8: -3 | BU8: 3 | BV8: -2 | BW8: -3 | BX8: -2 | BY8: 0 | BZ8: -1 | CA8: -2 | CB8: -3 | CC8: 0 | CD8: -2 | CE8: 2
A9: 5 | B9: 天琴座人 | C9: Lyran | D9: -1 | E9: -2 | F9: 0 | G9: 0 | H9: 1 | I9: -2 | J9: 2 | K9: 0 | L9: 3 | M9: 0 | N9: 3 | O9: 2 | P9: 0 | Q9: -2 | R9: 0 | S9: 0 | T9: -1 | U9: 2 | V9: -2 | W9: 0 | X9: -2 | Y9: 0 | Z9: -1 | AA9: -1 | AB9: -1 | AC9: 0 | AD9: 0 | AE9: 1 | AF9: -2 | AG9: 1 | AH9: -2 | AI9: -1 | AJ9: 0 | AK9: 1 | AL9: 1 | AM9: 2 | AN9: 0 | AO9: 2 | AP9: 1 | AQ9: 2 | AR9: 1 | AS9: 2 | AT9: -1 | AU9: 0 | AV9: -1 | AW9: 3 | AX9: 2 | AY9: -3 | AZ9: 3 | BA9: -2 | BB9: -2 | BC9: 3 | BD9: 1 | BE9: 1 | BF9: -2 | BG9: 1 | BH9: 0 | BI9: 2 | BJ9: 2 | BK9: -3 | BL9: 0 | BM9: -1 | BN9: 3 | BO9: 2 | BP9: 0 | BQ9: 1 | BR9: 3 | BS9: 3 | BT9: -3 | BU9: 3 | BV9: -3 | BW9: -1 | BX9: -1 | BY9: 2 | BZ9: 1 | CA9: 2 | CB9: -2 | CC9: 0 | CD9: -3 | CE9: 1
A10: 6 | B10: 獵戶座人 | C10: Orion | D10: -3 | E10: -1 | F10: 0 | G10: 3 | H10: 1 | I10: 1 | J10: 2 | K10: 0 | L10: 0 | M10: 0 | N10: -2 | O10: 2 | P10: 2 | Q10: 0 | R10: 2 | S10: 0 | T10: 0 | U10: 0 | V10: 2 | W10: 0 | X10: 3 | Y10: 0 | Z10: -2 | AA10: -1 | AB10: 0 | AC10: 0 | AD10: 0 | AE10: 0 | AF10: 1 | AG10: -3 | AH10: -2 | AI10: 1 | AJ10: 0 | AK10: 2 | AL10: 1 | AM10: 1 | AN10: 0 | AO10: -2 | AP10: 1 | AQ10: 0 | AR10: 3 | AS10: 2 | AT10: 1 | AU10: 2 | AV10: 2 | AW10: -2 | AX10: -2 | AY10: 3 | AZ10: -1 | BA10: 0 | BB10: 0 | BC10: -2 | BD10: -2 | BE10: 2 | BF10: 1 | BG10: -2 | BH10: 0 | BI10: -2 | BJ10: -2 | BK10: 0 | BL10: 0 | BM10: 1 | BN10: -3 | BO10: -2 | BP10: 0 | BQ10: 3 | BR10: -2 | BS10: 3 | BT10: -3 | BU10: 0 | BV10: 3 | BW10: 0 | BX10: 1 | BY10: 2 | BZ10: -1 | CA10: -2 | CB10: -3 | CC10: 0 | CD10: 1 | CE10: 2
A11: 7 | B11: 明塔卡星人 | C11: Mintakan | D11: 1 | E11: 1 | F11: 1 | G11: -2 | H11: -1 | I11: 1 | J11: 0 | K11: -2 | L11: 0 | M11: 0 | N11: -2 | O11: -3 | P11: -2 | Q11: 2 | R11: -2 | S11: 3 | T11: 1 | U11: 1 | V11: 1 | W11: -3 | X11: 0 | Y11: -1 | Z11: 1 | AA11: 1 | AB11: 0 | AC11: -1 | AD11: 1 | AE11: 0 | AF11: 2 | AG11: -3 | AH11: 0 | AI11: -1 | AJ11: -3 | AK11: -1 | AL11: -3 | AM11: -3 | AN11: 2 | AO11: 1 | AP11: 3 | AQ11: 3 | AR11: -1 | AS11: 3 | AT11: 1 | AU11: 2 | AV11: -1 | AW11: 0 | AX11: -2 | AY11: 0 | AZ11: 0 | BA11: 0 | BB11: -2 | BC11: 0 | BD11: 1 | BE11: 3 | BF11: -1 | BG11: 1 | BH11: -1 | BI11: 0 | BJ11: 1 | BK11: -3 | BL11: -3 | BM11: 1 | BN11: -2 | BO11: 1 | BP11: -3 | BQ11: 3 | BR11: 1 | BS11: 3 | BT11: 3 | BU11: 3 | BV11: -2 | BW11: -2 | BX11: -3 | BY11: 0 | BZ11: 1 | CA11: 0 | CB11: -3 | CC11: -3 | CD11: -2 | CE11: 3
A12: 8 | B12: 金星人 | C12: Venusian | D12: 1 | E12: 1 | F12: 3 | G12: -2 | H12: -1 | I12: 0 | J12: 0 | K12: 0 | L12: 0 | M12: 0 | N12: 0 | O12: -3 | P12: -2 | Q12: 2 | R12: 0 | S12: 3 | T12: 0 | U12: 0 | V12: 0 | W12: 0 | X12: 0 | Y12: 0 | Z12: 1 | AA12: 1 | AB12: 0 | AC12: -1 | AD12: 0 | AE12: 0 | AF12: 2 | AG12: -3 | AH12: -3 | AI12: -1 | AJ12: 1 | AK12: 2 | AL12: 3 | AM12: 2 | AN12: -3 | AO12: -1 | AP12: 2 | AQ12: 3 | AR12: -2 | AS12: 3 | AT12: 1 | AU12: 1 | AV12: -1 | AW12: 1 | AX12: -1 | AY12: -2 | AZ12: 0 | BA12: -1 | BB12: -1 | BC12: 1 | BD12: 1 | BE12: 3 | BF12: -1 | BG12: 1 | BH12: 0 | BI12: 0 | BJ12: -1 | BK12: -3 | BL12: -3 | BM12: 1 | BN12: 0 | BO12: -1 | BP12: -2 | BQ12: 2 | BR12: 3 | BS12: 3 | BT12: -3 | BU12: 3 | BV12: -3 | BW12: -1 | BX12: -3 | BY12: 3 | BZ12: 1 | CA12: 0 | CB12: -3 | CC12: 0 | CD12: -2 | CE12: 3
A13: 9 | B13: 哈達爾星人 | C13: Hadarian | D13: 1 | E13: 2 | F13: 1 | G13: -2 | H13: -1 | I13: 1 | J13: -2 | K13: 0 | L13: 0 | M13: 0 | N13: 0 | O13: -3 | P13: -3 | Q13: 0 | R13: -2 | S13: 3 | T13: 0 | U13: 0 | V13: 0 | W13: 0 | X13: 0 | Y13: 0 | Z13: 3 | AA13: 1 | AB13: 0 | AC13: -1 | AD13: 1 | AE13: 0 | AF13: 1 | AG13: -2 | AH13: 0 | AI13: -2 | AJ13: 1 | AK13: -2 | AL13: 1 | AM13: 3 | AN13: 3 | AO13: 0 | AP13: 2 | AQ13: 3 | AR13: -2 | AS13: 3 | AT13: 0 | AU13: 1 | AV13: -1 | AW13: 2 | AX13: 1 | AY13: -3 | AZ13: 0 | BA13: 0 | BB13: -1 | BC13: 2 | BD13: 2 | BE13: 3 | BF13: -1 | BG13: 2 | BH13: 0 | BI13: 0 | BJ13: 0 | BK13: -3 | BL13: -2 | BM13: 0 | BN13: 0 | BO13: 0 | BP13: -1 | BQ13: 2 | BR13: 3 | BS13: 2 | BT13: -3 | BU13: 3 | BV13: -3 | BW13: -1 | BX13: -3 | BY13: 0 | BZ13: 2 | CA13: 0 | CB13: -3 | CC13: 0 | CD13: -3 | CE13: 3
A14: 10 | B14: 北極星人 | C14: Polarian | D14: 0 | E14: 2 | F14: 0 | G14: 0 | H14: 0 | I14: 3 | J14: 0 | K14: -3 | L14: -2 | M14: 0 | N14: -2 | O14: -2 | P14: 0 | Q14: 2 | R14: 3 | S14: 0 | T14: 2 | U14: 3 | V14: -1 | W14: 0 | X14: 0 | Y14: 0 | Z14: 1 | AA14: 0 | AB14: -1 | AC14: 0 | AD14: 3 | AE14: -1 | AF14: 1 | AG14: -3 | AH14: 0 | AI14: 0 | AJ14: 1 | AK14: 0 | AL14: 1 | AM14: 2 | AN14: 2 | AO14: 0 | AP14: 3 | AQ14: 0 | AR14: 2 | AS14: 3 | AT14: 3 | AU14: 3 | AV14: 0 | AW14: 0 | AX14: -2 | AY14: 2 | AZ14: 3 | BA14: 2 | BB14: 3 | BC14: -2 | BD14: -2 | BE14: 2 | BF14: 3 | BG14: -2 | BH14: 2 | BI14: 3 | BJ14: 0 | BK14: -3 | BL14: -3 | BM14: 3 | BN14: -2 | BO14: 0 | BP14: -3 | BQ14: 2 | BR14: 2 | BS14: 3 | BT14: -3 | BU14: 1 | BV14: 0 | BW14: 3 | BX14: -1 | BY14: 0 | BZ14: 0 | CA14: 3 | CB14: -3 | CC14: 0 | CD14: 2 | CE14: 2
A15: 11 | B15: 半人馬座α星人 | C15: Alpha Centaurian | D15: -2 | E15: 1 | F15: -3 | G15: 2 | H15: 3 | I15: 2 | J15: 0 | K15: 0 | L15: -2 | M15: 0 | N15: -2 | O15: -2 | P15: 0 | Q15: 0 | R15: 0 | S15: -2 | T15: 1 | U15: 2 | V15: -2 | W15: 0 | X15: 0 | Y15: 1 | Z15: 0 | AA15: -1 | AB15: -1 | AC15: 2 | AD15: 1 | AE15: -2 | AF15: 1 | AG15: -3 | AH15: 0 | AI15: -1 | AJ15: 0 | AK15: -1 | AL15: 0 | AM15: 2 | AN15: 3 | AO15: 0 | AP15: 3 | AQ15: 2 | AR15: 1 | AS15: 3 | AT15: -3 | AU15: 3 | AV15: 1 | AW15: 0 | AX15: -2 | AY15: 2 | AZ15: 3 | BA15: 1 | BB15: 1 | BC15: 0 | BD15: -3 | BE15: 0 | BF15: 1 | BG15: -3 | BH15: 0 | BI15: 0 | BJ15: 0 | BK15: -3 | BL15: -2 | BM15: -3 | BN15: -2 | BO15: 0 | BP15: -1 | BQ15: 1 | BR15: 2 | BS15: 3 | BT15: -3 | BU15: 3 | BV15: 0 | BW15: 0 | BX15: 1 | BY15: 0 | BZ15: 1 | CA15: 0 | CB15: -3 | CC15: 0 | CD15: 0 | CE15: 0
A16: 12 | B16: 織女星人 | C16: Vegan | D16: -1 | E16: -3 | F16: 1 | G16: 2 | H16: 0 | I16: -2 | J16: 2 | K16: 3 | L16: 3 | M16: 0 | N16: 2 | O16: 0 | P16: 2 | Q16: -2 | R16: 0 | S16: 1 | T16: -2 | U16: -2 | V16: 1 | W16: 0 | X16: 2 | Y16: 0 | Z16: -2 | AA16: -1 | AB16: 0 | AC16: 0 | AD16: -3 | AE16: 2 | AF16: 0 | AG16: -2 | AH16: -2 | AI16: 2 | AJ16: 1 | AK16: 3 | AL16: 2 | AM16: 1 | AN16: -3 | AO16: -2 | AP16: -2 | AQ16: 2 | AR16: -1 | AS16: 2 | AT16: -2 | AU16: 0 | AV16: 1 | AW16: 0 | AX16: -2 | AY16: -1 | AZ16: -3 | BA16: -2 | BB16: -3 | BC16: 1 | BD16: 1 | BE16: 2 | BF16: -2 | BG16: 1 | BH16: -1 | BI16: -3 | BJ16: -2 | BK16: -1 | BL16: 3 | BM16: -2 | BN16: 2 | BO16: -2 | BP16: 3 | BQ16: 2 | BR16: 2 | BS16: 3 | BT16: -3 | BU16: 2 | BV16: 0 | BW16: -2 | BX16: -1 | BY16: 2 | BZ16: -2 | CA16: -3 | CB16: -3 | CC16: 0 | CD16: -2 | CE16: 2
... A27: 23 | B27: 地球源靈魂 | C27: Earth-Origin Soul | D27: 0 | E27: 2 | F27: 0 | G27: 0 | H27: 0 | I27: 1 | J27: -2 | K27: -3 | L27: -2 | M27: 0 | N27: 0 | O27: 0 | P27: 0 | Q27: 2 | R27: 2 | S27: 1 | T27: 2 | U27: 3 | V27: -2 | W27: 3 | X27: 0 | Y27: 2 | Z27: 2 | AA27: -1 | AB27: -1 | AC27: 0 | AD27: 3 | AE27: -2 | AF27: 1 | AG27: -2 | AH27: 0 | AI27: 0 | AJ27: 3 | AK27: 0 | AL27: 3 | AM27: 3 | AN27: 2 | AO27: -1 | AP27: 3 | AQ27: 1 | AR27: 3 | AS27: 3 | AT27: 2 | AU27: 2 | AV27: 1 | AW27: 1 | AX27: -1 | AY27: 0 | AZ27: 3 | BA27: 0 | BB27: 2 | BC27: 0 | BD27: -1 | BE27: 2 | BF27: 1 | BG27: -1 | BH27: 1 | BI27: 2 | BJ27: -1 | BK27: -3 | BL27: -3 | BM27: 2 | BN27: -2 | BO27: -1 | BP27: -3 | BQ27: -2 | BR27: 3 | BS27: -3 | BT27: -3 | BU27: 2 | BV27: 0 | BW27: 1 | BX27: -2 | BY27: 0 | BZ27: 0 | CA27: 2 | CB27: -3 | CC27: 3 | CD27: 0 | CE27: 2

Sheet 17_FORMULA_CODEBOOK_CHECK
A1: Formula Mirror — Expected Codebook Quantization Check
A2: This sheet re-derives 08_EXPECTED_CODEBOOK_V4 from 07_CONTINUOUS_CODEBOOK using numeric controls in 04_CODEBOOK_CONTROL. It is a reproducibility check; 08 remains the immediately readable frozen value table.
A4: # | B4: 中文 | C4: English | D4: G01 | E4: G02 | F4: G03 | G4: G04 | H4: G05 | I4: G06 | J4: G07 | K4: G08 | L4: G09 | M4: G10 | N4: G11 | O4: G12 | P4: G13 | Q4: G14 | R4: G15 | S4: G16 | T4: G17 | U4: G18 | V4: G19 | W4: G20 | X4: G21 | Y4: G22 | Z4: G23 | AA4: G24 | AB4: G25 | AC4: G26 | AD4: G27 | AE4: G28 | AF4: G29 | AG4: G30 | AH4: L01 | AI4: L02 | AJ4: L03 | AK4: L04 | AL4: L05 | AM4: L06 | AN4: L07 | AO4: L08 | AP4: L09 | AQ4: L10 | AR4: L11 | AS4: L12 | AT4: L13 | AU4: L14 | AV4: L15 | AW4: L16 | AX4: L17 | AY4: L18 | AZ4: L19 | BA4: L20 | BB4: L21 | BC4: L22 | BD4: L23 | BE4: L24 | BF4: L25 | BG4: L26 | BH4: L27 | BI4: L28 | BJ4: L29 | BK4: L30 | BL4: L31 | BM4: L32 | BN4: L33 | BO4: L34 | BP4: L35 | BQ4: L36 | BR4: L37 | BS4: L38 | BT4: A01 | BU4: A02 | BV4: A03 | BW4: A04 | BX4: A05 | BY4: A06 | BZ4: A07 | CA4: A08 | CB4: A09 | CC4: A10 | CD4: A11 | CE4: A12
A5: 1 | B5: 昴宿星人 | C5: Pleiadian | D5: =IF(ABS('07_CONTINUOUS_CODEBOOK'!D5)<'04_CODEBOOK_CONTROL'!$B$15,0,SIGN('07_CONTINUOUS_CODEBOOK'!D5)*IF(ABS('07_CONTINUOUS_CODEBOOK'!D5)<'04_CODEBOOK_CONTROL'!$B$16,1,IF(ABS('07_CONTINUOUS_CODEBOOK'!D5)<'04_CODEBOOK_CONTROL'!$B$17,2,3))) | E5: =IF(ABS('07_CONTINUOUS_CODEBOOK'!E5)<'04_CODEBOOK_CONTROL'!$B$15,0,SIGN('07_CONTINUOUS_CODEBOOK'!E5)*IF(ABS('07_CONTINUOUS_CODEBOOK'!E5)<'04_CODEBOOK_CONTROL'!$B$16,1,IF(ABS('07_CONTINUOUS_CODEBOOK'!E5)<'04_CODEBOOK_CONTROL'!$B$17,2,3))) | F5: =IF(ABS('07_CONTINUOUS_CODEBOOK'!F5)<'04_CODEBOOK_CONTROL'!$B$15,0,SIGN('07_CONTINUOUS_CODEBOOK'!F5)*IF(ABS('07_CONTINUOUS_CODEBOOK'!F5)<'04_CODEBOOK_CONTROL'!$B$16,1,IF(ABS('07_CONTINUOUS_CODEBOOK'!F5)<'04_CODEBOOK_CONTROL'!$B$17,2,3))) | G5: =IF(ABS('07_CONTINUOUS_CODEBOOK'!G5)<'04_CODEBOOK_CONTROL'!$B$15,0,SIGN('07_CONTINUOUS_CODEBOOK'!G5)*IF(ABS('07_CONTINUOUS_CODEBOOK'!G5)<'04_CODEBOOK_CONTROL'!$B$16,1,IF(ABS('07_CONTINUOUS_CODEBOOK'!G5)<'04_CODEBOOK_CONTROL'!$B$17,2,3))) | H5: =IF(ABS('07_CONTINUOUS_CODEBOOK'!H5)<'04_CODEBOOK_CONTROL'!$B$15,0,SIGN('07_CONTINUOUS_CODEBOOK'!H5)*IF(ABS('07_CONTINUOUS_CODEBOOK'!H5)<'04_CODEBOOK_CONTROL'!$B$16,1,IF(ABS('07_CONTINUOUS_CODEBOOK'!H5)<'04_CODEBOOK_CONTROL'!$B$17,2,3))) | I5: =IF(ABS('07_CONTINUOUS_CODEBOOK'!I5)<'04_CODEBOOK_CONTROL'!$B$15,0,SIGN('07_CONTINUOUS_CODEBOOK'!I5)*IF(ABS('07_CONTINUOUS_CODEBOOK'!I5)<'04_CODEBOOK_CONTROL'!$B$16,1,IF(ABS('07_CONTINUOUS_CODEBOOK'!I5)<'04_CODEBOOK_CONTROL'!$B$17,2,3))) | J5: =IF(ABS('07_CONTINUOUS_CODEBOOK'!J5)<'04_CODEBOOK_CONTROL'!$B$15,0,SIGN('07_CONTINUOUS_CODEBOOK'!J5)*IF(ABS('07_CONTINUOUS_CODEBOOK'!J5)<'04_CODEBOOK_CONTROL'!$B$16,1,IF(ABS('07_CONTINUOUS_CODEBOOK'!J5)<'04_CODEBOOK_CONTROL'!$B$17,2,3))) | K5: =IF(ABS('07_CONTINUOUS_CODEBOOK'!K5)<'04_CODEBOOK_CONTROL'!$B$15,0,SIGN('07_CONTINUOUS_CODEBOOK'!K5)*IF(ABS('07_CONTINUOUS_CODEBOOK'!K5)<'04_CODEBOOK_CONTROL'!$B$16,1,IF(ABS('07_CONTINUOUS_CODEBOOK'!K5)<'04_CODEBOOK_CONTROL'!$B$17,2,3))) | ... CE5: =IF(ABS('07_CONTINUOUS_CODEBOOK'!CE5)<'04_CODEBOOK_CONTROL'!$B$15,0,SIGN('07_CONTINUOUS_CODEBOOK'!CE5)*IF(ABS('07_CONTINUOUS_CODEBOOK'!CE5)<'04_CODEBOOK_CONTROL'!$B$16,1,IF(ABS('07_CONTINUOUS_CODEBOOK'!CE5)<'04_CODEBOOK_CONTROL'!$B$17,2,3)))
A6: 2 | B6: 大角星人 | C6: Arcturian | D6: =IF(ABS('07_CONTINUOUS_CODEBOOK'!D6)<'04_CODEBOOK_CONTROL'!$B$15,0,SIGN('07_CONTINUOUS_CODEBOOK'!D6)*IF(ABS('07_CONTINUOUS_CODEBOOK'!D6)<'04_CODEBOOK_CONTROL'!$B$16,1,IF(ABS('07_CONTINUOUS_CODEBOOK'!D6)<'04_CODEBOOK_CONTROL'!$B$17,2,3))) | E6: =IF(ABS('07_CONTINUOUS_CODEBOOK'!E6)<'04_CODEBOOK_CONTROL'!$B$15,0,SIGN('07_CONTINUOUS_CODEBOOK'!E6)*IF(ABS('07_CONTINUOUS_CODEBOOK'!E6)<'04_CODEBOOK_CONTROL'!$B$16,1,IF(ABS('07_CONTINUOUS_CODEBOOK'!E6)<'04_CODEBOOK_CONTROL'!$B$17,2,3))) | F6: =IF(ABS('07_CONTINUOUS_CODEBOOK'!F6)<'04_CODEBOOK_CONTROL'!$B$15,0,SIGN('07_CONTINUOUS_CODEBOOK'!F6)*IF(ABS('07_CONTINUOUS_CODEBOOK'!F6)<'04_CODEBOOK_CONTROL'!$B$16,1,IF(ABS('07_CONTINUOUS_CODEBOOK'!F6)<'04_CODEBOOK_CONTROL'!$B$17,2,3))) | G6: =IF(ABS('07_CONTINUOUS_CODEBOOK'!G6)<'04_CODEBOOK_CONTROL'!$B$15,0,SIGN('07_CONTINUOUS_CODEBOOK'!G6)*IF(ABS('07_CONTINUOUS_CODEBOOK'!G6)<'04_CODEBOOK_CONTROL'!$B$16,1,IF(ABS('07_CONTINUOUS_CODEBOOK'!G6)<'04_CODEBOOK_CONTROL'!$B$17,2,3))) | H6: =IF(ABS('07_CONTINUOUS_CODEBOOK'!H6)<'04_CODEBOOK_CONTROL'!$B$15,0,SIGN('07_CONTINUOUS_CODEBOOK'!H6)*IF(ABS('07_CONTINUOUS_CODEBOOK'!H6)<'04_CODEBOOK_CONTROL'!$B$16,1,IF(ABS('07_CONTINUOUS_CODEBOOK'!H6)<'04_CODEBOOK_CONTROL'!$B$17,2,3))) | I6: =IF(ABS('07_CONTINUOUS_CODEBOOK'!I6)<'04_CODEBOOK_CONTROL'!$B$15,0,SIGN('07_CONTINUOUS_CODEBOOK'!I6)*IF(ABS('07_CONTINUOUS_CODEBOOK'!I6)<'04_CODEBOOK_CONTROL'!$B$16,1,IF(ABS('07_CONTINUOUS_CODEBOOK'!I6)<'04_CODEBOOK_CONTROL'!$B$17,2,3))) | J6: =IF(ABS('07_CONTINUOUS_CODEBOOK'!J6)<'04_CODEBOOK_CONTROL'!$B$15,0,SIGN('07_CONTINUOUS_CODEBOOK'!J6)*IF(ABS('07_CONTINUOUS_CODEBOOK'!J6)<'04_CODEBOOK_CONTROL'!$B$16,1,IF(ABS('07_CONTINUOUS_CODEBOOK'!J6)<'04_CODEBOOK_CONTROL'!$B$17,2,3))) | K6: =IF(ABS('07_CONTINUOUS_CODEBOOK'!K6)<'04_CODEBOOK_CONTROL'!$B$15,0,SIGN('07_CONTINUOUS_CODEBOOK'!K6)*IF(ABS('07_CONTINUOUS_CODEBOOK'!K6)<'04_CODEBOOK_CONTROL'!$B$16,1,IF(ABS('07_CONTINUOUS_CODEBOOK'!K6)<'04_CODEBOOK_CONTROL'!$B$17,2,3))) | ... CE6: =IF(ABS('07_CONTINUOUS_CODEBOOK'!CE6)<'04_CODEBOOK_CONTROL'!$B$15,0,SIGN('07_CONTINUOUS_CODEBOOK'!CE6)*IF(ABS('07_CONTINUOUS_CODEBOOK'!CE6)<'04_CODEBOOK_CONTROL'!$B$16,1,IF(ABS('07_CONTINUOUS_CODEBOOK'!CE6)<'04_CODEBOOK_CONTROL'!$B$17,2,3)))
A7: 3 | B7: 天狼星人 | C7: Sirian | D7: =IF(ABS('07_CONTINUOUS_CODEBOOK'!D7)<'04_CODEBOOK_CONTROL'!$B$15,0,SIGN('07_CONTINUOUS_CODEBOOK'!D7)*IF(ABS('07_CONTINUOUS_CODEBOOK'!D7)<'04_CODEBOOK_CONTROL'!$B$16,1,IF(ABS('07_CONTINUOUS_CODEBOOK'!D7)<'04_CODEBOOK_CONTROL'!$B$17,2,3))) | E7: =IF(ABS('07_CONTINUOUS_CODEBOOK'!E7)<'04_CODEBOOK_CONTROL'!$B$15,0,SIGN('07_CONTINUOUS_CODEBOOK'!E7)*IF(ABS('07_CONTINUOUS_CODEBOOK'!E7)<'04_CODEBOOK_CONTROL'!$B$16,1,IF(ABS('07_CONTINUOUS_CODEBOOK'!E7)<'04_CODEBOOK_CONTROL'!$B$17,2,3))) | F7: =IF(ABS('07_CONTINUOUS_CODEBOOK'!F7)<'04_CODEBOOK_CONTROL'!$B$15,0,SIGN('07_CONTINUOUS_CODEBOOK'!F7)*IF(ABS('07_CONTINUOUS_CODEBOOK'!F7)<'04_CODEBOOK_CONTROL'!$B$16,1,IF(ABS('07_CONTINUOUS_CODEBOOK'!F7)<'04_CODEBOOK_CONTROL'!$B$17,2,3))) | G7: =IF(ABS('07_CONTINUOUS_CODEBOOK'!G7)<'04_CODEBOOK_CONTROL'!$B$15,0,SIGN('07_CONTINUOUS_CODEBOOK'!G7)*IF(ABS('07_CONTINUOUS_CODEBOOK'!G7)<'04_CODEBOOK_CONTROL'!$B$16,1,IF(ABS('07_CONTINUOUS_CODEBOOK'!G7)<'04_CODEBOOK_CONTROL'!$B$17,2,3))) | H7: =IF(ABS('07_CONTINUOUS_CODEBOOK'!H7)<'04_CODEBOOK_CONTROL'!$B$15,0,SIGN('07_CONTINUOUS_CODEBOOK'!H7)*IF(ABS('07_CONTINUOUS_CODEBOOK'!H7)<'04_CODEBOOK_CONTROL'!$B$16,1,IF(ABS('07_CONTINUOUS_CODEBOOK'!H7)<'04_CODEBOOK_CONTROL'!$B$17,2,3))) | I7: =IF(ABS('07_CONTINUOUS_CODEBOOK'!I7)<'04_CODEBOOK_CONTROL'!$B$15,0,SIGN('07_CONTINUOUS_CODEBOOK'!I7)*IF(ABS('07_CONTINUOUS_CODEBOOK'!I7)<'04_CODEBOOK_CONTROL'!$B$16,1,IF(ABS('07_CONTINUOUS_CODEBOOK'!I7)<'04_CODEBOOK_CONTROL'!$B$17,2,3))) | J7: =IF(ABS('07_CONTINUOUS_CODEBOOK'!J7)<'04_CODEBOOK_CONTROL'!$B$15,0,SIGN('07_CONTINUOUS_CODEBOOK'!J7)*IF(ABS('07_CONTINUOUS_CODEBOOK'!J7)<'04_CODEBOOK_CONTROL'!$B$16,1,IF(ABS('07_CONTINUOUS_CODEBOOK'!J7)<'04_CODEBOOK_CONTROL'!$B$17,2,3))) | K7: =IF(ABS('07_CONTINUOUS_CODEBOOK'!K7)<'04_CODEBOOK_CONTROL'!$B$15,0,SIGN('07_CONTINUOUS_CODEBOOK'!K7)*IF(ABS('07_CONTINUOUS_CODEBOOK'!K7)<'04_CODEBOOK_CONTROL'!$B$16,1,IF(ABS('07_CONTINUOUS_CODEBOOK'!K7)<'04_CODEBOOK_CONTROL'!$B$17,2,3))) | ... CE7: =IF(ABS('07_CONTINUOUS_CODEBOOK'!CE7)<'04_CODEBOOK_CONTROL'!$B$15,0,SIGN('07_CONTINUOUS_CODEBOOK'!CE7)*IF(ABS('07_CONTINUOUS_CODEBOOK'!CE7)<'04_CODEBOOK_CONTROL'!$B$16,1,IF(ABS('07_CONTINUOUS_CODEBOOK'!CE7)<'04_CODEBOOK_CONTROL'!$B$17,2,3)))
A8: 4 | B8: 仙女座人 | C8: Andromedan | D8: =IF(ABS('07_CONTINUOUS_CODEBOOK'!D8)<'04_CODEBOOK_CONTROL'!$B$15,0,SIGN('07_CONTINUOUS_CODEBOOK'!D8)*IF(ABS('07_CONTINUOUS_CODEBOOK'!D8)<'04_CODEBOOK_CONTROL'!$B$16,1,IF(ABS('07_CONTINUOUS_CODEBOOK'!D8)<'04_CODEBOOK_CONTROL'!$B$17,2,3))) | E8: =IF(ABS('07_CONTINUOUS_CODEBOOK'!E8)<'04_CODEBOOK_CONTROL'!$B$15,0,SIGN('07_CONTINUOUS_CODEBOOK'!E8)*IF(ABS('07_CONTINUOUS_CODEBOOK'!E8)<'04_CODEBOOK_CONTROL'!$B$16,1,IF(ABS('07_CONTINUOUS_CODEBOOK'!E8)<'04_CODEBOOK_CONTROL'!$B$17,2,3))) | F8: =IF(ABS('07_CONTINUOUS_CODEBOOK'!F8)<'04_CODEBOOK_CONTROL'!$B$15,0,SIGN('07_CONTINUOUS_CODEBOOK'!F8)*IF(ABS('07_CONTINUOUS_CODEBOOK'!F8)<'04_CODEBOOK_CONTROL'!$B$16,1,IF(ABS('07_CONTINUOUS_CODEBOOK'!F8)<'04_CODEBOOK_CONTROL'!$B$17,2,3))) | G8: =IF(ABS('07_CONTINUOUS_CODEBOOK'!G8)<'04_CODEBOOK_CONTROL'!$B$15,0,SIGN('07_CONTINUOUS_CODEBOOK'!G8)*IF(ABS('07_CONTINUOUS_CODEBOOK'!G8)<'04_CODEBOOK_CONTROL'!$B$16,1,IF(ABS('07_CONTINUOUS_CODEBOOK'!G8)<'04_CODEBOOK_CONTROL'!$B$17,2,3))) | H8: =IF(ABS('07_CONTINUOUS_CODEBOOK'!H8)<'04_CODEBOOK_CONTROL'!$B$15,0,SIGN('07_CONTINUOUS_CODEBOOK'!H8)*IF(ABS('07_CONTINUOUS_CODEBOOK'!H8)<'04_CODEBOOK_CONTROL'!$B$16,1,IF(ABS('07_CONTINUOUS_CODEBOOK'!H8)<'04_CODEBOOK_CONTROL'!$B$17,2,3))) | I8: =IF(ABS('07_CONTINUOUS_CODEBOOK'!I8)<'04_CODEBOOK_CONTROL'!$B$15,0,SIGN('07_CONTINUOUS_CODEBOOK'!I8)*IF(ABS('07_CONTINUOUS_CODEBOOK'!I8)<'04_CODEBOOK_CONTROL'!$B$16,1,IF(ABS('07_CONTINUOUS_CODEBOOK'!I8)<'04_CODEBOOK_CONTROL'!$B$17,2,3))) | J8: =IF(ABS('07_CONTINUOUS_CODEBOOK'!J8)<'04_CODEBOOK_CONTROL'!$B$15,0,SIGN('07_CONTINUOUS_CODEBOOK'!J8)*IF(ABS('07_CONTINUOUS_CODEBOOK'!J8)<'04_CODEBOOK_CONTROL'!$B$16,1,IF(ABS('07_CONTINUOUS_CODEBOOK'!J8)<'04_CODEBOOK_CONTROL'!$B$17,2,3))) | K8: =IF(ABS('07_CONTINUOUS_CODEBOOK'!K8)<'04_CODEBOOK_CONTROL'!$B$15,0,SIGN('07_CONTINUOUS_CODEBOOK'!K8)*IF(ABS('07_CONTINUOUS_CODEBOOK'!K8)<'04_CODEBOOK_CONTROL'!$B$16,1,IF(ABS('07_CONTINUOUS_CODEBOOK'!K8)<'04_CODEBOOK_CONTROL'!$B$17,2,3))) | ... CE8: =IF(ABS('07_CONTINUOUS_CODEBOOK'!CE8)<'04_CODEBOOK_CONTROL'!$B$15,0,SIGN('07_CONTINUOUS_CODEBOOK'!CE8)*IF(ABS('07_CONTINUOUS_CODEBOOK'!CE8)<'04_CODEBOOK_CONTROL'!$B$16,1,IF(ABS('07_CONTINUOUS_CODEBOOK'!CE8)<'04_CODEBOOK_CONTROL'!$B$17,2,3)))
A9: 5 | B9: 天琴座人 | C9: Lyran | D9: =IF(ABS('07_CONTINUOUS_CODEBOOK'!D9)<'04_CODEBOOK_CONTROL'!$B$15,0,SIGN('07_CONTINUOUS_CODEBOOK'!D9)*IF(ABS('07_CONTINUOUS_CODEBOOK'!D9)<'04_CODEBOOK_CONTROL'!$B$16,1,IF(ABS('07_CONTINUOUS_CODEBOOK'!D9)<'04_CODEBOOK_CONTROL'!$B$17,2,3))) | E9: =IF(ABS('07_CONTINUOUS_CODEBOOK'!E9)<'04_CODEBOOK_CONTROL'!$B$15,0,SIGN('07_CONTINUOUS_CODEBOOK'!E9)*IF(ABS('07_CONTINUOUS_CODEBOOK'!E9)<'04_CODEBOOK_CONTROL'!$B$16,1,IF(ABS('07_CONTINUOUS_CODEBOOK'!E9)<'04_CODEBOOK_CONTROL'!$B$17,2,3))) | F9: =IF(ABS('07_CONTINUOUS_CODEBOOK'!F9)<'04_CODEBOOK_CONTROL'!$B$15,0,SIGN('07_CONTINUOUS_CODEBOOK'!F9)*IF(ABS('07_CONTINUOUS_CODEBOOK'!F9)<'04_CODEBOOK_CONTROL'!$B$16,1,IF(ABS('07_CONTINUOUS_CODEBOOK'!F9)<'04_CODEBOOK_CONTROL'!$B$17,2,3))) | G9: =IF(ABS('07_CONTINUOUS_CODEBOOK'!G9)<'04_CODEBOOK_CONTROL'!$B$15,0,SIGN('07_CONTINUOUS_CODEBOOK'!G9)*IF(ABS('07_CONTINUOUS_CODEBOOK'!G9)<'04_CODEBOOK_CONTROL'!$B$16,1,IF(ABS('07_CONTINUOUS_CODEBOOK'!G9)<'04_CODEBOOK_CONTROL'!$B$17,2,3))) | H9: =IF(ABS('07_CONTINUOUS_CODEBOOK'!H9)<'04_CODEBOOK_CONTROL'!$B$15,0,SIGN('07_CONTINUOUS_CODEBOOK'!H9)*IF(ABS('07_CONTINUOUS_CODEBOOK'!H9)<'04_CODEBOOK_CONTROL'!$B$16,1,IF(ABS('07_CONTINUOUS_CODEBOOK'!H9)<'04_CODEBOOK_CONTROL'!$B$17,2,3))) | I9: =IF(ABS('07_CONTINUOUS_CODEBOOK'!I9)<'04_CODEBOOK_CONTROL'!$B$15,0,SIGN('07_CONTINUOUS_CODEBOOK'!I9)*IF(ABS('07_CONTINUOUS_CODEBOOK'!I9)<'04_CODEBOOK_CONTROL'!$B$16,1,IF(ABS('07_CONTINUOUS_CODEBOOK'!I9)<'04_CODEBOOK_CONTROL'!$B$17,2,3))) | J9: =IF(ABS('07_CONTINUOUS_CODEBOOK'!J9)<'04_CODEBOOK_CONTROL'!$B$15,0,SIGN('07_CONTINUOUS_CODEBOOK'!J9)*IF(ABS('07_CONTINUOUS_CODEBOOK'!J9)<'04_CODEBOOK_CONTROL'!$B$16,1,IF(ABS('07_CONTINUOUS_CODEBOOK'!J9)<'04_CODEBOOK_CONTROL'!$B$17,2,3))) | K9: =IF(ABS('07_CONTINUOUS_CODEBOOK'!K9)<'04_CODEBOOK_CONTROL'!$B$15,0,SIGN('07_CONTINUOUS_CODEBOOK'!K9)*IF(ABS('07_CONTINUOUS_CODEBOOK'!K9)<'04_CODEBOOK_CONTROL'!$B$16,1,IF(ABS('07_CONTINUOUS_CODEBOOK'!K9)<'04_CODEBOOK_CONTROL'!$B$17,2,3))) | ... CE9: =IF(ABS('07_CONTINUOUS_CODEBOOK'!CE9)<'04_CODEBOOK_CONTROL'!$B$15,0,SIGN('07_CONTINUOUS_CODEBOOK'!CE9)*IF(ABS('07_CONTINUOUS_CODEBOOK'!CE9)<'04_CODEBOOK_CONTROL'!$B$16,1,IF(ABS('07_CONTINUOUS_CODEBOOK'!CE9)<'04_CODEBOOK_CONTROL'!$B$17,2,3)))
A10: 6 | B10: 獵戶座人 | C10: Orion | D10: =IF(ABS('07_CONTINUOUS_CODEBOOK'!D10)<'04_CODEBOOK_CONTROL'!$B$15,0,SIGN('07_CONTINUOUS_CODEBOOK'!D10)*IF(ABS('07_CONTINUOUS_CODEBOOK'!D10)<'04_CODEBOOK_CONTROL'!$B$16,1,IF(ABS('07_CONTINUOUS_CODEBOOK'!D10)<'04_CODEBOOK_CONTROL'!$B$17,2,3))) | E10: =IF(ABS('07_CONTINUOUS_CODEBOOK'!E10)<'04_CODEBOOK_CONTROL'!$B$15,0,SIGN('07_CONTINUOUS_CODEBOOK'!E10)*IF(ABS('07_CONTINUOUS_CODEBOOK'!E10)<'04_CODEBOOK_CONTROL'!$B$16,1,IF(ABS('07_CONTINUOUS_CODEBOOK'!E10)<'04_CODEBOOK_CONTROL'!$B$17,2,3))) | F10: =IF(ABS('07_CONTINUOUS_CODEBOOK'!F10)<'04_CODEBOOK_CONTROL'!$B$15,0,SIGN('07_CONTINUOUS_CODEBOOK'!F10)*IF(ABS('07_CONTINUOUS_CODEBOOK'!F10)<'04_CODEBOOK_CONTROL'!$B$16,1,IF(ABS('07_CONTINUOUS_CODEBOOK'!F10)<'04_CODEBOOK_CONTROL'!$B$17,2,3))) | G10: =IF(ABS('07_CONTINUOUS_CODEBOOK'!G10)<'04_CODEBOOK_CONTROL'!$B$15,0,SIGN('07_CONTINUOUS_CODEBOOK'!G10)*IF(ABS('07_CONTINUOUS_CODEBOOK'!G10)<'04_CODEBOOK_CONTROL'!$B$16,1,IF(ABS('07_CONTINUOUS_CODEBOOK'!G10)<'04_CODEBOOK_CONTROL'!$B$17,2,3))) | H10: =IF(ABS('07_CONTINUOUS_CODEBOOK'!H10)<'04_CODEBOOK_CONTROL'!$B$15,0,SIGN('07_CONTINUOUS_CODEBOOK'!H10)*IF(ABS('07_CONTINUOUS_CODEBOOK'!H10)<'04_CODEBOOK_CONTROL'!$B$16,1,IF(ABS('07_CONTINUOUS_CODEBOOK'!H10)<'04_CODEBOOK_CONTROL'!$B$17,2,3))) | I10: =IF(ABS('07_CONTINUOUS_CODEBOOK'!I10)<'04_CODEBOOK_CONTROL'!$B$15,0,SIGN('07_CONTINUOUS_CODEBOOK'!I10)*IF(ABS('07_CONTINUOUS_CODEBOOK'!I10)<'04_CODEBOOK_CONTROL'!$B$16,1,IF(ABS('07_CONTINUOUS_CODEBOOK'!I10)<'04_CODEBOOK_CONTROL'!$B$17,2,3))) | J10: =IF(ABS('07_CONTINUOUS_CODEBOOK'!J10)<'04_CODEBOOK_CONTROL'!$B$15,0,SIGN('07_CONTINUOUS_CODEBOOK'!J10)*IF(ABS('07_CONTINUOUS_CODEBOOK'!J10)<'04_CODEBOOK_CONTROL'!$B$16,1,IF(ABS('07_CONTINUOUS_CODEBOOK'!J10)<'04_CODEBOOK_CONTROL'!$B$17,2,3))) | K10: =IF(ABS('07_CONTINUOUS_CODEBOOK'!K10)<'04_CODEBOOK_CONTROL'!$B$15,0,SIGN('07_CONTINUOUS_CODEBOOK'!K10)*IF(ABS('07_CONTINUOUS_CODEBOOK'!K10)<'04_CODEBOOK_CONTROL'!$B$16,1,IF(ABS('07_CONTINUOUS_CODEBOOK'!K10)<'04_CODEBOOK_CONTROL'!$B$17,2,3))) | ... CE10: =IF(ABS('07_CONTINUOUS_CODEBOOK'!CE10)<'04_CODEBOOK_CONTROL'!$B$15,0,SIGN('07_CONTINUOUS_CODEBOOK'!CE10)*IF(ABS('07_CONTINUOUS_CODEBOOK'!CE10)<'04_CODEBOOK_CONTROL'!$B$16,1,IF(ABS('07_CONTINUOUS_CODEBOOK'!CE10)<'04_CODEBOOK_CONTROL'!$B$17,2,3)))
A11: 7 | B11: 明塔卡星人 | C11: Mintakan | D11: =IF(ABS('07_CONTINUOUS_CODEBOOK'!D11)<'04_CODEBOOK_CONTROL'!$B$15,0,SIGN('07_CONTINUOUS_CODEBOOK'!D11)*IF(ABS('07_CONTINUOUS_CODEBOOK'!D11)<'04_CODEBOOK_CONTROL'!$B$16,1,IF(ABS('07_CONTINUOUS_CODEBOOK'!D11)<'04_CODEBOOK_CONTROL'!$B$17,2,3))) | E11: =IF(ABS('07_CONTINUOUS_CODEBOOK'!E11)<'04_CODEBOOK_CONTROL'!$B$15,0,SIGN('07_CONTINUOUS_CODEBOOK'!E11)*IF(ABS('07_CONTINUOUS_CODEBOOK'!E11)<'04_CODEBOOK_CONTROL'!$B$16,1,IF(ABS('07_CONTINUOUS_CODEBOOK'!E11)<'04_CODEBOOK_CONTROL'!$B$17,2,3))) | F11: =IF(ABS('07_CONTINUOUS_CODEBOOK'!F11)<'04_CODEBOOK_CONTROL'!$B$15,0,SIGN('07_CONTINUOUS_CODEBOOK'!F11)*IF(ABS('07_CONTINUOUS_CODEBOOK'!F11)<'04_CODEBOOK_CONTROL'!$B$16,1,IF(ABS('07_CONTINUOUS_CODEBOOK'!F11)<'04_CODEBOOK_CONTROL'!$B$17,2,3))) | G11: =IF(ABS('07_CONTINUOUS_CODEBOOK'!G11)<'04_CODEBOOK_CONTROL'!$B$15,0,SIGN('07_CONTINUOUS_CODEBOOK'!G11)*IF(ABS('07_CONTINUOUS_CODEBOOK'!G11)<'04_CODEBOOK_CONTROL'!$B$16,1,IF(ABS('07_CONTINUOUS_CODEBOOK'!G11)<'04_CODEBOOK_CONTROL'!$B$17,2,3))) | H11: =IF(ABS('07_CONTINUOUS_CODEBOOK'!H11)<'04_CODEBOOK_CONTROL'!$B$15,0,SIGN('07_CONTINUOUS_CODEBOOK'!H11)*IF(ABS('07_CONTINUOUS_CODEBOOK'!H11)<'04_CODEBOOK_CONTROL'!$B$16,1,IF(ABS('07_CONTINUOUS_CODEBOOK'!H11)<'04_CODEBOOK_CONTROL'!$B$17,2,3))) | I11: =IF(ABS('07_CONTINUOUS_CODEBOOK'!I11)<'04_CODEBOOK_CONTROL'!$B$15,0,SIGN('07_CONTINUOUS_CODEBOOK'!I11)*IF(ABS('07_CONTINUOUS_CODEBOOK'!I11)<'04_CODEBOOK_CONTROL'!$B$16,1,IF(ABS('07_CONTINUOUS_CODEBOOK'!I11)<'04_CODEBOOK_CONTROL'!$B$17,2,3))) | J11: =IF(ABS('07_CONTINUOUS_CODEBOOK'!J11)<'04_CODEBOOK_CONTROL'!$B$15,0,SIGN('07_CONTINUOUS_CODEBOOK'!J11)*IF(ABS('07_CONTINUOUS_CODEBOOK'!J11)<'04_CODEBOOK_CONTROL'!$B$16,1,IF(ABS('07_CONTINUOUS_CODEBOOK'!J11)<'04_CODEBOOK_CONTROL'!$B$17,2,3))) | K11: =IF(ABS('07_CONTINUOUS_CODEBOOK'!K11)<'04_CODEBOOK_CONTROL'!$B$15,0,SIGN('07_CONTINUOUS_CODEBOOK'!K11)*IF(ABS('07_CONTINUOUS_CODEBOOK'!K11)<'04_CODEBOOK_CONTROL'!$B$16,1,IF(ABS('07_CONTINUOUS_CODEBOOK'!K11)<'04_CODEBOOK_CONTROL'!$B$17,2,3))) | ... CE11: =IF(ABS('07_CONTINUOUS_CODEBOOK'!CE11)<'04_CODEBOOK_CONTROL'!$B$15,0,SIGN('07_CONTINUOUS_CODEBOOK'!CE11)*IF(ABS('07_CONTINUOUS_CODEBOOK'!CE11)<'04_CODEBOOK_CONTROL'!$B$16,1,IF(ABS('07_CONTINUOUS_CODEBOOK'!CE11)<'04_CODEBOOK_CONTROL'!$B$17,2,3)))
A12: 8 | B12: 金星人 | C12: Venusian | D12: =IF(ABS('07_CONTINUOUS_CODEBOOK'!D12)<'04_CODEBOOK_CONTROL'!$B$15,0,SIGN('07_CONTINUOUS_CODEBOOK'!D12)*IF(ABS('07_CONTINUOUS_CODEBOOK'!D12)<'04_CODEBOOK_CONTROL'!$B$16,1,IF(ABS('07_CONTINUOUS_CODEBOOK'!D12)<'04_CODEBOOK_CONTROL'!$B$17,2,3))) | E12: =IF(ABS('07_CONTINUOUS_CODEBOOK'!E12)<'04_CODEBOOK_CONTROL'!$B$15,0,SIGN('07_CONTINUOUS_CODEBOOK'!E12)*IF(ABS('07_CONTINUOUS_CODEBOOK'!E12)<'04_CODEBOOK_CONTROL'!$B$16,1,IF(ABS('07_CONTINUOUS_CODEBOOK'!E12)<'04_CODEBOOK_CONTROL'!$B$17,2,3))) | F12: =IF(ABS('07_CONTINUOUS_CODEBOOK'!F12)<'04_CODEBOOK_CONTROL'!$B$15,0,SIGN('07_CONTINUOUS_CODEBOOK'!F12)*IF(ABS('07_CONTINUOUS_CODEBOOK'!F12)<'04_CODEBOOK_CONTROL'!$B$16,1,IF(ABS('07_CONTINUOUS_CODEBOOK'!F12)<'04_CODEBOOK_CONTROL'!$B$17,2,3))) | G12: =IF(ABS('07_CONTINUOUS_CODEBOOK'!G12)<'04_CODEBOOK_CONTROL'!$B$15,0,SIGN('07_CONTINUOUS_CODEBOOK'!G12)*IF(ABS('07_CONTINUOUS_CODEBOOK'!G12)<'04_CODEBOOK_CONTROL'!$B$16,1,IF(ABS('07_CONTINUOUS_CODEBOOK'!G12)<'04_CODEBOOK_CONTROL'!$B$17,2,3))) | H12: =IF(ABS('07_CONTINUOUS_CODEBOOK'!H12)<'04_CODEBOOK_CONTROL'!$B$15,0,SIGN('07_CONTINUOUS_CODEBOOK'!H12)*IF(ABS('07_CONTINUOUS_CODEBOOK'!H12)<'04_CODEBOOK_CONTROL'!$B$16,1,IF(ABS('07_CONTINUOUS_CODEBOOK'!H12)<'04_CODEBOOK_CONTROL'!$B$17,2,3))) | I12: =IF(ABS('07_CONTINUOUS_CODEBOOK'!I12)<'04_CODEBOOK_CONTROL'!$B$15,0,SIGN('07_CONTINUOUS_CODEBOOK'!I12)*IF(ABS('07_CONTINUOUS_CODEBOOK'!I12)<'04_CODEBOOK_CONTROL'!$B$16,1,IF(ABS('07_CONTINUOUS_CODEBOOK'!I12)<'04_CODEBOOK_CONTROL'!$B$17,2,3))) | J12: =IF(ABS('07_CONTINUOUS_CODEBOOK'!J12)<'04_CODEBOOK_CONTROL'!$B$15,0,SIGN('07_CONTINUOUS_CODEBOOK'!J12)*IF(ABS('07_CONTINUOUS_CODEBOOK'!J12)<'04_CODEBOOK_CONTROL'!$B$16,1,IF(ABS('07_CONTINUOUS_CODEBOOK'!J12)<'04_CODEBOOK_CONTROL'!$B$17,2,3))) | K12: =IF(ABS('07_CONTINUOUS_CODEBOOK'!K12)<'04_CODEBOOK_CONTROL'!$B$15,0,SIGN('07_CONTINUOUS_CODEBOOK'!K12)*IF(ABS('07_CONTINUOUS_CODEBOOK'!K12)<'04_CODEBOOK_CONTROL'!$B$16,1,IF(ABS('07_CONTINUOUS_CODEBOOK'!K12)<'04_CODEBOOK_CONTROL'!$B$17,2,3))) | ... CE12: =IF(ABS('07_CONTINUOUS_CODEBOOK'!CE12)<'04_CODEBOOK_CONTROL'!$B$15,0,SIGN('07_CONTINUOUS_CODEBOOK'!CE12)*IF(ABS('07_CONTINUOUS_CODEBOOK'!CE12)<'04_CODEBOOK_CONTROL'!$B$16,1,IF(ABS('07_CONTINUOUS_CODEBOOK'!CE12)<'04_CODEBOOK_CONTROL'!$B$17,2,3)))
A13: 9 | B13: 哈達爾星人 | C13: Hadarian | D13: =IF(ABS('07_CONTINUOUS_CODEBOOK'!D13)<'04_CODEBOOK_CONTROL'!$B$15,0,SIGN('07_CONTINUOUS_CODEBOOK'!D13)*IF(ABS('07_CONTINUOUS_CODEBOOK'!D13)<'04_CODEBOOK_CONTROL'!$B$16,1,IF(ABS('07_CONTINUOUS_CODEBOOK'!D13)<'04_CODEBOOK_CONTROL'!$B$17,2,3))) | E13: =IF(ABS('07_CONTINUOUS_CODEBOOK'!E13)<'04_CODEBOOK_CONTROL'!$B$15,0,SIGN('07_CONTINUOUS_CODEBOOK'!E13)*IF(ABS('07_CONTINUOUS_CODEBOOK'!E13)<'04_CODEBOOK_CONTROL'!$B$16,1,IF(ABS('07_CONTINUOUS_CODEBOOK'!E13)<'04_CODEBOOK_CONTROL'!$B$17,2,3))) | F13: =IF(ABS('07_CONTINUOUS_CODEBOOK'!F13)<'04_CODEBOOK_CONTROL'!$B$15,0,SIGN('07_CONTINUOUS_CODEBOOK'!F13)*IF(ABS('07_CONTINUOUS_CODEBOOK'!F13)<'04_CODEBOOK_CONTROL'!$B$16,1,IF(ABS('07_CONTINUOUS_CODEBOOK'!F13)<'04_CODEBOOK_CONTROL'!$B$17,2,3))) | G13: =IF(ABS('07_CONTINUOUS_CODEBOOK'!G13)<'04_CODEBOOK_CONTROL'!$B$15,0,SIGN('07_CONTINUOUS_CODEBOOK'!G13)*IF(ABS('07_CONTINUOUS_CODEBOOK'!G13)<'04_CODEBOOK_CONTROL'!$B$16,1,IF(ABS('07_CONTINUOUS_CODEBOOK'!G13)<'04_CODEBOOK_CONTROL'!$B$17,2,3))) | H13: =IF(ABS('07_CONTINUOUS_CODEBOOK'!H13)<'04_CODEBOOK_CONTROL'!$B$15,0,SIGN('07_CONTINUOUS_CODEBOOK'!H13)*IF(ABS('07_CONTINUOUS_CODEBOOK'!H13)<'04_CODEBOOK_CONTROL'!$B$16,1,IF(ABS('07_CONTINUOUS_CODEBOOK'!H13)<'04_CODEBOOK_CONTROL'!$B$17,2,3))) | I13: =IF(ABS('07_CONTINUOUS_CODEBOOK'!I13)<'04_CODEBOOK_CONTROL'!$B$15,0,SIGN('07_CONTINUOUS_CODEBOOK'!I13)*IF(ABS('07_CONTINUOUS_CODEBOOK'!I13)<'04_CODEBOOK_CONTROL'!$B$16,1,IF(ABS('07_CONTINUOUS_CODEBOOK'!I13)<'04_CODEBOOK_CONTROL'!$B$17,2,3))) | J13: =IF(ABS('07_CONTINUOUS_CODEBOOK'!J13)<'04_CODEBOOK_CONTROL'!$B$15,0,SIGN('07_CONTINUOUS_CODEBOOK'!J13)*IF(ABS('07_CONTINUOUS_CODEBOOK'!J13)<'04_CODEBOOK_CONTROL'!$B$16,1,IF(ABS('07_CONTINUOUS_CODEBOOK'!J13)<'04_CODEBOOK_CONTROL'!$B$17,2,3))) | K13: =IF(ABS('07_CONTINUOUS_CODEBOOK'!K13)<'04_CODEBOOK_CONTROL'!$B$15,0,SIGN('07_CONTINUOUS_CODEBOOK'!K13)*IF(ABS('07_CONTINUOUS_CODEBOOK'!K13)<'04_CODEBOOK_CONTROL'!$B$16,1,IF(ABS('07_CONTINUOUS_CODEBOOK'!K13)<'04_CODEBOOK_CONTROL'!$B$17,2,3))) | ... CE13: =IF(ABS('07_CONTINUOUS_CODEBOOK'!CE13)<'04_CODEBOOK_CONTROL'!$B$15,0,SIGN('07_CONTINUOUS_CODEBOOK'!CE13)*IF(ABS('07_CONTINUOUS_CODEBOOK'!CE13)<'04_CODEBOOK_CONTROL'!$B$16,1,IF(ABS('07_CONTINUOUS_CODEBOOK'!CE13)<'04_CODEBOOK_CONTROL'!$B$17,2,3)))
A14: 10 | B14: 北極星人 | C14: Polarian | D14: =IF(ABS('07_CONTINUOUS_CODEBOOK'!D14)<'04_CODEBOOK_CONTROL'!$B$15,0,SIGN('07_CONTINUOUS_CODEBOOK'!D14)*IF(ABS('07_CONTINUOUS_CODEBOOK'!D14)<'04_CODEBOOK_CONTROL'!$B$16,1,IF(ABS('07_CONTINUOUS_CODEBOOK'!D14)<'04_CODEBOOK_CONTROL'!$B$17,2,3))) | E14: =IF(ABS('07_CONTINUOUS_CODEBOOK'!E14)<'04_CODEBOOK_CONTROL'!$B$15,0,SIGN('07_CONTINUOUS_CODEBOOK'!E14)*IF(ABS('07_CONTINUOUS_CODEBOOK'!E14)<'04_CODEBOOK_CONTROL'!$B$16,1,IF(ABS('07_CONTINUOUS_CODEBOOK'!E14)<'04_CODEBOOK_CONTROL'!$B$17,2,3))) | F14: =IF(ABS('07_CONTINUOUS_CODEBOOK'!F14)<'04_CODEBOOK_CONTROL'!$B$15,0,SIGN('07_CONTINUOUS_CODEBOOK'!F14)*IF(ABS('07_CONTINUOUS_CODEBOOK'!F14)<'04_CODEBOOK_CONTROL'!$B$16,1,IF(ABS('07_CONTINUOUS_CODEBOOK'!F14)<'04_CODEBOOK_CONTROL'!$B$17,2,3))) | G14: =IF(ABS('07_CONTINUOUS_CODEBOOK'!G14)<'04_CODEBOOK_CONTROL'!$B$15,0,SIGN('07_CONTINUOUS_CODEBOOK'!G14)*IF(ABS('07_CONTINUOUS_CODEBOOK'!G14)<'04_CODEBOOK_CONTROL'!$B$16,1,IF(ABS('07_CONTINUOUS_CODEBOOK'!G14)<'04_CODEBOOK_CONTROL'!$B$17,2,3))) | H14: =IF(ABS('07_CONTINUOUS_CODEBOOK'!H14)<'04_CODEBOOK_CONTROL'!$B$15,0,SIGN('07_CONTINUOUS_CODEBOOK'!H14)*IF(ABS('07_CONTINUOUS_CODEBOOK'!H14)<'04_CODEBOOK_CONTROL'!$B$16,1,IF(ABS('07_CONTINUOUS_CODEBOOK'!H14)<'04_CODEBOOK_CONTROL'!$B$17,2,3))) | I14: =IF(ABS('07_CONTINUOUS_CODEBOOK'!I14)<'04_CODEBOOK_CONTROL'!$B$15,0,SIGN('07_CONTINUOUS_CODEBOOK'!I14)*IF(ABS('07_CONTINUOUS_CODEBOOK'!I14)<'04_CODEBOOK_CONTROL'!$B$16,1,IF(ABS('07_CONTINUOUS_CODEBOOK'!I14)<'04_CODEBOOK_CONTROL'!$B$17,2,3))) | J14: =IF(ABS('07_CONTINUOUS_CODEBOOK'!J14)<'04_CODEBOOK_CONTROL'!$B$15,0,SIGN('07_CONTINUOUS_CODEBOOK'!J14)*IF(ABS('07_CONTINUOUS_CODEBOOK'!J14)<'04_CODEBOOK_CONTROL'!$B$16,1,IF(ABS('07_CONTINUOUS_CODEBOOK'!J14)<'04_CODEBOOK_CONTROL'!$B$17,2,3))) | K14: =IF(ABS('07_CONTINUOUS_CODEBOOK'!K14)<'04_CODEBOOK_CONTROL'!$B$15,0,SIGN('07_CONTINUOUS_CODEBOOK'!K14)*IF(ABS('07_CONTINUOUS_CODEBOOK'!K14)<'04_CODEBOOK_CONTROL'!$B$16,1,IF(ABS('07_CONTINUOUS_CODEBOOK'!K14)<'04_CODEBOOK_CONTROL'!$B$17,2,3))) | ... CE14: =IF(ABS('07_CONTINUOUS_CODEBOOK'!CE14)<'04_CODEBOOK_CONTROL'!$B$15,0,SIGN('07_CONTINUOUS_CODEBOOK'!CE14)*IF(ABS('07_CONTINUOUS_CODEBOOK'!CE14)<'04_CODEBOOK_CONTROL'!$B$16,1,IF(ABS('07_CONTINUOUS_CODEBOOK'!CE14)<'04_CODEBOOK_CONTROL'!$B$17,2,3)))
A15: 11 | B15: 半人馬座α星人 | C15: Alpha Centaurian | D15: =IF(ABS('07_CONTINUOUS_CODEBOOK'!D15)<'04_CODEBOOK_CONTROL'!$B$15,0,SIGN('07_CONTINUOUS_CODEBOOK'!D15)*IF(ABS('07_CONTINUOUS_CODEBOOK'!D15)<'04_CODEBOOK_CONTROL'!$B$16,1,IF(ABS('07_CONTINUOUS_CODEBOOK'!D15)<'04_CODEBOOK_CONTROL'!$B$17,2,3))) | E15: =IF(ABS('07_CONTINUOUS_CODEBOOK'!E15)<'04_CODEBOOK_CONTROL'!$B$15,0,SIGN('07_CONTINUOUS_CODEBOOK'!E15)*IF(ABS('07_CONTINUOUS_CODEBOOK'!E15)<'04_CODEBOOK_CONTROL'!$B$16,1,IF(ABS('07_CONTINUOUS_CODEBOOK'!E15)<'04_CODEBOOK_CONTROL'!$B$17,2,3))) | F15: =IF(ABS('07_CONTINUOUS_CODEBOOK'!F15)<'04_CODEBOOK_CONTROL'!$B$15,0,SIGN('07_CONTINUOUS_CODEBOOK'!F15)*IF(ABS('07_CONTINUOUS_CODEBOOK'!F15)<'04_CODEBOOK_CONTROL'!$B$16,1,IF(ABS('07_CONTINUOUS_CODEBOOK'!F15)<'04_CODEBOOK_CONTROL'!$B$17,2,3))) | G15: =IF(ABS('07_CONTINUOUS_CODEBOOK'!G15)<'04_CODEBOOK_CONTROL'!$B$15,0,SIGN('07_CONTINUOUS_CODEBOOK'!G15)*IF(ABS('07_CONTINUOUS_CODEBOOK'!G15)<'04_CODEBOOK_CONTROL'!$B$16,1,IF(ABS('07_CONTINUOUS_CODEBOOK'!G15)<'04_CODEBOOK_CONTROL'!$B$17,2,3))) | H15: =IF(ABS('07_CONTINUOUS_CODEBOOK'!H15)<'04_CODEBOOK_CONTROL'!$B$15,0,SIGN('07_CONTINUOUS_CODEBOOK'!H15)*IF(ABS('07_CONTINUOUS_CODEBOOK'!H15)<'04_CODEBOOK_CONTROL'!$B$16,1,IF(ABS('07_CONTINUOUS_CODEBOOK'!H15)<'04_CODEBOOK_CONTROL'!$B$17,2,3))) | I15: =IF(ABS('07_CONTINUOUS_CODEBOOK'!I15)<'04_CODEBOOK_CONTROL'!$B$15,0,SIGN('07_CONTINUOUS_CODEBOOK'!I15)*IF(ABS('07_CONTINUOUS_CODEBOOK'!I15)<'04_CODEBOOK_CONTROL'!$B$16,1,IF(ABS('07_CONTINUOUS_CODEBOOK'!I15)<'04_CODEBOOK_CONTROL'!$B$17,2,3))) | J15: =IF(ABS('07_CONTINUOUS_CODEBOOK'!J15)<'04_CODEBOOK_CONTROL'!$B$15,0,SIGN('07_CONTINUOUS_CODEBOOK'!J15)*IF(ABS('07_CONTINUOUS_CODEBOOK'!J15)<'04_CODEBOOK_CONTROL'!$B$16,1,IF(ABS('07_CONTINUOUS_CODEBOOK'!J15)<'04_CODEBOOK_CONTROL'!$B$17,2,3))) | K15: =IF(ABS('07_CONTINUOUS_CODEBOOK'!K15)<'04_CODEBOOK_CONTROL'!$B$15,0,SIGN('07_CONTINUOUS_CODEBOOK'!K15)*IF(ABS('07_CONTINUOUS_CODEBOOK'!K15)<'04_CODEBOOK_CONTROL'!$B$16,1,IF(ABS('07_CONTINUOUS_CODEBOOK'!K15)<'04_CODEBOOK_CONTROL'!$B$17,2,3))) | ... CE15: =IF(ABS('07_CONTINUOUS_CODEBOOK'!CE15)<'04_CODEBOOK_CONTROL'!$B$15,0,SIGN('07_CONTINUOUS_CODEBOOK'!CE15)*IF(ABS('07_CONTINUOUS_CODEBOOK'!CE15)<'04_CODEBOOK_CONTROL'!$B$16,1,IF(ABS('07_CONTINUOUS_CODEBOOK'!CE15)<'04_CODEBOOK_CONTROL'!$B$17,2,3)))
A16: 12 | B16: 織女星人 | C16: Vegan | D16: =IF(ABS('07_CONTINUOUS_CODEBOOK'!D16)<'04_CODEBOOK_CONTROL'!$B$15,0,SIGN('07_CONTINUOUS_CODEBOOK'!D16)*IF(ABS('07_CONTINUOUS_CODEBOOK'!D16)<'04_CODEBOOK_CONTROL'!$B$16,1,IF(ABS('07_CONTINUOUS_CODEBOOK'!D16)<'04_CODEBOOK_CONTROL'!$B$17,2,3))) | E16: =IF(ABS('07_CONTINUOUS_CODEBOOK'!E16)<'04_CODEBOOK_CONTROL'!$B$15,0,SIGN('07_CONTINUOUS_CODEBOOK'!E16)*IF(ABS('07_CONTINUOUS_CODEBOOK'!E16)<'04_CODEBOOK_CONTROL'!$B$16,1,IF(ABS('07_CONTINUOUS_CODEBOOK'!E16)<'04_CODEBOOK_CONTROL'!$B$17,2,3))) | F16: =IF(ABS('07_CONTINUOUS_CODEBOOK'!F16)<'04_CODEBOOK_CONTROL'!$B$15,0,SIGN('07_CONTINUOUS_CODEBOOK'!F16)*IF(ABS('07_CONTINUOUS_CODEBOOK'!F16)<'04_CODEBOOK_CONTROL'!$B$16,1,IF(ABS('07_CONTINUOUS_CODEBOOK'!F16)<'04_CODEBOOK_CONTROL'!$B$17,2,3))) | G16: =IF(ABS('07_CONTINUOUS_CODEBOOK'!G16)<'04_CODEBOOK_CONTROL'!$B$15,0,SIGN('07_CONTINUOUS_CODEBOOK'!G16)*IF(ABS('07_CONTINUOUS_CODEBOOK'!G16)<'04_CODEBOOK_CONTROL'!$B$16,1,IF(ABS('07_CONTINUOUS_CODEBOOK'!G16)<'04_CODEBOOK_CONTROL'!$B$17,2,3))) | H16: =IF(ABS('07_CONTINUOUS_CODEBOOK'!H16)<'04_CODEBOOK_CONTROL'!$B$15,0,SIGN('07_CONTINUOUS_CODEBOOK'!H16)*IF(ABS('07_CONTINUOUS_CODEBOOK'!H16)<'04_CODEBOOK_CONTROL'!$B$16,1,IF(ABS('07_CONTINUOUS_CODEBOOK'!H16)<'04_CODEBOOK_CONTROL'!$B$17,2,3))) | I16: =IF(ABS('07_CONTINUOUS_CODEBOOK'!I16)<'04_CODEBOOK_CONTROL'!$B$15,0,SIGN('07_CONTINUOUS_CODEBOOK'!I16)*IF(ABS('07_CONTINUOUS_CODEBOOK'!I16)<'04_CODEBOOK_CONTROL'!$B$16,1,IF(ABS('07_CONTINUOUS_CODEBOOK'!I16)<'04_CODEBOOK_CONTROL'!$B$17,2,3))) | J16: =IF(ABS('07_CONTINUOUS_CODEBOOK'!J16)<'04_CODEBOOK_CONTROL'!$B$15,0,SIGN('07_CONTINUOUS_CODEBOOK'!J16)*IF(ABS('07_CONTINUOUS_CODEBOOK'!J16)<'04_CODEBOOK_CONTROL'!$B$16,1,IF(ABS('07_CONTINUOUS_CODEBOOK'!J16)<'04_CODEBOOK_CONTROL'!$B$17,2,3))) | K16: =IF(ABS('07_CONTINUOUS_CODEBOOK'!K16)<'04_CODEBOOK_CONTROL'!$B$15,0,SIGN('07_CONTINUOUS_CODEBOOK'!K16)*IF(ABS('07_CONTINUOUS_CODEBOOK'!K16)<'04_CODEBOOK_CONTROL'!$B$16,1,IF(ABS('07_CONTINUOUS_CODEBOOK'!K16)<'04_CODEBOOK_CONTROL'!$B$17,2,3))) | ... CE16: =IF(ABS('07_CONTINUOUS_CODEBOOK'!CE16)<'04_CODEBOOK_CONTROL'!$B$15,0,SIGN('07_CONTINUOUS_CODEBOOK'!CE16)*IF(ABS('07_CONTINUOUS_CODEBOOK'!CE16)<'04_CODEBOOK_CONTROL'!$B$16,1,IF(ABS('07_CONTINUOUS_CODEBOOK'!CE16)<'04_CODEBOOK_CONTROL'!$B$17,2,3)))
... A27: 23 | B27: 地球源靈魂 | C27: Earth-Origin Soul | D27: =IF(ABS('07_CONTINUOUS_CODEBOOK'!D27)<'04_CODEBOOK_CONTROL'!$B$15,0,SIGN('07_CONTINUOUS_CODEBOOK'!D27)*IF(ABS('07_CONTINUOUS_CODEBOOK'!D27)<'04_CODEBOOK_CONTROL'!$B$16,1,IF(ABS('07_CONTINUOUS_CODEBOOK'!D27)<'04_CODEBOOK_CONTROL'!$B$17,2,3))) | E27: =IF(ABS('07_CONTINUOUS_CODEBOOK'!E27)<'04_CODEBOOK_CONTROL'!$B$15,0,SIGN('07_CONTINUOUS_CODEBOOK'!E27)*IF(ABS('07_CONTINUOUS_CODEBOOK'!E27)<'04_CODEBOOK_CONTROL'!$B$16,1,IF(ABS('07_CONTINUOUS_CODEBOOK'!E27)<'04_CODEBOOK_CONTROL'!$B$17,2,3))) | F27: =IF(ABS('07_CONTINUOUS_CODEBOOK'!F27)<'04_CODEBOOK_CONTROL'!$B$15,0,SIGN('07_CONTINUOUS_CODEBOOK'!F27)*IF(ABS('07_CONTINUOUS_CODEBOOK'!F27)<'04_CODEBOOK_CONTROL'!$B$16,1,IF(ABS('07_CONTINUOUS_CODEBOOK'!F27)<'04_CODEBOOK_CONTROL'!$B$17,2,3))) | G27: =IF(ABS('07_CONTINUOUS_CODEBOOK'!G27)<'04_CODEBOOK_CONTROL'!$B$15,0,SIGN('07_CONTINUOUS_CODEBOOK'!G27)*IF(ABS('07_CONTINUOUS_CODEBOOK'!G27)<'04_CODEBOOK_CONTROL'!$B$16,1,IF(ABS('07_CONTINUOUS_CODEBOOK'!G27)<'04_CODEBOOK_CONTROL'!$B$17,2,3))) | H27: =IF(ABS('07_CONTINUOUS_CODEBOOK'!H27)<'04_CODEBOOK_CONTROL'!$B$15,0,SIGN('07_CONTINUOUS_CODEBOOK'!H27)*IF(ABS('07_CONTINUOUS_CODEBOOK'!H27)<'04_CODEBOOK_CONTROL'!$B$16,1,IF(ABS('07_CONTINUOUS_CODEBOOK'!H27)<'04_CODEBOOK_CONTROL'!$B$17,2,3))) | I27: =IF(ABS('07_CONTINUOUS_CODEBOOK'!I27)<'04_CODEBOOK_CONTROL'!$B$15,0,SIGN('07_CONTINUOUS_CODEBOOK'!I27)*IF(ABS('07_CONTINUOUS_CODEBOOK'!I27)<'04_CODEBOOK_CONTROL'!$B$16,1,IF(ABS('07_CONTINUOUS_CODEBOOK'!I27)<'04_CODEBOOK_CONTROL'!$B$17,2,3))) | J27: =IF(ABS('07_CONTINUOUS_CODEBOOK'!J27)<'04_CODEBOOK_CONTROL'!$B$15,0,SIGN('07_CONTINUOUS_CODEBOOK'!J27)*IF(ABS('07_CONTINUOUS_CODEBOOK'!J27)<'04_CODEBOOK_CONTROL'!$B$16,1,IF(ABS('07_CONTINUOUS_CODEBOOK'!J27)<'04_CODEBOOK_CONTROL'!$B$17,2,3))) | K27: =IF(ABS('07_CONTINUOUS_CODEBOOK'!K27)<'04_CODEBOOK_CONTROL'!$B$15,0,SIGN('07_CONTINUOUS_CODEBOOK'!K27)*IF(ABS('07_CONTINUOUS_CODEBOOK'!K27)<'04_CODEBOOK_CONTROL'!$B$16,1,IF(ABS('07_CONTINUOUS_CODEBOOK'!K27)<'04_CODEBOOK_CONTROL'!$B$17,2,3))) | ... CE27: =IF(ABS('07_CONTINUOUS_CODEBOOK'!CE27)<'04_CODEBOOK_CONTROL'!$B$15,0,SIGN('07_CONTINUOUS_CODEBOOK'!CE27)*IF(ABS('07_CONTINUOUS_CODEBOOK'!CE27)<'04_CODEBOOK_CONTROL'!$B$16,1,IF(ABS('07_CONTINUOUS_CODEBOOK'!CE27)<'04_CODEBOOK_CONTROL'!$B$17,2,3)))

Sheet 09_ADMIN_ORDER_CODEBOOK
A1: Codebook in Q1…Q80 Administration Order — v4.4 PUBLIC WORDING FINAL
A2: Raw UI answer is left/right signed; convert to canonical x = raw × key before scoring.
A4: Q# | B4: Slot | C4: Stem | D4: Left | E4: Right | F4: Key | G4: Canonical rule | H4: Pleiadian | I4: Arcturian | J4: Sirian | K4: Andromedan | L4: Lyran | M4: Orion | N4: Mintakan | O4: Venusian | P4: Hadarian | Q4: Polarian | R4: Alpha Centaurian | S4: Vegan | T4: Feline / Urmah | U4: Avian / Blue Avian | V4: Martian | W4: Maldekian | X4: Draconian | Y4: Reptilian | Z4: Zeta / Grey | AA4: Anunnaki / Nibiruan | AB4: Tau Cetian | AC4: Antarian | AD4: Earth-Origin Soul | AE4: Final weight v4
A5: 1 | B5: G17 | C5: 當一個你參與的共同計畫開始偏離你認同的方向時，你比較自然會…… | D5: 離開這個不適合自己的安排，改由自己決定下一步 | E5: 留下來，守住你認為重要的人和事 | F5: 1 | G5: x=raw×key | H5: 0 | I5: -1 | J5: 2 | K5: -2 | L5: -1 | M5: 0 | N5: 1 | O5: 0 | P5: 0 | Q5: 2 | R5: 1 | S5: -2 | T5: 1 | U5: -2 | V5: 1 | W5: 1 | X5: 2 | Y5: 1 | Z5: 0 | AA5: 2 | AB5: 0 | AC5: 1 | AD5: 2 | AE5: =INDEX('24_FINAL_ITEM_WEIGHTS'!$I$5:$I$84,MATCH(B5,'24_FINAL_ITEM_WEIGHTS'!$A$5:$A$84,0))
A6: 2 | B6: L05 | C6: 當一個空間讓你覺得不太對勁時，你比較想怎麼調整？ | D6: 用顏色、材質和擺設增加層次，讓整體氣氛更豐富和諧 | E6: 減少刺激和雜亂，讓空間回到簡單、清楚又安定的感覺 | F6: -1 | G6: x=raw×key | H6: 1 | I6: 1 | J6: 1 | K6: 1 | L6: 1 | M6: 1 | N6: -3 | O6: 3 | P6: 1 | Q6: 1 | R6: 0 | S6: 2 | T6: 1 | U6: 1 | V6: 0 | W6: 0 | X6: 0 | Y6: 0 | Z6: 0 | AA6: 0 | AB6: 1 | AC6: 0 | AD6: 3 | AE6: =INDEX('24_FINAL_ITEM_WEIGHTS'!$I$5:$I$84,MATCH(B6,'24_FINAL_ITEM_WEIGHTS'!$A$5:$A$84,0))
A7: 3 | B7: G13 | C7: 當新的人想加入你正在維持的小圈子或合作小組時，你通常會…… | D7: 先讓對方參與一些基本的事，再按實際相處調整參與範圍 | E7: 先不要讓對方參與太多，觀察彼此是否合適後再慢慢開放 | F7: 1 | G7: x=raw×key | H7: -2 | I7: 0 | J7: 3 | K7: 0 | L7: 0 | M7: 2 | N7: -2 | O7: -2 | P7: -3 | Q7: 0 | R7: 0 | S7: 2 | T7: 3 | U7: 0 | V7: 0 | W7: 3 | X7: 2 | Y7: 3 | Z7: 2 | AA7: 2 | AB7: -2 | AC7: 3 | AD7: 0 | AE7: =INDEX('24_FINAL_ITEM_WEIGHTS'!$I$5:$I$84,MATCH(B7,'24_FINAL_ITEM_WEIGHTS'!$A$5:$A$84,0))
A8: 4 | B8: L06 | C8: 當你長期覺得生活不太對勁時，什麼最能幫你找回方向？ | D8: 把生活重新整理得更清楚、簡單，讓自己真正安定下來 | E8: 投入一段可信任的一對一關係，慢慢加深彼此的承諾和連結 | F8: 1 | G8: x=raw×key | H8: 2 | I8: 1 | J8: 2 | K8: 2 | L8: 2 | M8: 1 | N8: -3 | O8: 2 | P8: 3 | Q8: 2 | R8: 2 | S8: 1 | T8: 2 | U8: 1 | V8: 2 | W8: 2 | X8: 1 | Y8: 1 | Z8: 0 | AA8: 1 | AB8: 2 | AC8: 2 | AD8: 3 | AE8: =INDEX('24_FINAL_ITEM_WEIGHTS'!$I$5:$I$84,MATCH(B8,'24_FINAL_ITEM_WEIGHTS'!$A$5:$A$84,0))
A9: 5 | B9: G23 | C9: 面對一件重要又複雜的事時，你比較容易先注意哪一部分？ | D9: 先看整體，理解各個部分怎樣和更大的情況連在一起 | E9: 少數重要關係裡真正的需要，以及彼此願意投入多少 | F9: 1 | G9: x=raw×key | H9: 1 | I9: -2 | J9: 1 | K9: -2 | L9: -1 | M9: -2 | N9: 1 | O9: 1 | P9: 3 | Q9: 1 | R9: 0 | S9: -2 | T9: 1 | U9: -3 | V9: 1 | W9: 1 | X9: -2 | Y9: 0 | Z9: -3 | AA9: -3 | AB9: -1 | AC9: -1 | AD9: 2 | AE9: =INDEX('24_FINAL_ITEM_WEIGHTS'!$I$5:$I$84,MATCH(B9,'24_FINAL_ITEM_WEIGHTS'!$A$5:$A$84,0))
A10: 6 | B10: A09 | C10: 如果一項很多人都會使用的公共服務需要重新設計，你比較想從哪裡開始？ | D10: 規劃整體規則、分工和資源怎麼安排，讓不同單位能一起運作 | E10: 把日常流程和工具做得更順，讓前線的人容易照著做 | F10: -1 | G10: x=raw×key | H10: -3 | I10: -2 | J10: -3 | K10: -3 | L10: -2 | M10: -3 | N10: -3 | O10: -3 | P10: -3 | Q10: -3 | R10: -3 | S10: -3 | T10: -3 | U10: -2 | V10: -3 | W10: -3 | X10: -1 | Y10: -3 | Z10: -3 | AA10: 2 | AB10: -3 | AC10: -3 | AD10: -3 | AE10: =INDEX('24_FINAL_ITEM_WEIGHTS'!$I$5:$I$84,MATCH(B10,'24_FINAL_ITEM_WEIGHTS'!$A$5:$A$84,0))
A11: 7 | B11: G01 | C11: 面對一段同時帶有情緒和資訊的分享，你第一個自然反應比較像…… | D11: 先看看說法有沒有道理、前後有沒有矛盾，再形成自己的理解 | E11: 先留意其中的情緒變化和彼此的關係，再形成自己的理解 | F11: 1 | G11: x=raw×key | H11: 3 | I11: -1 | J11: 0 | K11: 0 | L11: -1 | M11: -3 | N11: 1 | O11: 1 | P11: 1 | Q11: 0 | R11: -2 | S11: -1 | T11: -1 | U11: -1 | V11: 0 | W11: -3 | X11: -1 | Y11: -1 | Z11: -3 | AA11: -1 | AB11: 0 | AC11: -1 | AD11: 0 | AE11: =INDEX('24_FINAL_ITEM_WEIGHTS'!$I$5:$I$84,MATCH(B11,'24_FINAL_ITEM_WEIGHTS'!$A$5:$A$84,0))
A12: 8 | B12: L19 | C12: 當你得到一段完全自由支配的創作時間，你更想…… | D12: 先立下一個方向，做出一個之後可以繼續發展的起點 | E12: 自由組合不同領域的想法，看看能發展出什麼新東西 | F12: -1 | G12: x=raw×key | H12: 0 | I12: 0 | J12: 3 | K12: -3 | L12: 3 | M12: -1 | N12: 0 | O12: 0 | P12: 0 | Q12: 3 | R12: 3 | S12: -3 | T12: 2 | U12: -3 | V12: 1 | W12: 3 | X12: 3 | Y12: 1 | Z12: 0 | AA12: 3 | AB12: 0 | AC12: 1 | AD12: 3 | AE12: =INDEX('24_FINAL_ITEM_WEIGHTS'!$I$5:$I$84,MATCH(B12,'24_FINAL_ITEM_WEIGHTS'!$A$5:$A$84,0))
A13: 9 | B13: G02 | C13: 一個對你很重要的決定，也會明顯影響親近的人時，你比較自然會…… | D13: 把彼此的關係和共同承諾當成最重要的考量之一 | E13: 先確定這仍是自己真正想走的方向，再想怎樣和對方協調 | F13: -1 | G13: x=raw×key | H13: 1 | I13: -2 | J13: 2 | K13: -2 | L13: -2 | M13: -1 | N13: 1 | O13: 1 | P13: 2 | Q13: 2 | R13: 1 | S13: -3 | T13: -2 | U13: -2 | V13: -1 | W13: 1 | X13: 0 | Y13: -2 | Z13: -2 | AA13: 0 | AB13: 0 | AC13: 0 | AD13: 2 | AE13: =INDEX('24_FINAL_ITEM_WEIGHTS'!$I$5:$I$84,MATCH(B13,'24_FINAL_ITEM_WEIGHTS'!$A$5:$A$84,0))
A14: 10 | B14: L07 | C14: 要讓一段相處重新有連結感，你比較相信關鍵在於…… | D14: 把注意力放回兩個人的信任，以及彼此是否真心投入 | E14: 先讓相處的空間、氣氛和節奏變得舒服協調 | F14: -1 | G14: x=raw×key | H14: 2 | I14: 0 | J14: 2 | K14: 0 | L14: 0 | M14: 0 | N14: 2 | O14: -3 | P14: 3 | Q14: 2 | R14: 3 | S14: -3 | T14: 0 | U14: 0 | V14: 3 | W14: 3 | X14: 2 | Y14: 2 | Z14: 0 | AA14: 2 | AB14: 0 | AC14: 3 | AD14: 2 | AE14: =INDEX('24_FINAL_ITEM_WEIGHTS'!$I$5:$I$84,MATCH(B14,'24_FINAL_ITEM_WEIGHTS'!$A$5:$A$84,0))
A15: 11 | B15: G27 | C15: 如果兩種生活節奏都可行，你通常更被哪一種吸引？ | D15: 定期換到新的環境或主題，保持探索和變化 | E15: 沿著同一方向走很多年，慢慢累積經驗和投入 | F15: 1 | G15: x=raw×key | H15: 0 | I15: -1 | J15: 3 | K15: -3 | L15: 0 | M15: 0 | N15: 1 | O15: 0 | P15: 1 | Q15: 3 | R15: 1 | S15: -3 | T15: 2 | U15: -2 | V15: -1 | W15: 3 | X15: 2 | Y15: -1 | Z15: 1 | AA15: 3 | AB15: 1 | AC15: 1 | AD15: 3 | AE15: =INDEX('24_FINAL_ITEM_WEIGHTS'!$I$5:$I$84,MATCH(B15,'24_FINAL_ITEM_WEIGHTS'!$A$5:$A$84,0))
A16: 12 | B16: L36 | C16: 當你長期生活在一個正在改變的地方或群體裡，你比較自然會扮演哪種角色？ | D16: 投入當地日常，親自參與維護和照料，讓共同生活一直延續下去 | E16: 保持一致的方向和節奏，成為大家可以依靠的穩定一方 | F16: 1 | G16: x=raw×key | H16: 2 | I16: 1 | J16: 0 | K16: 2 | L16: 1 | M16: 3 | N16: 3 | O16: 2 | P16: 2 | Q16: 2 | R16: 1 | S16: 2 | T16: 2 | U16: 3 | V16: 2 | W16: 1 | X16: 1 | Y16: 2 | Z16: 3 | AA16: 1 | AB16: 3 | AC16: 2 | AD16: -2 | AE16: =INDEX('24_FINAL_ITEM_WEIGHTS'!$I$5:$I$84,MATCH(B16,'24_FINAL_ITEM_WEIGHTS'!$A$5:$A$84,0))
... A84: 80 | B84: A06 | C84: 當一個空間裡的互動開始變淡、彼此距離也增加時，你比較傾向先…… | D84: 直接回應人的情緒或實際需要，從互動和安排上調整 | E84: 改變光線、聲音、材質或擺設，讓空間本身帶動氣氛 | F84: 1 | G84: x=raw×key | H84: -3 | I84: 2 | J84: 0 | K84: 0 | L84: 2 | M84: 2 | N84: 0 | O84: 3 | P84: 0 | Q84: 0 | R84: 0 | S84: 2 | T84: 2 | U84: 2 | V84: 0 | W84: 0 | X84: 0 | Y84: 0 | Z84: 2 | AA84: 0 | AB84: 0 | AC84: 0 | AD84: 0 | AE84: =INDEX('24_FINAL_ITEM_WEIGHTS'!$I$5:$I$84,MATCH(B84,'24_FINAL_ITEM_WEIGHTS'!$A$5:$A$84,0))

Sheet 10_TARGET_EDGE_AUDIT
A1: CRITICAL / SEVERE / HIGH Direct-Code Audit
A2: CRITICAL gate = all 3 direct cuts directional + ≥2 strong; SEVERE = 2 directional + 2 strong; HIGH = ≥1 directional strong.
A4: Rank | B4: Pair | C4: Risk | D4: Tier | E4: Direct slots | F4: Code A/B | G4: Directional | H4: Req dir | I4: Strong | J4: Req strong | K4: PASS | L4: Angular chord | M4: RMS
A5: 1 | B5: Martian ↔ Reptilian | C5: 80.937981 | D5: CRITICAL | E5: G30; L17; A03 | F5: G30:2/-2; L17:2/-2; A03:-3/3 | G5: 3 | H5: 3 | I5: 3 | J5: 2 | K5: PASS | L5: 0.76228303 | M5: 1.4491377
A6: 2 | B6: Draconian ↔ Reptilian | C6: 78.7174 | D6: CRITICAL | E6: L21; L27; A04 | F6: L21:3/-3; L27:3/-3; A04:3/-3 | G6: 3 | H6: 3 | I6: 3 | J6: 2 | K6: PASS | L6: 1.1998137 | M6: 2.2107691
A7: 3 | B7: Andromedan ↔ Vegan | C7: 77.519549 | D7: CRITICAL | E7: L08; L29; L34 | F7: L08:2/-2; L29:2/-2; L34:2/-2 | G7: 3 | H7: 3 | I7: 3 | J7: 2 | K7: PASS | L7: 0.67609936 | M7: 1.2599603
A8: 4 | B8: Draconian ↔ Anunnaki / Nibiruan | C8: 76.012428 | D8: CRITICAL | E8: L24; A09; A12 | F8: L24:2/-2; A09:-1/2; A12:2/-2 | G8: 3 | H8: 3 | I8: 2 | J8: 2 | K8: PASS | L8: 0.61090781 | M8: 1.1726039
A9: 5 | B9: Pleiadian ↔ Mintakan | C9: 71.759892 | D9: SEVERE | E9: L03; A01 | F9: L03:3/-3; A01:-3/3 | G9: 2 | H9: 2 | I9: 2 | J9: 2 | K9: PASS | L9: 0.82931234 | M9: 1.5491933
A10: 6 | B10: Feline / Urmah ↔ Reptilian | C10: 71.403979 | D10: SEVERE | E10: L20; L25 | F10: L20:3/-3; L25:3/-3 | G10: 2 | H10: 2 | I10: 2 | J10: 2 | K10: PASS | L10: 1.005555 | M10: 1.9072231
A11: 7 | B11: Venusian ↔ Hadarian | C11: 71.236718 | D11: SEVERE | E11: L04; L07 | F11: L04:2/-2; L07:-3/3 | G11: 2 | H11: 2 | I11: 2 | J11: 2 | K11: PASS | L11: 0.68625061 | M11: 1.2349089
A12: 8 | B12: Feline / Urmah ↔ Antarian | C12: 70.472631 | D12: SEVERE | E12: L23; L26 | F12: L23:3/-3; L26:3/-3 | G12: 2 | H12: 2 | I12: 2 | J12: 2 | K12: PASS | L12: 0.91049973 | M12: 1.7248188
A13: 9 | B13: Alpha Centaurian ↔ Anunnaki / Nibiruan | C13: 69.873695 | D13: SEVERE | E13: L12; A09 | F13: L12:3/-3; A09:-3/2 | G13: 2 | H13: 2 | I13: 2 | J13: 2 | K13: PASS | L13: 0.99962104 | M13: 1.8540496
A14: 10 | B14: Draconian ↔ Antarian | C14: 68.426005 | D14: SEVERE | E14: L22; A11 | F14: L22:3/-3; A11:-2/3 | G14: 2 | H14: 2 | I14: 2 | J14: 2 | K14: PASS | L14: 1.0357735 | M14: 1.9039433
A15: 11 | B15: Alpha Centaurian ↔ Maldekian | C15: 66.440945 | D15: HIGH | E15: L10; A02 | F15: L10:2/-2; A02:3/-3 | G15: 2 | H15: 1 | I15: 2 | J15: 1 | K15: PASS | L15: 0.89238962 | M15: 1.7284386
A16: 12 | B16: Orion ↔ Avian / Blue Avian | C16: 66.065574 | D16: HIGH | E16: L11 | F16: L11:3/-3 | G16: 1 | H16: 1 | I16: 1 | J16: 1 | K16: PASS | L16: 0.93585224 | M16: 1.6240382
... A32: 28 | B32: Polarian ↔ Alpha Centaurian | C32: 60.450103 | D32: HIGH | E32: L13; L32 | F32: L13:3/-3; L32:3/-3 | G32: 2 | H32: 1 | I32: 2 | J32: 1 | K32: PASS | L32: 0.90292823 | M32: 1.677051

Sheet 11_PAIR_GEOMETRY
A1: 253 Pair Codeword Geometry
A2: Equal-weight spherical/cosine geometry before final item-weight rebuild.
A4: Rank | B4: A | C4: B | D4: Cosine | E4: Angular chord | F4: RMS | G4: Note
A5: 1 | B5: Draconian | C5: Anunnaki / Nibiruan | D5: 0.81339583 | E5: 0.61090781 | F5: 1.1726039 | G5: Nearest codeword pair
A6: 2 | B6: Maldekian | C6: Zeta / Grey | D6: 0.78444174 | E6: 0.65659465 | F6: 1.3228757
A7: 3 | B7: Andromedan | C7: Vegan | D7: 0.77144483 | E7: 0.67609936 | F7: 1.2599603
A8: 4 | B8: Zeta / Grey | C8: Antarian | D8: 0.76498911 | E8: 0.68558135 | F8: 1.2845233
A9: 5 | B9: Venusian | C9: Hadarian | D9: 0.76453005 | E9: 0.68625061 | F9: 1.2349089
A10: 6 | B10: Lyran | C10: Martian | D10: 0.76040109 | E10: 0.69224115 | F10: 1.3086252
A11: 7 | B11: Maldekian | C11: Antarian | D11: 0.75145964 | E11: 0.70503952 | F11: 1.3874437
A12: 8 | B12: Sirian | C12: Polarian | D12: 0.74695739 | E12: 0.71139667 | F12: 1.3416408
A13: 9 | B13: Polarian | C13: Earth-Origin Soul | D13: 0.74532923 | E13: 0.71368168 | F13: 1.3693064
A14: 10 | B14: Pleiadian | C14: Hadarian | D14: 0.74276535 | E14: 0.71726515 | F14: 1.3038405
A15: 11 | B15: Polarian | C15: Maldekian | D15: 0.74215604 | E15: 0.71811414 | F15: 1.4491377
A16: 12 | B16: Martian | C16: Reptilian | D16: 0.70946229 | E16: 0.76228303 | F16: 1.4491377
A17: 13 | B17: Sirian | C17: Maldekian | D17: 0.70553175 | E17: 0.76742199 | F17: 1.5083103
... A257: 253 | B257: Andromedan | C257: Maldekian | D257: -0.39426358 | E257: 1.6698884 | F257: 3.2287769

Sheet 12_ROBUSTNESS
A1: Structural Robustness — Equal-Weight Spherical Decoder
A2: Synthetic structural tests, not empirical accuracy.
A4: Test | B4: 25% | C4: 50% | D4: 75% | E4: 100% | F4: Result | G4: Status | H4: Interpretation
A5: Exact prototype self-classification | F5: 23/23 | G5: PASS | H5: Unique 80-D directions.
A6: Continuous amplitude | B6: 23 | C6: 23 | D6: 23 | E6: 23 | F6: 23 each | G6: PASS | H6: Positive rescaling should not alter cosine direction.
A7: Quantized amplitude | B7: 23 | C7: 23 | D7: 23 | E7: 23 | F7: 23 each | G7: PASS | H7: After scale + legal integer rounding.
A8: One-item arbitrary corruption | F8: 11040/11040 | G8: PASS | H8: Each item replaced by any other legal response.
A9: Min angular chord | F9: 0.610908 | G9: PASS | H9: Draconian ↔ Anunnaki / Nibiruan
A10: Median angular chord | F10: 1.254834 | G10: INFO | H10: 253 pairs.
A11: High-risk code gates | F11: 28/28 | G11: PASS | H11: All top 28 edge gates.

Sheet 13_THRESHOLD_SENSITIVITY
A1: Quantization Threshold Sensitivity
A2: Thresholds are design bands, not calibrated psychometric parameters. Nearby alternatives keep codewords unique and separation structurally similar.
A4: t0 | B4: t1 | C4: t2 | D4: Unique | E4: Min chord | F4: Median chord | G4: Selected
A5: 0.12 | B5: 0.34 | C5: 0.6 | D5: 23 | E5: 0.57114935 | F5: 1.2528022 | G5: NO
A6: 0.15 | B6: 0.4 | C6: 0.7 | D6: 23 | E6: 0.61090781 | F6: 1.2548343 | G6: YES
A7: 0.18 | B7: 0.45 | C7: 0.75 | D7: 23 | E7: 0.52338787 | F7: 1.2557553 | G7: NO
A8: 0.1 | B8: 0.3 | C8: 0.55 | D8: 23 | E8: 0.58548067 | F8: 1.250723 | G8: NO

Sheet 14_GAIN_SENSITIVITY
A1: Comparative-Centering Gain Sensitivity
A2: Gain is a design constant, not calibration. 1.70 is the smallest tested simple value that satisfies all 28 direct-code gates; larger values add extremity without improving the discrete gate outcome.
A4: Gain | B4: Unique codewords | C4: Min chord | D4: Median chord | E4: High-risk gates | F4: Zero cells | G4: ±3 cells | H4: Selected
A5: 1.5 | B5: 23 | C5: 0.52777161 | D5: 1.2455749 | E5: 25/28 | F5: 485 | G5: 303 | H5: NO
A6: 1.6 | B6: 23 | C6: 0.57763714 | D6: 1.2471498 | E6: 27/28 | F6: 485 | G6: 360 | H6: NO
A7: 1.65 | B7: 23 | C7: 0.58986676 | D7: 1.2446921 | E7: 27/28 | F7: 482 | G7: 360 | H7: NO
A8: 1.7 | B8: 23 | C8: 0.61090781 | D8: 1.2548343 | E8: 28/28 | F8: 481 | G8: 407 | H8: YES
A9: 1.75 | B9: 23 | C9: 0.61090781 | D9: 1.2548343 | E9: 28/28 | F9: 481 | G9: 407 | H9: NO
A10: 2 | B10: 23 | C10: 0.57595431 | D10: 1.2515536 | E10: 28/28 | F10: 446 | G10: 488 | H10: NO

Sheet 15_CODEWORD_NORM_AUDIT
A1: Prototype Magnitude / Sparsity Audit
A2: Spherical decoding removes prototype-norm centrality from scoring, but extreme sparsity can still increase quantization sensitivity. This sheet checks that no lineage codeword is abnormally empty.
A4: # | B4: Lineage | C4: Nonzero items | D4: Zero items | E4: L2 norm | F4: Mean |code| | G4: Max |code| | H4: Status
A5: 1 | B5: Pleiadian | C5: 59 | D5: 21 | E5: 16.492423 | F5: 1.475 | G5: 3 | H5: PASS
A6: 2 | B6: Arcturian | C6: 55 | D6: 25 | E6: 13.56466 | F6: 1.175 | G6: 3 | H6: PASS
A7: 3 | B7: Sirian | C7: 56 | D7: 24 | E7: 16.124515 | F7: 1.425 | G7: 3 | H7: PASS
A8: 4 | B8: Andromedan | C8: 61 | D8: 19 | E8: 16 | F8: 1.475 | G8: 3 | H8: PASS
A9: 5 | B9: Lyran | C9: 62 | D9: 18 | E9: 15.684387 | F9: 1.425 | G9: 3 | H9: PASS
A10: 6 | B10: Orion | C10: 54 | D10: 26 | E10: 15.099669 | F10: 1.3 | G10: 3 | H10: PASS
A11: 7 | B11: Mintakan | C11: 65 | D11: 15 | E11: 16.911535 | F11: 1.55 | G11: 3 | H11: PASS
A12: 8 | B12: Venusian | C12: 58 | D12: 22 | E12: 16.186414 | F12: 1.4 | G12: 3 | H12: PASS
A13: 9 | B13: Hadarian | C13: 53 | D13: 27 | E13: 16 | F13: 1.35 | G13: 3 | H13: PASS
A14: 10 | B14: Polarian | C14: 54 | D14: 26 | E14: 17.435596 | F14: 1.525 | G14: 3 | H14: PASS
A15: 11 | B15: Alpha Centaurian | C15: 53 | D15: 27 | E15: 15.588457 | F15: 1.3125 | G15: 3 | H15: PASS
A16: 12 | B16: Vegan | C16: 67 | D16: 13 | E16: 17.175564 | F16: 1.6625 | G16: 3 | H16: PASS
... A27: 23 | B27: Earth-Origin Soul | C27: 60 | D27: 20 | E27: 16.8523 | F27: 1.525 | G27: 3 | H27: PASS

Sheet 16_QA_SNAPSHOT
A1: Static QA Snapshot
A2: Independent Python calculation of the final integer codebook.
A4: Metric | B4: Value | C4: Status | D4: Detail
A5: Unique codewords | B5: 23/23 | C5: PASS
A6: Legal code range | B6: -3…3 | C6: PASS
A7: Zero cells | B7: 481 | C7: INFO | D7: 26.1%
A8: ±3 cells | B8: 407 | C8: INFO | D8: 22.1%
A9: Min angular chord | B9: 0.610908 | C9: PASS | D9: Draconian ↔ Anunnaki / Nibiruan
A10: Exact classification | B10: 23/23 | C10: PASS | D10: Equal-weight cosine
A11: Amplitude continuous | B11: 23 / 23 / 23 / 23 | C11: PASS | D11: 25/50/75/100%
A12: Amplitude quantized | B12: 23 / 23 / 23 / 23 | C12: PASS | D12: 25/50/75/100%
A13: One-item corruption | B13: 11040/11040 | C13: PASS
A14: High-risk gates | B14: 28/28 | C14: PASS
A15: Final item weights | B15: NOT YET REBUILT | C15: NEXT | D15: Equal-weight QA is not the final production scoring geometry.

Sheet 90_CANON_CONF_SOURCE
A1: 23×22 Cell Coding Confidence
A2: Confidence is intentionally conservative: lineage phenotype-convergence caps every cell; ±1/secondary lean is one grade below a defining ±2; zero cells never receive A/B because “not defining” is not proof of exact neutrality.
A4: # | B4: 中文 | C4: English | D4: D01 | E4: D02 | F4: D03 | G4: D04 | H4: D05 | I4: D06 | J4: D07 | K4: D08 | L4: D09 | M4: D10 | N4: D11 | O4: D12 | P4: D13 | Q4: D14 | R4: D15 | S4: D16 | T4: D17 | U4: D18 | V4: D19 | W4: D20 | X4: D21 | Y4: D22
A5: 1 | B5: 昴宿星人 | C5: Pleiadian | D5: A | E5: B | F5: C | G5: B | H5: B | I5: C | J5: C | K5: C | L5: C | M5: C | N5: B | O5: A | P5: B | Q5: B | R5: B | S5: A | T5: C | U5: C | V5: B | W5: C | X5: C | Y5: C
A6: 2 | B6: 大角星人 | C6: Arcturian | D6: C | E6: C | F6: C | G6: C | H6: C | I6: C | J6: C | K6: C | L6: C | M6: C | N6: C | O6: C | P6: C | Q6: C | R6: C | S6: B | T6: C | U6: C | V6: C | W6: C | X6: C | Y6: C
A7: 3 | B7: 天狼星人 | C7: Sirian | D7: C | E7: C | F7: C | G7: C | H7: C | I7: B | J7: C | K7: B | L7: C | M7: C | N7: C | O7: C | P7: B | Q7: C | R7: C | S7: C | T7: B | U7: C | V7: C | W7: C | X7: C | Y7: C
A8: 4 | B8: 仙女座人 | C8: Andromedan | D8: C | E8: C | F8: C | G8: C | H8: C | I8: C | J8: B | K8: C | L8: B | M8: C | N8: C | O8: C | P8: C | Q8: C | R8: C | S8: C | T8: C | U8: C | V8: C | W8: B | X8: C | Y8: C
A9: 5 | B9: 天琴座人 | C9: Lyran | D9: C | E9: C | F9: C | G9: C | H9: C | I9: C | J9: C | K9: C | L9: B | M9: C | N9: B | O9: C | P9: C | Q9: C | R9: C | S9: C | T9: C | U9: B | V9: C | W9: C | X9: C | Y9: C
A10: 6 | B10: 獵戶座人 | C10: Orion | D10: B | E10: B | F10: C | G10: A | H10: C | I10: C | J10: B | K10: C | L10: C | M10: C | N10: B | O10: B | P10: B | Q10: C | R10: B | S10: C | T10: C | U10: C | V10: A | W10: C | X10: A | Y10: C
A11: 7 | B11: 明塔卡星人 | C11: Mintakan | D11: C | E11: C | F11: C | G11: C | H11: C | I11: C | J11: C | K11: C | L11: C | M11: C | N11: C | O11: B | P11: C | Q11: C | R11: C | S11: B | T11: C | U11: C | V11: C | W11: C | X11: C | Y11: B
A12: 8 | B12: 金星人 | C12: Venusian | D12: C | E12: C | F12: B | G12: C | H12: C | I12: C | J12: C | K12: C | L12: C | M12: C | N12: C | O12: B | P12: C | Q12: C | R12: C | S12: B | T12: C | U12: C | V12: C | W12: C | X12: C | Y12: C
A13: 9 | B13: 哈達爾星人 | C13: Hadarian | D13: C | E13: B | F13: C | G13: C | H13: C | I13: C | J13: C | K13: C | L13: C | M13: C | N13: C | O13: B | P13: B | Q13: C | R13: C | S13: B | T13: C | U13: C | V13: C | W13: C | X13: C | Y13: C
A14: 10 | B14: 北極星人 | C14: Polarian | D14: D | E14: D | F14: D | G14: D | H14: D | I14: C | J14: D | K14: D | L14: D | M14: D | N14: D | O14: D | P14: D | Q14: D | R14: C | S14: D | T14: D | U14: D | V14: D | W14: C | X14: D | Y14: D
A15: 11 | B15: 半人馬座α星人 | C15: Alpha Centaurian | D15: D | E15: D | F15: D | G15: D | H15: C | I15: D | J15: D | K15: D | L15: D | M15: D | N15: D | O15: D | P15: D | Q15: D | R15: D | S15: D | T15: D | U15: C | V15: D | W15: D | X15: D | Y15: D
A16: 12 | B16: 織女星人 | C16: Vegan | D16: D | E16: D | F16: D | G16: D | H16: D | I16: D | J16: D | K16: D | L16: C | M16: D | N16: D | O16: D | P16: D | Q16: D | R16: D | S16: D | T16: D | U16: D | V16: D | W16: C | X16: D | Y16: D
... A27: 23 | B27: 地球源靈魂 | C27: Earth-Origin Soul | D27: C | E27: C | F27: C | G27: C | H27: C | I27: C | J27: C | K27: C | L27: C | M27: C | N27: C | O27: C | P27: C | Q27: C | R27: C | S27: C | T27: C | U27: B | V27: C | W27: B | X27: C | Y27: B

Sheet 91_MOTIF_CONF_SOURCE
A1: 23×19 Motif Confidence
A2: Nonzero motif confidence is manually assigned from provenance/convergence. Zero motif cells are D because absence of a motif is generally “not defining,” not a strong claim that the motif never appears.
A4: # | B4: 中文 | C4: English | D4: M01 | E4: M02 | F4: M03 | G4: M04 | H4: M05 | I4: M06 | J4: M07 | K4: M08 | L4: M09 | M4: M10 | N4: M11 | O4: M12 | P4: M13 | Q4: M14 | R4: M15 | S4: M16 | T4: M17 | U4: M18 | V4: M19
A5: 1 | B5: 昴宿星人 | C5: Pleiadian | D5: D | E5: D | F5: D | G5: D | H5: D | I5: D | J5: D | K5: D | L5: D | M5: D | N5: D | O5: D | P5: D | Q5: D | R5: D | S5: D | T5: D | U5: D | V5: D
A6: 2 | B6: 大角星人 | C6: Arcturian | D6: D | E6: D | F6: D | G6: D | H6: D | I6: C | J6: D | K6: D | L6: D | M6: D | N6: D | O6: D | P6: D | Q6: D | R6: D | S6: D | T6: D | U6: D | V6: D
A7: 3 | B7: 天狼星人 | C7: Sirian | D7: D | E7: D | F7: C | G7: D | H7: D | I7: D | J7: D | K7: D | L7: D | M7: D | N7: D | O7: D | P7: D | Q7: D | R7: D | S7: D | T7: D | U7: D | V7: B
A8: 4 | B8: 仙女座人 | C8: Andromedan | D8: D | E8: D | F8: D | G8: D | H8: D | I8: D | J8: D | K8: D | L8: D | M8: D | N8: D | O8: D | P8: B | Q8: D | R8: D | S8: D | T8: D | U8: D | V8: D
A9: 5 | B9: 天琴座人 | C9: Lyran | D9: D | E9: D | F9: D | G9: C | H9: D | I9: D | J9: D | K9: D | L9: D | M9: D | N9: D | O9: D | P9: D | Q9: D | R9: C | S9: D | T9: D | U9: D | V9: D
A10: 6 | B10: 獵戶座人 | C10: Orion | D10: D | E10: D | F10: D | G10: D | H10: D | I10: D | J10: D | K10: D | L10: D | M10: D | N10: D | O10: B | P10: D | Q10: D | R10: D | S10: D | T10: D | U10: D | V10: D
A11: 7 | B11: 明塔卡星人 | C11: Mintakan | D11: B | E11: D | F11: B | G11: D | H11: D | I11: D | J11: D | K11: D | L11: D | M11: D | N11: D | O11: D | P11: D | Q11: D | R11: D | S11: D | T11: D | U11: D | V11: D
A12: 8 | B12: 金星人 | C12: Venusian | D12: D | E12: D | F12: D | G12: D | H12: D | I12: D | J12: D | K12: B | L12: D | M12: D | N12: D | O12: D | P12: D | Q12: D | R12: D | S12: D | T12: D | U12: C | V12: D
A13: 9 | B13: 哈達爾星人 | C13: Hadarian | D13: D | E13: D | F13: D | G13: D | H13: D | I13: D | J13: D | K13: D | L13: B | M13: D | N13: D | O13: D | P13: D | Q13: D | R13: D | S13: D | T13: D | U13: D | V13: D
A14: 10 | B14: 北極星人 | C14: Polarian | D14: D | E14: D | F14: D | G14: D | H14: D | I14: D | J14: D | K14: D | L14: D | M14: B | N14: D | O14: D | P14: D | Q14: D | R14: D | S14: D | T14: D | U14: D | V14: D
A15: 11 | B15: 半人馬座α星人 | C15: Alpha Centaurian | D15: D | E15: D | F15: D | G15: D | H15: D | I15: D | J15: D | K15: D | L15: D | M15: D | N15: D | O15: D | P15: D | Q15: D | R15: D | S15: D | T15: D | U15: D | V15: D
A16: 12 | B16: 織女星人 | C16: Vegan | D16: D | E16: D | F16: D | G16: D | H16: D | I16: D | J16: D | K16: D | L16: D | M16: D | N16: D | O16: D | P16: B | Q16: D | R16: D | S16: D | T16: D | U16: B | V16: D
... A27: 23 | B27: 地球源靈魂 | C27: Earth-Origin Soul | D27: D | E27: D | F27: D | G27: D | H27: D | I27: D | J27: D | K27: D | L27: D | M27: D | N27: D | O27: D | P27: D | Q27: B | R27: D | S27: D | T27: D | U27: D | V27: D

Sheet 18_WEIGHT_CONTROL
A1: v4 Final Item Weight Control
A2: No respondent calibration. Final weights are a bounded semantic-confidence prior around unit weights; confusion risk, layer, slot count and expert wording flags do NOT enter the weight formula.
A4: Control | B4: Value | C4: Meaning | D4: Status
A5: Confidence A | B5: 1 | C5: Frozen cell-confidence numeric mapping; design scale, not empirical reliability. | D5: FROZEN
A6: Confidence B | B6: 0.8 | C6: Same mapping used in v4 confidence-aware graph. | D6: FROZEN
A7: Confidence C | B7: 0.55 | C7: Same mapping used in v4 confidence-aware graph. | D7: FROZEN
A8: Confidence D | B8: 0.3 | C8: Same mapping used in v4 confidence-aware graph. | D8: FROZEN
A9: Max weight deviation δ | B9: 0.1 | C9: Final item weights stay close to equal weights: no item may deviate more than +10% from unit weight. | D9: SELECTED
A10: Dependency correlation threshold | B10: 0.8 | C10: Within-item feature dependence is only penalized above |r|=.80 in the 23-lineage feature model. | D10: FROZEN
A11: Maximum dependency penalty | B11: 0.1 | C11: At perfect duplicate evidence with balanced coefficient mass, semantic reliability can be reduced by at most 10%. | D11: FROZEN
A12: Mean raw reliability | B12: =AVERAGE('23_ITEM_WEIGHT_MODEL'!K5:K84) | C12: Calculated from 80 items. | D12: FORMULA
A13: Max |raw−mean| | B13: =MAX(MAX('23_ITEM_WEIGHT_MODEL'!K5:K84)-B12,B12-MIN('23_ITEM_WEIGHT_MODEL'!K5:K84)) | C13: Used to scale the bounded linear shrinkage. | D13: FORMULA
A14: Shrink slope β | B14: =B9/B13 | C14: β=δ/max|R−mean|. This is a deterministic design transform, not a fitted parameter. | D14: FORMULA
A15: Weight sum | B15: =SUM('24_FINAL_ITEM_WEIGHTS'!I5:I84) | C15: Must equal 80 so mean item weight=1. | D15: GATE

Sheet 92_FEATURE_CONF_NUMERIC
A1: Numeric Feature Confidence Helper
A4: # | B4: 中文 | C4: English | D4: D01 | E4: D02 | F4: D03 | G4: D04 | H4: D05 | I4: D06 | J4: D07 | K4: D08 | L4: D09 | M4: D10 | N4: D11 | O4: D12 | P4: D13 | Q4: D14 | R4: D15 | S4: D16 | T4: D17 | U4: D18 | V4: D19 | W4: D20 | X4: D21 | Y4: D22 | Z4: M01 | AA4: M02 | AB4: M03 | AC4: M04 | AD4: M05 | AE4: M06 | AF4: M07 | AG4: M08 | AH4: M09 | AI4: M10 | AJ4: M11 | AK4: M12 | AL4: M13 | AM4: M14 | AN4: M15 | AO4: M16 | AP4: M17 | AQ4: M18 | AR4: M19
A5: 1 | B5: 昴宿星人 | C5: Pleiadian | D5: =IF('90_CANON_CONF_SOURCE'!D5='18_WEIGHT_CONTROL'!$A$5,'18_WEIGHT_CONTROL'!$B$5,IF('90_CANON_CONF_SOURCE'!D5='18_WEIGHT_CONTROL'!$A$6,'18_WEIGHT_CONTROL'!$B$6,IF('90_CANON_CONF_SOURCE'!D5='18_WEIGHT_CONTROL'!$A$7,'18_WEIGHT_CONTROL'!$B$7,'18_WEIGHT_CONTROL'!$B$8))) | E5: =IF('90_CANON_CONF_SOURCE'!E5='18_WEIGHT_CONTROL'!$A$5,'18_WEIGHT_CONTROL'!$B$5,IF('90_CANON_CONF_SOURCE'!E5='18_WEIGHT_CONTROL'!$A$6,'18_WEIGHT_CONTROL'!$B$6,IF('90_CANON_CONF_SOURCE'!E5='18_WEIGHT_CONTROL'!$A$7,'18_WEIGHT_CONTROL'!$B$7,'18_WEIGHT_CONTROL'!$B$8))) | F5: =IF('90_CANON_CONF_SOURCE'!F5='18_WEIGHT_CONTROL'!$A$5,'18_WEIGHT_CONTROL'!$B$5,IF('90_CANON_CONF_SOURCE'!F5='18_WEIGHT_CONTROL'!$A$6,'18_WEIGHT_CONTROL'!$B$6,IF('90_CANON_CONF_SOURCE'!F5='18_WEIGHT_CONTROL'!$A$7,'18_WEIGHT_CONTROL'!$B$7,'18_WEIGHT_CONTROL'!$B$8))) | G5: =IF('90_CANON_CONF_SOURCE'!G5='18_WEIGHT_CONTROL'!$A$5,'18_WEIGHT_CONTROL'!$B$5,IF('90_CANON_CONF_SOURCE'!G5='18_WEIGHT_CONTROL'!$A$6,'18_WEIGHT_CONTROL'!$B$6,IF('90_CANON_CONF_SOURCE'!G5='18_WEIGHT_CONTROL'!$A$7,'18_WEIGHT_CONTROL'!$B$7,'18_WEIGHT_CONTROL'!$B$8))) | H5: =IF('90_CANON_CONF_SOURCE'!H5='18_WEIGHT_CONTROL'!$A$5,'18_WEIGHT_CONTROL'!$B$5,IF('90_CANON_CONF_SOURCE'!H5='18_WEIGHT_CONTROL'!$A$6,'18_WEIGHT_CONTROL'!$B$6,IF('90_CANON_CONF_SOURCE'!H5='18_WEIGHT_CONTROL'!$A$7,'18_WEIGHT_CONTROL'!$B$7,'18_WEIGHT_CONTROL'!$B$8))) | I5: =IF('90_CANON_CONF_SOURCE'!I5='18_WEIGHT_CONTROL'!$A$5,'18_WEIGHT_CONTROL'!$B$5,IF('90_CANON_CONF_SOURCE'!I5='18_WEIGHT_CONTROL'!$A$6,'18_WEIGHT_CONTROL'!$B$6,IF('90_CANON_CONF_SOURCE'!I5='18_WEIGHT_CONTROL'!$A$7,'18_WEIGHT_CONTROL'!$B$7,'18_WEIGHT_CONTROL'!$B$8))) | J5: =IF('90_CANON_CONF_SOURCE'!J5='18_WEIGHT_CONTROL'!$A$5,'18_WEIGHT_CONTROL'!$B$5,IF('90_CANON_CONF_SOURCE'!J5='18_WEIGHT_CONTROL'!$A$6,'18_WEIGHT_CONTROL'!$B$6,IF('90_CANON_CONF_SOURCE'!J5='18_WEIGHT_CONTROL'!$A$7,'18_WEIGHT_CONTROL'!$B$7,'18_WEIGHT_CONTROL'!$B$8))) | K5: =IF('90_CANON_CONF_SOURCE'!K5='18_WEIGHT_CONTROL'!$A$5,'18_WEIGHT_CONTROL'!$B$5,IF('90_CANON_CONF_SOURCE'!K5='18_WEIGHT_CONTROL'!$A$6,'18_WEIGHT_CONTROL'!$B$6,IF('90_CANON_CONF_SOURCE'!K5='18_WEIGHT_CONTROL'!$A$7,'18_WEIGHT_CONTROL'!$B$7,'18_WEIGHT_CONTROL'!$B$8))) | ... Y5: =IF('90_CANON_CONF_SOURCE'!Y5='18_WEIGHT_CONTROL'!$A$5,'18_WEIGHT_CONTROL'!$B$5,IF('90_CANON_CONF_SOURCE'!Y5='18_WEIGHT_CONTROL'!$A$6,'18_WEIGHT_CONTROL'!$B$6,IF('90_CANON_CONF_SOURCE'!Y5='18_WEIGHT_CONTROL'!$A$7,'18_WEIGHT_CONTROL'!$B$7,'18_WEIGHT_CONTROL'!$B$8))) | Z5: =IF('91_MOTIF_CONF_SOURCE'!D5='18_WEIGHT_CONTROL'!$A$5,'18_WEIGHT_CONTROL'!$B$5,IF('91_MOTIF_CONF_SOURCE'!D5='18_WEIGHT_CONTROL'!$A$6,'18_WEIGHT_CONTROL'!$B$6,IF('91_MOTIF_CONF_SOURCE'!D5='18_WEIGHT_CONTROL'!$A$7,'18_WEIGHT_CONTROL'!$B$7,'18_WEIGHT_CONTROL'!$B$8))) | AA5: =IF('91_MOTIF_CONF_SOURCE'!E5='18_WEIGHT_CONTROL'!$A$5,'18_WEIGHT_CONTROL'!$B$5,IF('91_MOTIF_CONF_SOURCE'!E5='18_WEIGHT_CONTROL'!$A$6,'18_WEIGHT_CONTROL'!$B$6,IF('91_MOTIF_CONF_SOURCE'!E5='18_WEIGHT_CONTROL'!$A$7,'18_WEIGHT_CONTROL'!$B$7,'18_WEIGHT_CONTROL'!$B$8))) | AB5: =IF('91_MOTIF_CONF_SOURCE'!F5='18_WEIGHT_CONTROL'!$A$5,'18_WEIGHT_CONTROL'!$B$5,IF('91_MOTIF_CONF_SOURCE'!F5='18_WEIGHT_CONTROL'!$A$6,'18_WEIGHT_CONTROL'!$B$6,IF('91_MOTIF_CONF_SOURCE'!F5='18_WEIGHT_CONTROL'!$A$7,'18_WEIGHT_CONTROL'!$B$7,'18_WEIGHT_CONTROL'!$B$8))) | AC5: =IF('91_MOTIF_CONF_SOURCE'!G5='18_WEIGHT_CONTROL'!$A$5,'18_WEIGHT_CONTROL'!$B$5,IF('91_MOTIF_CONF_SOURCE'!G5='18_WEIGHT_CONTROL'!$A$6,'18_WEIGHT_CONTROL'!$B$6,IF('91_MOTIF_CONF_SOURCE'!G5='18_WEIGHT_CONTROL'!$A$7,'18_WEIGHT_CONTROL'!$B$7,'18_WEIGHT_CONTROL'!$B$8))) | AD5: =IF('91_MOTIF_CONF_SOURCE'!H5='18_WEIGHT_CONTROL'!$A$5,'18_WEIGHT_CONTROL'!$B$5,IF('91_MOTIF_CONF_SOURCE'!H5='18_WEIGHT_CONTROL'!$A$6,'18_WEIGHT_CONTROL'!$B$6,IF('91_MOTIF_CONF_SOURCE'!H5='18_WEIGHT_CONTROL'!$A$7,'18_WEIGHT_CONTROL'!$B$7,'18_WEIGHT_CONTROL'!$B$8))) | AE5: =IF('91_MOTIF_CONF_SOURCE'!I5='18_WEIGHT_CONTROL'!$A$5,'18_WEIGHT_CONTROL'!$B$5,IF('91_MOTIF_CONF_SOURCE'!I5='18_WEIGHT_CONTROL'!$A$6,'18_WEIGHT_CONTROL'!$B$6,IF('91_MOTIF_CONF_SOURCE'!I5='18_WEIGHT_CONTROL'!$A$7,'18_WEIGHT_CONTROL'!$B$7,'18_WEIGHT_CONTROL'!$B$8))) | AF5: =IF('91_MOTIF_CONF_SOURCE'!J5='18_WEIGHT_CONTROL'!$A$5,'18_WEIGHT_CONTROL'!$B$5,IF('91_MOTIF_CONF_SOURCE'!J5='18_WEIGHT_CONTROL'!$A$6,'18_WEIGHT_CONTROL'!$B$6,IF('91_MOTIF_CONF_SOURCE'!J5='18_WEIGHT_CONTROL'!$A$7,'18_WEIGHT_CONTROL'!$B$7,'18_WEIGHT_CONTROL'!$B$8))) | AG5: =IF('91_MOTIF_CONF_SOURCE'!K5='18_WEIGHT_CONTROL'!$A$5,'18_WEIGHT_CONTROL'!$B$5,IF('91_MOTIF_CONF_SOURCE'!K5='18_WEIGHT_CONTROL'!$A$6,'18_WEIGHT_CONTROL'!$B$6,IF('91_MOTIF_CONF_SOURCE'!K5='18_WEIGHT_CONTROL'!$A$7,'18_WEIGHT_CONTROL'!$B$7,'18_WEIGHT_CONTROL'!$B$8))) | ... AR5: =IF('91_MOTIF_CONF_SOURCE'!V5='18_WEIGHT_CONTROL'!$A$5,'18_WEIGHT_CONTROL'!$B$5,IF('91_MOTIF_CONF_SOURCE'!V5='18_WEIGHT_CONTROL'!$A$6,'18_WEIGHT_CONTROL'!$B$6,IF('91_MOTIF_CONF_SOURCE'!V5='18_WEIGHT_CONTROL'!$A$7,'18_WEIGHT_CONTROL'!$B$7,'18_WEIGHT_CONTROL'!$B$8)))
A6: 2 | B6: 大角星人 | C6: Arcturian | D6: =IF('90_CANON_CONF_SOURCE'!D6='18_WEIGHT_CONTROL'!$A$5,'18_WEIGHT_CONTROL'!$B$5,IF('90_CANON_CONF_SOURCE'!D6='18_WEIGHT_CONTROL'!$A$6,'18_WEIGHT_CONTROL'!$B$6,IF('90_CANON_CONF_SOURCE'!D6='18_WEIGHT_CONTROL'!$A$7,'18_WEIGHT_CONTROL'!$B$7,'18_WEIGHT_CONTROL'!$B$8))) | E6: =IF('90_CANON_CONF_SOURCE'!E6='18_WEIGHT_CONTROL'!$A$5,'18_WEIGHT_CONTROL'!$B$5,IF('90_CANON_CONF_SOURCE'!E6='18_WEIGHT_CONTROL'!$A$6,'18_WEIGHT_CONTROL'!$B$6,IF('90_CANON_CONF_SOURCE'!E6='18_WEIGHT_CONTROL'!$A$7,'18_WEIGHT_CONTROL'!$B$7,'18_WEIGHT_CONTROL'!$B$8))) | F6: =IF('90_CANON_CONF_SOURCE'!F6='18_WEIGHT_CONTROL'!$A$5,'18_WEIGHT_CONTROL'!$B$5,IF('90_CANON_CONF_SOURCE'!F6='18_WEIGHT_CONTROL'!$A$6,'18_WEIGHT_CONTROL'!$B$6,IF('90_CANON_CONF_SOURCE'!F6='18_WEIGHT_CONTROL'!$A$7,'18_WEIGHT_CONTROL'!$B$7,'18_WEIGHT_CONTROL'!$B$8))) | G6: =IF('90_CANON_CONF_SOURCE'!G6='18_WEIGHT_CONTROL'!$A$5,'18_WEIGHT_CONTROL'!$B$5,IF('90_CANON_CONF_SOURCE'!G6='18_WEIGHT_CONTROL'!$A$6,'18_WEIGHT_CONTROL'!$B$6,IF('90_CANON_CONF_SOURCE'!G6='18_WEIGHT_CONTROL'!$A$7,'18_WEIGHT_CONTROL'!$B$7,'18_WEIGHT_CONTROL'!$B$8))) | H6: =IF('90_CANON_CONF_SOURCE'!H6='18_WEIGHT_CONTROL'!$A$5,'18_WEIGHT_CONTROL'!$B$5,IF('90_CANON_CONF_SOURCE'!H6='18_WEIGHT_CONTROL'!$A$6,'18_WEIGHT_CONTROL'!$B$6,IF('90_CANON_CONF_SOURCE'!H6='18_WEIGHT_CONTROL'!$A$7,'18_WEIGHT_CONTROL'!$B$7,'18_WEIGHT_CONTROL'!$B$8))) | I6: =IF('90_CANON_CONF_SOURCE'!I6='18_WEIGHT_CONTROL'!$A$5,'18_WEIGHT_CONTROL'!$B$5,IF('90_CANON_CONF_SOURCE'!I6='18_WEIGHT_CONTROL'!$A$6,'18_WEIGHT_CONTROL'!$B$6,IF('90_CANON_CONF_SOURCE'!I6='18_WEIGHT_CONTROL'!$A$7,'18_WEIGHT_CONTROL'!$B$7,'18_WEIGHT_CONTROL'!$B$8))) | J6: =IF('90_CANON_CONF_SOURCE'!J6='18_WEIGHT_CONTROL'!$A$5,'18_WEIGHT_CONTROL'!$B$5,IF('90_CANON_CONF_SOURCE'!J6='18_WEIGHT_CONTROL'!$A$6,'18_WEIGHT_CONTROL'!$B$6,IF('90_CANON_CONF_SOURCE'!J6='18_WEIGHT_CONTROL'!$A$7,'18_WEIGHT_CONTROL'!$B$7,'18_WEIGHT_CONTROL'!$B$8))) | K6: =IF('90_CANON_CONF_SOURCE'!K6='18_WEIGHT_CONTROL'!$A$5,'18_WEIGHT_CONTROL'!$B$5,IF('90_CANON_CONF_SOURCE'!K6='18_WEIGHT_CONTROL'!$A$6,'18_WEIGHT_CONTROL'!$B$6,IF('90_CANON_CONF_SOURCE'!K6='18_WEIGHT_CONTROL'!$A$7,'18_WEIGHT_CONTROL'!$B$7,'18_WEIGHT_CONTROL'!$B$8))) | ... Y6: =IF('90_CANON_CONF_SOURCE'!Y6='18_WEIGHT_CONTROL'!$A$5,'18_WEIGHT_CONTROL'!$B$5,IF('90_CANON_CONF_SOURCE'!Y6='18_WEIGHT_CONTROL'!$A$6,'18_WEIGHT_CONTROL'!$B$6,IF('90_CANON_CONF_SOURCE'!Y6='18_WEIGHT_CONTROL'!$A$7,'18_WEIGHT_CONTROL'!$B$7,'18_WEIGHT_CONTROL'!$B$8))) | Z6: =IF('91_MOTIF_CONF_SOURCE'!D6='18_WEIGHT_CONTROL'!$A$5,'18_WEIGHT_CONTROL'!$B$5,IF('91_MOTIF_CONF_SOURCE'!D6='18_WEIGHT_CONTROL'!$A$6,'18_WEIGHT_CONTROL'!$B$6,IF('91_MOTIF_CONF_SOURCE'!D6='18_WEIGHT_CONTROL'!$A$7,'18_WEIGHT_CONTROL'!$B$7,'18_WEIGHT_CONTROL'!$B$8))) | AA6: =IF('91_MOTIF_CONF_SOURCE'!E6='18_WEIGHT_CONTROL'!$A$5,'18_WEIGHT_CONTROL'!$B$5,IF('91_MOTIF_CONF_SOURCE'!E6='18_WEIGHT_CONTROL'!$A$6,'18_WEIGHT_CONTROL'!$B$6,IF('91_MOTIF_CONF_SOURCE'!E6='18_WEIGHT_CONTROL'!$A$7,'18_WEIGHT_CONTROL'!$B$7,'18_WEIGHT_CONTROL'!$B$8))) | AB6: =IF('91_MOTIF_CONF_SOURCE'!F6='18_WEIGHT_CONTROL'!$A$5,'18_WEIGHT_CONTROL'!$B$5,IF('91_MOTIF_CONF_SOURCE'!F6='18_WEIGHT_CONTROL'!$A$6,'18_WEIGHT_CONTROL'!$B$6,IF('91_MOTIF_CONF_SOURCE'!F6='18_WEIGHT_CONTROL'!$A$7,'18_WEIGHT_CONTROL'!$B$7,'18_WEIGHT_CONTROL'!$B$8))) | AC6: =IF('91_MOTIF_CONF_SOURCE'!G6='18_WEIGHT_CONTROL'!$A$5,'18_WEIGHT_CONTROL'!$B$5,IF('91_MOTIF_CONF_SOURCE'!G6='18_WEIGHT_CONTROL'!$A$6,'18_WEIGHT_CONTROL'!$B$6,IF('91_MOTIF_CONF_SOURCE'!G6='18_WEIGHT_CONTROL'!$A$7,'18_WEIGHT_CONTROL'!$B$7,'18_WEIGHT_CONTROL'!$B$8))) | AD6: =IF('91_MOTIF_CONF_SOURCE'!H6='18_WEIGHT_CONTROL'!$A$5,'18_WEIGHT_CONTROL'!$B$5,IF('91_MOTIF_CONF_SOURCE'!H6='18_WEIGHT_CONTROL'!$A$6,'18_WEIGHT_CONTROL'!$B$6,IF('91_MOTIF_CONF_SOURCE'!H6='18_WEIGHT_CONTROL'!$A$7,'18_WEIGHT_CONTROL'!$B$7,'18_WEIGHT_CONTROL'!$B$8))) | AE6: =IF('91_MOTIF_CONF_SOURCE'!I6='18_WEIGHT_CONTROL'!$A$5,'18_WEIGHT_CONTROL'!$B$5,IF('91_MOTIF_CONF_SOURCE'!I6='18_WEIGHT_CONTROL'!$A$6,'18_WEIGHT_CONTROL'!$B$6,IF('91_MOTIF_CONF_SOURCE'!I6='18_WEIGHT_CONTROL'!$A$7,'18_WEIGHT_CONTROL'!$B$7,'18_WEIGHT_CONTROL'!$B$8))) | AF6: =IF('91_MOTIF_CONF_SOURCE'!J6='18_WEIGHT_CONTROL'!$A$5,'18_WEIGHT_CONTROL'!$B$5,IF('91_MOTIF_CONF_SOURCE'!J6='18_WEIGHT_CONTROL'!$A$6,'18_WEIGHT_CONTROL'!$B$6,IF('91_MOTIF_CONF_SOURCE'!J6='18_WEIGHT_CONTROL'!$A$7,'18_WEIGHT_CONTROL'!$B$7,'18_WEIGHT_CONTROL'!$B$8))) | AG6: =IF('91_MOTIF_CONF_SOURCE'!K6='18_WEIGHT_CONTROL'!$A$5,'18_WEIGHT_CONTROL'!$B$5,IF('91_MOTIF_CONF_SOURCE'!K6='18_WEIGHT_CONTROL'!$A$6,'18_WEIGHT_CONTROL'!$B$6,IF('91_MOTIF_CONF_SOURCE'!K6='18_WEIGHT_CONTROL'!$A$7,'18_WEIGHT_CONTROL'!$B$7,'18_WEIGHT_CONTROL'!$B$8))) | ... AR6: =IF('91_MOTIF_CONF_SOURCE'!V6='18_WEIGHT_CONTROL'!$A$5,'18_WEIGHT_CONTROL'!$B$5,IF('91_MOTIF_CONF_SOURCE'!V6='18_WEIGHT_CONTROL'!$A$6,'18_WEIGHT_CONTROL'!$B$6,IF('91_MOTIF_CONF_SOURCE'!V6='18_WEIGHT_CONTROL'!$A$7,'18_WEIGHT_CONTROL'!$B$7,'18_WEIGHT_CONTROL'!$B$8)))
A7: 3 | B7: 天狼星人 | C7: Sirian | D7: =IF('90_CANON_CONF_SOURCE'!D7='18_WEIGHT_CONTROL'!$A$5,'18_WEIGHT_CONTROL'!$B$5,IF('90_CANON_CONF_SOURCE'!D7='18_WEIGHT_CONTROL'!$A$6,'18_WEIGHT_CONTROL'!$B$6,IF('90_CANON_CONF_SOURCE'!D7='18_WEIGHT_CONTROL'!$A$7,'18_WEIGHT_CONTROL'!$B$7,'18_WEIGHT_CONTROL'!$B$8))) | E7: =IF('90_CANON_CONF_SOURCE'!E7='18_WEIGHT_CONTROL'!$A$5,'18_WEIGHT_CONTROL'!$B$5,IF('90_CANON_CONF_SOURCE'!E7='18_WEIGHT_CONTROL'!$A$6,'18_WEIGHT_CONTROL'!$B$6,IF('90_CANON_CONF_SOURCE'!E7='18_WEIGHT_CONTROL'!$A$7,'18_WEIGHT_CONTROL'!$B$7,'18_WEIGHT_CONTROL'!$B$8))) | F7: =IF('90_CANON_CONF_SOURCE'!F7='18_WEIGHT_CONTROL'!$A$5,'18_WEIGHT_CONTROL'!$B$5,IF('90_CANON_CONF_SOURCE'!F7='18_WEIGHT_CONTROL'!$A$6,'18_WEIGHT_CONTROL'!$B$6,IF('90_CANON_CONF_SOURCE'!F7='18_WEIGHT_CONTROL'!$A$7,'18_WEIGHT_CONTROL'!$B$7,'18_WEIGHT_CONTROL'!$B$8))) | G7: =IF('90_CANON_CONF_SOURCE'!G7='18_WEIGHT_CONTROL'!$A$5,'18_WEIGHT_CONTROL'!$B$5,IF('90_CANON_CONF_SOURCE'!G7='18_WEIGHT_CONTROL'!$A$6,'18_WEIGHT_CONTROL'!$B$6,IF('90_CANON_CONF_SOURCE'!G7='18_WEIGHT_CONTROL'!$A$7,'18_WEIGHT_CONTROL'!$B$7,'18_WEIGHT_CONTROL'!$B$8))) | H7: =IF('90_CANON_CONF_SOURCE'!H7='18_WEIGHT_CONTROL'!$A$5,'18_WEIGHT_CONTROL'!$B$5,IF('90_CANON_CONF_SOURCE'!H7='18_WEIGHT_CONTROL'!$A$6,'18_WEIGHT_CONTROL'!$B$6,IF('90_CANON_CONF_SOURCE'!H7='18_WEIGHT_CONTROL'!$A$7,'18_WEIGHT_CONTROL'!$B$7,'18_WEIGHT_CONTROL'!$B$8))) | I7: =IF('90_CANON_CONF_SOURCE'!I7='18_WEIGHT_CONTROL'!$A$5,'18_WEIGHT_CONTROL'!$B$5,IF('90_CANON_CONF_SOURCE'!I7='18_WEIGHT_CONTROL'!$A$6,'18_WEIGHT_CONTROL'!$B$6,IF('90_CANON_CONF_SOURCE'!I7='18_WEIGHT_CONTROL'!$A$7,'18_WEIGHT_CONTROL'!$B$7,'18_WEIGHT_CONTROL'!$B$8))) | J7: =IF('90_CANON_CONF_SOURCE'!J7='18_WEIGHT_CONTROL'!$A$5,'18_WEIGHT_CONTROL'!$B$5,IF('90_CANON_CONF_SOURCE'!J7='18_WEIGHT_CONTROL'!$A$6,'18_WEIGHT_CONTROL'!$B$6,IF('90_CANON_CONF_SOURCE'!J7='18_WEIGHT_CONTROL'!$A$7,'18_WEIGHT_CONTROL'!$B$7,'18_WEIGHT_CONTROL'!$B$8))) | K7: =IF('90_CANON_CONF_SOURCE'!K7='18_WEIGHT_CONTROL'!$A$5,'18_WEIGHT_CONTROL'!$B$5,IF('90_CANON_CONF_SOURCE'!K7='18_WEIGHT_CONTROL'!$A$6,'18_WEIGHT_CONTROL'!$B$6,IF('90_CANON_CONF_SOURCE'!K7='18_WEIGHT_CONTROL'!$A$7,'18_WEIGHT_CONTROL'!$B$7,'18_WEIGHT_CONTROL'!$B$8))) | ... Y7: =IF('90_CANON_CONF_SOURCE'!Y7='18_WEIGHT_CONTROL'!$A$5,'18_WEIGHT_CONTROL'!$B$5,IF('90_CANON_CONF_SOURCE'!Y7='18_WEIGHT_CONTROL'!$A$6,'18_WEIGHT_CONTROL'!$B$6,IF('90_CANON_CONF_SOURCE'!Y7='18_WEIGHT_CONTROL'!$A$7,'18_WEIGHT_CONTROL'!$B$7,'18_WEIGHT_CONTROL'!$B$8))) | Z7: =IF('91_MOTIF_CONF_SOURCE'!D7='18_WEIGHT_CONTROL'!$A$5,'18_WEIGHT_CONTROL'!$B$5,IF('91_MOTIF_CONF_SOURCE'!D7='18_WEIGHT_CONTROL'!$A$6,'18_WEIGHT_CONTROL'!$B$6,IF('91_MOTIF_CONF_SOURCE'!D7='18_WEIGHT_CONTROL'!$A$7,'18_WEIGHT_CONTROL'!$B$7,'18_WEIGHT_CONTROL'!$B$8))) | AA7: =IF('91_MOTIF_CONF_SOURCE'!E7='18_WEIGHT_CONTROL'!$A$5,'18_WEIGHT_CONTROL'!$B$5,IF('91_MOTIF_CONF_SOURCE'!E7='18_WEIGHT_CONTROL'!$A$6,'18_WEIGHT_CONTROL'!$B$6,IF('91_MOTIF_CONF_SOURCE'!E7='18_WEIGHT_CONTROL'!$A$7,'18_WEIGHT_CONTROL'!$B$7,'18_WEIGHT_CONTROL'!$B$8))) | AB7: =IF('91_MOTIF_CONF_SOURCE'!F7='18_WEIGHT_CONTROL'!$A$5,'18_WEIGHT_CONTROL'!$B$5,IF('91_MOTIF_CONF_SOURCE'!F7='18_WEIGHT_CONTROL'!$A$6,'18_WEIGHT_CONTROL'!$B$6,IF('91_MOTIF_CONF_SOURCE'!F7='18_WEIGHT_CONTROL'!$A$7,'18_WEIGHT_CONTROL'!$B$7,'18_WEIGHT_CONTROL'!$B$8))) | AC7: =IF('91_MOTIF_CONF_SOURCE'!G7='18_WEIGHT_CONTROL'!$A$5,'18_WEIGHT_CONTROL'!$B$5,IF('91_MOTIF_CONF_SOURCE'!G7='18_WEIGHT_CONTROL'!$A$6,'18_WEIGHT_CONTROL'!$B$6,IF('91_MOTIF_CONF_SOURCE'!G7='18_WEIGHT_CONTROL'!$A$7,'18_WEIGHT_CONTROL'!$B$7,'18_WEIGHT_CONTROL'!$B$8))) | AD7: =IF('91_MOTIF_CONF_SOURCE'!H7='18_WEIGHT_CONTROL'!$A$5,'18_WEIGHT_CONTROL'!$B$5,IF('91_MOTIF_CONF_SOURCE'!H7='18_WEIGHT_CONTROL'!$A$6,'18_WEIGHT_CONTROL'!$B$6,IF('91_MOTIF_CONF_SOURCE'!H7='18_WEIGHT_CONTROL'!$A$7,'18_WEIGHT_CONTROL'!$B$7,'18_WEIGHT_CONTROL'!$B$8))) | AE7: =IF('91_MOTIF_CONF_SOURCE'!I7='18_WEIGHT_CONTROL'!$A$5,'18_WEIGHT_CONTROL'!$B$5,IF('91_MOTIF_CONF_SOURCE'!I7='18_WEIGHT_CONTROL'!$A$6,'18_WEIGHT_CONTROL'!$B$6,IF('91_MOTIF_CONF_SOURCE'!I7='18_WEIGHT_CONTROL'!$A$7,'18_WEIGHT_CONTROL'!$B$7,'18_WEIGHT_CONTROL'!$B$8))) | AF7: =IF('91_MOTIF_CONF_SOURCE'!J7='18_WEIGHT_CONTROL'!$A$5,'18_WEIGHT_CONTROL'!$B$5,IF('91_MOTIF_CONF_SOURCE'!J7='18_WEIGHT_CONTROL'!$A$6,'18_WEIGHT_CONTROL'!$B$6,IF('91_MOTIF_CONF_SOURCE'!J7='18_WEIGHT_CONTROL'!$A$7,'18_WEIGHT_CONTROL'!$B$7,'18_WEIGHT_CONTROL'!$B$8))) | AG7: =IF('91_MOTIF_CONF_SOURCE'!K7='18_WEIGHT_CONTROL'!$A$5,'18_WEIGHT_CONTROL'!$B$5,IF('91_MOTIF_CONF_SOURCE'!K7='18_WEIGHT_CONTROL'!$A$6,'18_WEIGHT_CONTROL'!$B$6,IF('91_MOTIF_CONF_SOURCE'!K7='18_WEIGHT_CONTROL'!$A$7,'18_WEIGHT_CONTROL'!$B$7,'18_WEIGHT_CONTROL'!$B$8))) | ... AR7: =IF('91_MOTIF_CONF_SOURCE'!V7='18_WEIGHT_CONTROL'!$A$5,'18_WEIGHT_CONTROL'!$B$5,IF('91_MOTIF_CONF_SOURCE'!V7='18_WEIGHT_CONTROL'!$A$6,'18_WEIGHT_CONTROL'!$B$6,IF('91_MOTIF_CONF_SOURCE'!V7='18_WEIGHT_CONTROL'!$A$7,'18_WEIGHT_CONTROL'!$B$7,'18_WEIGHT_CONTROL'!$B$8)))
A8: 4 | B8: 仙女座人 | C8: Andromedan | D8: =IF('90_CANON_CONF_SOURCE'!D8='18_WEIGHT_CONTROL'!$A$5,'18_WEIGHT_CONTROL'!$B$5,IF('90_CANON_CONF_SOURCE'!D8='18_WEIGHT_CONTROL'!$A$6,'18_WEIGHT_CONTROL'!$B$6,IF('90_CANON_CONF_SOURCE'!D8='18_WEIGHT_CONTROL'!$A$7,'18_WEIGHT_CONTROL'!$B$7,'18_WEIGHT_CONTROL'!$B$8))) | E8: =IF('90_CANON_CONF_SOURCE'!E8='18_WEIGHT_CONTROL'!$A$5,'18_WEIGHT_CONTROL'!$B$5,IF('90_CANON_CONF_SOURCE'!E8='18_WEIGHT_CONTROL'!$A$6,'18_WEIGHT_CONTROL'!$B$6,IF('90_CANON_CONF_SOURCE'!E8='18_WEIGHT_CONTROL'!$A$7,'18_WEIGHT_CONTROL'!$B$7,'18_WEIGHT_CONTROL'!$B$8))) | F8: =IF('90_CANON_CONF_SOURCE'!F8='18_WEIGHT_CONTROL'!$A$5,'18_WEIGHT_CONTROL'!$B$5,IF('90_CANON_CONF_SOURCE'!F8='18_WEIGHT_CONTROL'!$A$6,'18_WEIGHT_CONTROL'!$B$6,IF('90_CANON_CONF_SOURCE'!F8='18_WEIGHT_CONTROL'!$A$7,'18_WEIGHT_CONTROL'!$B$7,'18_WEIGHT_CONTROL'!$B$8))) | G8: =IF('90_CANON_CONF_SOURCE'!G8='18_WEIGHT_CONTROL'!$A$5,'18_WEIGHT_CONTROL'!$B$5,IF('90_CANON_CONF_SOURCE'!G8='18_WEIGHT_CONTROL'!$A$6,'18_WEIGHT_CONTROL'!$B$6,IF('90_CANON_CONF_SOURCE'!G8='18_WEIGHT_CONTROL'!$A$7,'18_WEIGHT_CONTROL'!$B$7,'18_WEIGHT_CONTROL'!$B$8))) | H8: =IF('90_CANON_CONF_SOURCE'!H8='18_WEIGHT_CONTROL'!$A$5,'18_WEIGHT_CONTROL'!$B$5,IF('90_CANON_CONF_SOURCE'!H8='18_WEIGHT_CONTROL'!$A$6,'18_WEIGHT_CONTROL'!$B$6,IF('90_CANON_CONF_SOURCE'!H8='18_WEIGHT_CONTROL'!$A$7,'18_WEIGHT_CONTROL'!$B$7,'18_WEIGHT_CONTROL'!$B$8))) | I8: =IF('90_CANON_CONF_SOURCE'!I8='18_WEIGHT_CONTROL'!$A$5,'18_WEIGHT_CONTROL'!$B$5,IF('90_CANON_CONF_SOURCE'!I8='18_WEIGHT_CONTROL'!$A$6,'18_WEIGHT_CONTROL'!$B$6,IF('90_CANON_CONF_SOURCE'!I8='18_WEIGHT_CONTROL'!$A$7,'18_WEIGHT_CONTROL'!$B$7,'18_WEIGHT_CONTROL'!$B$8))) | J8: =IF('90_CANON_CONF_SOURCE'!J8='18_WEIGHT_CONTROL'!$A$5,'18_WEIGHT_CONTROL'!$B$5,IF('90_CANON_CONF_SOURCE'!J8='18_WEIGHT_CONTROL'!$A$6,'18_WEIGHT_CONTROL'!$B$6,IF('90_CANON_CONF_SOURCE'!J8='18_WEIGHT_CONTROL'!$A$7,'18_WEIGHT_CONTROL'!$B$7,'18_WEIGHT_CONTROL'!$B$8))) | K8: =IF('90_CANON_CONF_SOURCE'!K8='18_WEIGHT_CONTROL'!$A$5,'18_WEIGHT_CONTROL'!$B$5,IF('90_CANON_CONF_SOURCE'!K8='18_WEIGHT_CONTROL'!$A$6,'18_WEIGHT_CONTROL'!$B$6,IF('90_CANON_CONF_SOURCE'!K8='18_WEIGHT_CONTROL'!$A$7,'18_WEIGHT_CONTROL'!$B$7,'18_WEIGHT_CONTROL'!$B$8))) | ... Y8: =IF('90_CANON_CONF_SOURCE'!Y8='18_WEIGHT_CONTROL'!$A$5,'18_WEIGHT_CONTROL'!$B$5,IF('90_CANON_CONF_SOURCE'!Y8='18_WEIGHT_CONTROL'!$A$6,'18_WEIGHT_CONTROL'!$B$6,IF('90_CANON_CONF_SOURCE'!Y8='18_WEIGHT_CONTROL'!$A$7,'18_WEIGHT_CONTROL'!$B$7,'18_WEIGHT_CONTROL'!$B$8))) | Z8: =IF('91_MOTIF_CONF_SOURCE'!D8='18_WEIGHT_CONTROL'!$A$5,'18_WEIGHT_CONTROL'!$B$5,IF('91_MOTIF_CONF_SOURCE'!D8='18_WEIGHT_CONTROL'!$A$6,'18_WEIGHT_CONTROL'!$B$6,IF('91_MOTIF_CONF_SOURCE'!D8='18_WEIGHT_CONTROL'!$A$7,'18_WEIGHT_CONTROL'!$B$7,'18_WEIGHT_CONTROL'!$B$8))) | AA8: =IF('91_MOTIF_CONF_SOURCE'!E8='18_WEIGHT_CONTROL'!$A$5,'18_WEIGHT_CONTROL'!$B$5,IF('91_MOTIF_CONF_SOURCE'!E8='18_WEIGHT_CONTROL'!$A$6,'18_WEIGHT_CONTROL'!$B$6,IF('91_MOTIF_CONF_SOURCE'!E8='18_WEIGHT_CONTROL'!$A$7,'18_WEIGHT_CONTROL'!$B$7,'18_WEIGHT_CONTROL'!$B$8))) | AB8: =IF('91_MOTIF_CONF_SOURCE'!F8='18_WEIGHT_CONTROL'!$A$5,'18_WEIGHT_CONTROL'!$B$5,IF('91_MOTIF_CONF_SOURCE'!F8='18_WEIGHT_CONTROL'!$A$6,'18_WEIGHT_CONTROL'!$B$6,IF('91_MOTIF_CONF_SOURCE'!F8='18_WEIGHT_CONTROL'!$A$7,'18_WEIGHT_CONTROL'!$B$7,'18_WEIGHT_CONTROL'!$B$8))) | AC8: =IF('91_MOTIF_CONF_SOURCE'!G8='18_WEIGHT_CONTROL'!$A$5,'18_WEIGHT_CONTROL'!$B$5,IF('91_MOTIF_CONF_SOURCE'!G8='18_WEIGHT_CONTROL'!$A$6,'18_WEIGHT_CONTROL'!$B$6,IF('91_MOTIF_CONF_SOURCE'!G8='18_WEIGHT_CONTROL'!$A$7,'18_WEIGHT_CONTROL'!$B$7,'18_WEIGHT_CONTROL'!$B$8))) | AD8: =IF('91_MOTIF_CONF_SOURCE'!H8='18_WEIGHT_CONTROL'!$A$5,'18_WEIGHT_CONTROL'!$B$5,IF('91_MOTIF_CONF_SOURCE'!H8='18_WEIGHT_CONTROL'!$A$6,'18_WEIGHT_CONTROL'!$B$6,IF('91_MOTIF_CONF_SOURCE'!H8='18_WEIGHT_CONTROL'!$A$7,'18_WEIGHT_CONTROL'!$B$7,'18_WEIGHT_CONTROL'!$B$8))) | AE8: =IF('91_MOTIF_CONF_SOURCE'!I8='18_WEIGHT_CONTROL'!$A$5,'18_WEIGHT_CONTROL'!$B$5,IF('91_MOTIF_CONF_SOURCE'!I8='18_WEIGHT_CONTROL'!$A$6,'18_WEIGHT_CONTROL'!$B$6,IF('91_MOTIF_CONF_SOURCE'!I8='18_WEIGHT_CONTROL'!$A$7,'18_WEIGHT_CONTROL'!$B$7,'18_WEIGHT_CONTROL'!$B$8))) | AF8: =IF('91_MOTIF_CONF_SOURCE'!J8='18_WEIGHT_CONTROL'!$A$5,'18_WEIGHT_CONTROL'!$B$5,IF('91_MOTIF_CONF_SOURCE'!J8='18_WEIGHT_CONTROL'!$A$6,'18_WEIGHT_CONTROL'!$B$6,IF('91_MOTIF_CONF_SOURCE'!J8='18_WEIGHT_CONTROL'!$A$7,'18_WEIGHT_CONTROL'!$B$7,'18_WEIGHT_CONTROL'!$B$8))) | AG8: =IF('91_MOTIF_CONF_SOURCE'!K8='18_WEIGHT_CONTROL'!$A$5,'18_WEIGHT_CONTROL'!$B$5,IF('91_MOTIF_CONF_SOURCE'!K8='18_WEIGHT_CONTROL'!$A$6,'18_WEIGHT_CONTROL'!$B$6,IF('91_MOTIF_CONF_SOURCE'!K8='18_WEIGHT_CONTROL'!$A$7,'18_WEIGHT_CONTROL'!$B$7,'18_WEIGHT_CONTROL'!$B$8))) | ... AR8: =IF('91_MOTIF_CONF_SOURCE'!V8='18_WEIGHT_CONTROL'!$A$5,'18_WEIGHT_CONTROL'!$B$5,IF('91_MOTIF_CONF_SOURCE'!V8='18_WEIGHT_CONTROL'!$A$6,'18_WEIGHT_CONTROL'!$B$6,IF('91_MOTIF_CONF_SOURCE'!V8='18_WEIGHT_CONTROL'!$A$7,'18_WEIGHT_CONTROL'!$B$7,'18_WEIGHT_CONTROL'!$B$8)))
A9: 5 | B9: 天琴座人 | C9: Lyran | D9: =IF('90_CANON_CONF_SOURCE'!D9='18_WEIGHT_CONTROL'!$A$5,'18_WEIGHT_CONTROL'!$B$5,IF('90_CANON_CONF_SOURCE'!D9='18_WEIGHT_CONTROL'!$A$6,'18_WEIGHT_CONTROL'!$B$6,IF('90_CANON_CONF_SOURCE'!D9='18_WEIGHT_CONTROL'!$A$7,'18_WEIGHT_CONTROL'!$B$7,'18_WEIGHT_CONTROL'!$B$8))) | E9: =IF('90_CANON_CONF_SOURCE'!E9='18_WEIGHT_CONTROL'!$A$5,'18_WEIGHT_CONTROL'!$B$5,IF('90_CANON_CONF_SOURCE'!E9='18_WEIGHT_CONTROL'!$A$6,'18_WEIGHT_CONTROL'!$B$6,IF('90_CANON_CONF_SOURCE'!E9='18_WEIGHT_CONTROL'!$A$7,'18_WEIGHT_CONTROL'!$B$7,'18_WEIGHT_CONTROL'!$B$8))) | F9: =IF('90_CANON_CONF_SOURCE'!F9='18_WEIGHT_CONTROL'!$A$5,'18_WEIGHT_CONTROL'!$B$5,IF('90_CANON_CONF_SOURCE'!F9='18_WEIGHT_CONTROL'!$A$6,'18_WEIGHT_CONTROL'!$B$6,IF('90_CANON_CONF_SOURCE'!F9='18_WEIGHT_CONTROL'!$A$7,'18_WEIGHT_CONTROL'!$B$7,'18_WEIGHT_CONTROL'!$B$8))) | G9: =IF('90_CANON_CONF_SOURCE'!G9='18_WEIGHT_CONTROL'!$A$5,'18_WEIGHT_CONTROL'!$B$5,IF('90_CANON_CONF_SOURCE'!G9='18_WEIGHT_CONTROL'!$A$6,'18_WEIGHT_CONTROL'!$B$6,IF('90_CANON_CONF_SOURCE'!G9='18_WEIGHT_CONTROL'!$A$7,'18_WEIGHT_CONTROL'!$B$7,'18_WEIGHT_CONTROL'!$B$8))) | H9: =IF('90_CANON_CONF_SOURCE'!H9='18_WEIGHT_CONTROL'!$A$5,'18_WEIGHT_CONTROL'!$B$5,IF('90_CANON_CONF_SOURCE'!H9='18_WEIGHT_CONTROL'!$A$6,'18_WEIGHT_CONTROL'!$B$6,IF('90_CANON_CONF_SOURCE'!H9='18_WEIGHT_CONTROL'!$A$7,'18_WEIGHT_CONTROL'!$B$7,'18_WEIGHT_CONTROL'!$B$8))) | I9: =IF('90_CANON_CONF_SOURCE'!I9='18_WEIGHT_CONTROL'!$A$5,'18_WEIGHT_CONTROL'!$B$5,IF('90_CANON_CONF_SOURCE'!I9='18_WEIGHT_CONTROL'!$A$6,'18_WEIGHT_CONTROL'!$B$6,IF('90_CANON_CONF_SOURCE'!I9='18_WEIGHT_CONTROL'!$A$7,'18_WEIGHT_CONTROL'!$B$7,'18_WEIGHT_CONTROL'!$B$8))) | J9: =IF('90_CANON_CONF_SOURCE'!J9='18_WEIGHT_CONTROL'!$A$5,'18_WEIGHT_CONTROL'!$B$5,IF('90_CANON_CONF_SOURCE'!J9='18_WEIGHT_CONTROL'!$A$6,'18_WEIGHT_CONTROL'!$B$6,IF('90_CANON_CONF_SOURCE'!J9='18_WEIGHT_CONTROL'!$A$7,'18_WEIGHT_CONTROL'!$B$7,'18_WEIGHT_CONTROL'!$B$8))) | K9: =IF('90_CANON_CONF_SOURCE'!K9='18_WEIGHT_CONTROL'!$A$5,'18_WEIGHT_CONTROL'!$B$5,IF('90_CANON_CONF_SOURCE'!K9='18_WEIGHT_CONTROL'!$A$6,'18_WEIGHT_CONTROL'!$B$6,IF('90_CANON_CONF_SOURCE'!K9='18_WEIGHT_CONTROL'!$A$7,'18_WEIGHT_CONTROL'!$B$7,'18_WEIGHT_CONTROL'!$B$8))) | ... Y9: =IF('90_CANON_CONF_SOURCE'!Y9='18_WEIGHT_CONTROL'!$A$5,'18_WEIGHT_CONTROL'!$B$5,IF('90_CANON_CONF_SOURCE'!Y9='18_WEIGHT_CONTROL'!$A$6,'18_WEIGHT_CONTROL'!$B$6,IF('90_CANON_CONF_SOURCE'!Y9='18_WEIGHT_CONTROL'!$A$7,'18_WEIGHT_CONTROL'!$B$7,'18_WEIGHT_CONTROL'!$B$8))) | Z9: =IF('91_MOTIF_CONF_SOURCE'!D9='18_WEIGHT_CONTROL'!$A$5,'18_WEIGHT_CONTROL'!$B$5,IF('91_MOTIF_CONF_SOURCE'!D9='18_WEIGHT_CONTROL'!$A$6,'18_WEIGHT_CONTROL'!$B$6,IF('91_MOTIF_CONF_SOURCE'!D9='18_WEIGHT_CONTROL'!$A$7,'18_WEIGHT_CONTROL'!$B$7,'18_WEIGHT_CONTROL'!$B$8))) | AA9: =IF('91_MOTIF_CONF_SOURCE'!E9='18_WEIGHT_CONTROL'!$A$5,'18_WEIGHT_CONTROL'!$B$5,IF('91_MOTIF_CONF_SOURCE'!E9='18_WEIGHT_CONTROL'!$A$6,'18_WEIGHT_CONTROL'!$B$6,IF('91_MOTIF_CONF_SOURCE'!E9='18_WEIGHT_CONTROL'!$A$7,'18_WEIGHT_CONTROL'!$B$7,'18_WEIGHT_CONTROL'!$B$8))) | AB9: =IF('91_MOTIF_CONF_SOURCE'!F9='18_WEIGHT_CONTROL'!$A$5,'18_WEIGHT_CONTROL'!$B$5,IF('91_MOTIF_CONF_SOURCE'!F9='18_WEIGHT_CONTROL'!$A$6,'18_WEIGHT_CONTROL'!$B$6,IF('91_MOTIF_CONF_SOURCE'!F9='18_WEIGHT_CONTROL'!$A$7,'18_WEIGHT_CONTROL'!$B$7,'18_WEIGHT_CONTROL'!$B$8))) | AC9: =IF('91_MOTIF_CONF_SOURCE'!G9='18_WEIGHT_CONTROL'!$A$5,'18_WEIGHT_CONTROL'!$B$5,IF('91_MOTIF_CONF_SOURCE'!G9='18_WEIGHT_CONTROL'!$A$6,'18_WEIGHT_CONTROL'!$B$6,IF('91_MOTIF_CONF_SOURCE'!G9='18_WEIGHT_CONTROL'!$A$7,'18_WEIGHT_CONTROL'!$B$7,'18_WEIGHT_CONTROL'!$B$8))) | AD9: =IF('91_MOTIF_CONF_SOURCE'!H9='18_WEIGHT_CONTROL'!$A$5,'18_WEIGHT_CONTROL'!$B$5,IF('91_MOTIF_CONF_SOURCE'!H9='18_WEIGHT_CONTROL'!$A$6,'18_WEIGHT_CONTROL'!$B$6,IF('91_MOTIF_CONF_SOURCE'!H9='18_WEIGHT_CONTROL'!$A$7,'18_WEIGHT_CONTROL'!$B$7,'18_WEIGHT_CONTROL'!$B$8))) | AE9: =IF('91_MOTIF_CONF_SOURCE'!I9='18_WEIGHT_CONTROL'!$A$5,'18_WEIGHT_CONTROL'!$B$5,IF('91_MOTIF_CONF_SOURCE'!I9='18_WEIGHT_CONTROL'!$A$6,'18_WEIGHT_CONTROL'!$B$6,IF('91_MOTIF_CONF_SOURCE'!I9='18_WEIGHT_CONTROL'!$A$7,'18_WEIGHT_CONTROL'!$B$7,'18_WEIGHT_CONTROL'!$B$8))) | AF9: =IF('91_MOTIF_CONF_SOURCE'!J9='18_WEIGHT_CONTROL'!$A$5,'18_WEIGHT_CONTROL'!$B$5,IF('91_MOTIF_CONF_SOURCE'!J9='18_WEIGHT_CONTROL'!$A$6,'18_WEIGHT_CONTROL'!$B$6,IF('91_MOTIF_CONF_SOURCE'!J9='18_WEIGHT_CONTROL'!$A$7,'18_WEIGHT_CONTROL'!$B$7,'18_WEIGHT_CONTROL'!$B$8))) | AG9: =IF('91_MOTIF_CONF_SOURCE'!K9='18_WEIGHT_CONTROL'!$A$5,'18_WEIGHT_CONTROL'!$B$5,IF('91_MOTIF_CONF_SOURCE'!K9='18_WEIGHT_CONTROL'!$A$6,'18_WEIGHT_CONTROL'!$B$6,IF('91_MOTIF_CONF_SOURCE'!K9='18_WEIGHT_CONTROL'!$A$7,'18_WEIGHT_CONTROL'!$B$7,'18_WEIGHT_CONTROL'!$B$8))) | ... AR9: =IF('91_MOTIF_CONF_SOURCE'!V9='18_WEIGHT_CONTROL'!$A$5,'18_WEIGHT_CONTROL'!$B$5,IF('91_MOTIF_CONF_SOURCE'!V9='18_WEIGHT_CONTROL'!$A$6,'18_WEIGHT_CONTROL'!$B$6,IF('91_MOTIF_CONF_SOURCE'!V9='18_WEIGHT_CONTROL'!$A$7,'18_WEIGHT_CONTROL'!$B$7,'18_WEIGHT_CONTROL'!$B$8)))
A10: 6 | B10: 獵戶座人 | C10: Orion | D10: =IF('90_CANON_CONF_SOURCE'!D10='18_WEIGHT_CONTROL'!$A$5,'18_WEIGHT_CONTROL'!$B$5,IF('90_CANON_CONF_SOURCE'!D10='18_WEIGHT_CONTROL'!$A$6,'18_WEIGHT_CONTROL'!$B$6,IF('90_CANON_CONF_SOURCE'!D10='18_WEIGHT_CONTROL'!$A$7,'18_WEIGHT_CONTROL'!$B$7,'18_WEIGHT_CONTROL'!$B$8))) | E10: =IF('90_CANON_CONF_SOURCE'!E10='18_WEIGHT_CONTROL'!$A$5,'18_WEIGHT_CONTROL'!$B$5,IF('90_CANON_CONF_SOURCE'!E10='18_WEIGHT_CONTROL'!$A$6,'18_WEIGHT_CONTROL'!$B$6,IF('90_CANON_CONF_SOURCE'!E10='18_WEIGHT_CONTROL'!$A$7,'18_WEIGHT_CONTROL'!$B$7,'18_WEIGHT_CONTROL'!$B$8))) | F10: =IF('90_CANON_CONF_SOURCE'!F10='18_WEIGHT_CONTROL'!$A$5,'18_WEIGHT_CONTROL'!$B$5,IF('90_CANON_CONF_SOURCE'!F10='18_WEIGHT_CONTROL'!$A$6,'18_WEIGHT_CONTROL'!$B$6,IF('90_CANON_CONF_SOURCE'!F10='18_WEIGHT_CONTROL'!$A$7,'18_WEIGHT_CONTROL'!$B$7,'18_WEIGHT_CONTROL'!$B$8))) | G10: =IF('90_CANON_CONF_SOURCE'!G10='18_WEIGHT_CONTROL'!$A$5,'18_WEIGHT_CONTROL'!$B$5,IF('90_CANON_CONF_SOURCE'!G10='18_WEIGHT_CONTROL'!$A$6,'18_WEIGHT_CONTROL'!$B$6,IF('90_CANON_CONF_SOURCE'!G10='18_WEIGHT_CONTROL'!$A$7,'18_WEIGHT_CONTROL'!$B$7,'18_WEIGHT_CONTROL'!$B$8))) | H10: =IF('90_CANON_CONF_SOURCE'!H10='18_WEIGHT_CONTROL'!$A$5,'18_WEIGHT_CONTROL'!$B$5,IF('90_CANON_CONF_SOURCE'!H10='18_WEIGHT_CONTROL'!$A$6,'18_WEIGHT_CONTROL'!$B$6,IF('90_CANON_CONF_SOURCE'!H10='18_WEIGHT_CONTROL'!$A$7,'18_WEIGHT_CONTROL'!$B$7,'18_WEIGHT_CONTROL'!$B$8))) | I10: =IF('90_CANON_CONF_SOURCE'!I10='18_WEIGHT_CONTROL'!$A$5,'18_WEIGHT_CONTROL'!$B$5,IF('90_CANON_CONF_SOURCE'!I10='18_WEIGHT_CONTROL'!$A$6,'18_WEIGHT_CONTROL'!$B$6,IF('90_CANON_CONF_SOURCE'!I10='18_WEIGHT_CONTROL'!$A$7,'18_WEIGHT_CONTROL'!$B$7,'18_WEIGHT_CONTROL'!$B$8))) | J10: =IF('90_CANON_CONF_SOURCE'!J10='18_WEIGHT_CONTROL'!$A$5,'18_WEIGHT_CONTROL'!$B$5,IF('90_CANON_CONF_SOURCE'!J10='18_WEIGHT_CONTROL'!$A$6,'18_WEIGHT_CONTROL'!$B$6,IF('90_CANON_CONF_SOURCE'!J10='18_WEIGHT_CONTROL'!$A$7,'18_WEIGHT_CONTROL'!$B$7,'18_WEIGHT_CONTROL'!$B$8))) | K10: =IF('90_CANON_CONF_SOURCE'!K10='18_WEIGHT_CONTROL'!$A$5,'18_WEIGHT_CONTROL'!$B$5,IF('90_CANON_CONF_SOURCE'!K10='18_WEIGHT_CONTROL'!$A$6,'18_WEIGHT_CONTROL'!$B$6,IF('90_CANON_CONF_SOURCE'!K10='18_WEIGHT_CONTROL'!$A$7,'18_WEIGHT_CONTROL'!$B$7,'18_WEIGHT_CONTROL'!$B$8))) | ... Y10: =IF('90_CANON_CONF_SOURCE'!Y10='18_WEIGHT_CONTROL'!$A$5,'18_WEIGHT_CONTROL'!$B$5,IF('90_CANON_CONF_SOURCE'!Y10='18_WEIGHT_CONTROL'!$A$6,'18_WEIGHT_CONTROL'!$B$6,IF('90_CANON_CONF_SOURCE'!Y10='18_WEIGHT_CONTROL'!$A$7,'18_WEIGHT_CONTROL'!$B$7,'18_WEIGHT_CONTROL'!$B$8))) | Z10: =IF('91_MOTIF_CONF_SOURCE'!D10='18_WEIGHT_CONTROL'!$A$5,'18_WEIGHT_CONTROL'!$B$5,IF('91_MOTIF_CONF_SOURCE'!D10='18_WEIGHT_CONTROL'!$A$6,'18_WEIGHT_CONTROL'!$B$6,IF('91_MOTIF_CONF_SOURCE'!D10='18_WEIGHT_CONTROL'!$A$7,'18_WEIGHT_CONTROL'!$B$7,'18_WEIGHT_CONTROL'!$B$8))) | AA10: =IF('91_MOTIF_CONF_SOURCE'!E10='18_WEIGHT_CONTROL'!$A$5,'18_WEIGHT_CONTROL'!$B$5,IF('91_MOTIF_CONF_SOURCE'!E10='18_WEIGHT_CONTROL'!$A$6,'18_WEIGHT_CONTROL'!$B$6,IF('91_MOTIF_CONF_SOURCE'!E10='18_WEIGHT_CONTROL'!$A$7,'18_WEIGHT_CONTROL'!$B$7,'18_WEIGHT_CONTROL'!$B$8))) | AB10: =IF('91_MOTIF_CONF_SOURCE'!F10='18_WEIGHT_CONTROL'!$A$5,'18_WEIGHT_CONTROL'!$B$5,IF('91_MOTIF_CONF_SOURCE'!F10='18_WEIGHT_CONTROL'!$A$6,'18_WEIGHT_CONTROL'!$B$6,IF('91_MOTIF_CONF_SOURCE'!F10='18_WEIGHT_CONTROL'!$A$7,'18_WEIGHT_CONTROL'!$B$7,'18_WEIGHT_CONTROL'!$B$8))) | AC10: =IF('91_MOTIF_CONF_SOURCE'!G10='18_WEIGHT_CONTROL'!$A$5,'18_WEIGHT_CONTROL'!$B$5,IF('91_MOTIF_CONF_SOURCE'!G10='18_WEIGHT_CONTROL'!$A$6,'18_WEIGHT_CONTROL'!$B$6,IF('91_MOTIF_CONF_SOURCE'!G10='18_WEIGHT_CONTROL'!$A$7,'18_WEIGHT_CONTROL'!$B$7,'18_WEIGHT_CONTROL'!$B$8))) | AD10: =IF('91_MOTIF_CONF_SOURCE'!H10='18_WEIGHT_CONTROL'!$A$5,'18_WEIGHT_CONTROL'!$B$5,IF('91_MOTIF_CONF_SOURCE'!H10='18_WEIGHT_CONTROL'!$A$6,'18_WEIGHT_CONTROL'!$B$6,IF('91_MOTIF_CONF_SOURCE'!H10='18_WEIGHT_CONTROL'!$A$7,'18_WEIGHT_CONTROL'!$B$7,'18_WEIGHT_CONTROL'!$B$8))) | AE10: =IF('91_MOTIF_CONF_SOURCE'!I10='18_WEIGHT_CONTROL'!$A$5,'18_WEIGHT_CONTROL'!$B$5,IF('91_MOTIF_CONF_SOURCE'!I10='18_WEIGHT_CONTROL'!$A$6,'18_WEIGHT_CONTROL'!$B$6,IF('91_MOTIF_CONF_SOURCE'!I10='18_WEIGHT_CONTROL'!$A$7,'18_WEIGHT_CONTROL'!$B$7,'18_WEIGHT_CONTROL'!$B$8))) | AF10: =IF('91_MOTIF_CONF_SOURCE'!J10='18_WEIGHT_CONTROL'!$A$5,'18_WEIGHT_CONTROL'!$B$5,IF('91_MOTIF_CONF_SOURCE'!J10='18_WEIGHT_CONTROL'!$A$6,'18_WEIGHT_CONTROL'!$B$6,IF('91_MOTIF_CONF_SOURCE'!J10='18_WEIGHT_CONTROL'!$A$7,'18_WEIGHT_CONTROL'!$B$7,'18_WEIGHT_CONTROL'!$B$8))) | AG10: =IF('91_MOTIF_CONF_SOURCE'!K10='18_WEIGHT_CONTROL'!$A$5,'18_WEIGHT_CONTROL'!$B$5,IF('91_MOTIF_CONF_SOURCE'!K10='18_WEIGHT_CONTROL'!$A$6,'18_WEIGHT_CONTROL'!$B$6,IF('91_MOTIF_CONF_SOURCE'!K10='18_WEIGHT_CONTROL'!$A$7,'18_WEIGHT_CONTROL'!$B$7,'18_WEIGHT_CONTROL'!$B$8))) | ... AR10: =IF('91_MOTIF_CONF_SOURCE'!V10='18_WEIGHT_CONTROL'!$A$5,'18_WEIGHT_CONTROL'!$B$5,IF('91_MOTIF_CONF_SOURCE'!V10='18_WEIGHT_CONTROL'!$A$6,'18_WEIGHT_CONTROL'!$B$6,IF('91_MOTIF_CONF_SOURCE'!V10='18_WEIGHT_CONTROL'!$A$7,'18_WEIGHT_CONTROL'!$B$7,'18_WEIGHT_CONTROL'!$B$8)))
A11: 7 | B11: 明塔卡星人 | C11: Mintakan | D11: =IF('90_CANON_CONF_SOURCE'!D11='18_WEIGHT_CONTROL'!$A$5,'18_WEIGHT_CONTROL'!$B$5,IF('90_CANON_CONF_SOURCE'!D11='18_WEIGHT_CONTROL'!$A$6,'18_WEIGHT_CONTROL'!$B$6,IF('90_CANON_CONF_SOURCE'!D11='18_WEIGHT_CONTROL'!$A$7,'18_WEIGHT_CONTROL'!$B$7,'18_WEIGHT_CONTROL'!$B$8))) | E11: =IF('90_CANON_CONF_SOURCE'!E11='18_WEIGHT_CONTROL'!$A$5,'18_WEIGHT_CONTROL'!$B$5,IF('90_CANON_CONF_SOURCE'!E11='18_WEIGHT_CONTROL'!$A$6,'18_WEIGHT_CONTROL'!$B$6,IF('90_CANON_CONF_SOURCE'!E11='18_WEIGHT_CONTROL'!$A$7,'18_WEIGHT_CONTROL'!$B$7,'18_WEIGHT_CONTROL'!$B$8))) | F11: =IF('90_CANON_CONF_SOURCE'!F11='18_WEIGHT_CONTROL'!$A$5,'18_WEIGHT_CONTROL'!$B$5,IF('90_CANON_CONF_SOURCE'!F11='18_WEIGHT_CONTROL'!$A$6,'18_WEIGHT_CONTROL'!$B$6,IF('90_CANON_CONF_SOURCE'!F11='18_WEIGHT_CONTROL'!$A$7,'18_WEIGHT_CONTROL'!$B$7,'18_WEIGHT_CONTROL'!$B$8))) | G11: =IF('90_CANON_CONF_SOURCE'!G11='18_WEIGHT_CONTROL'!$A$5,'18_WEIGHT_CONTROL'!$B$5,IF('90_CANON_CONF_SOURCE'!G11='18_WEIGHT_CONTROL'!$A$6,'18_WEIGHT_CONTROL'!$B$6,IF('90_CANON_CONF_SOURCE'!G11='18_WEIGHT_CONTROL'!$A$7,'18_WEIGHT_CONTROL'!$B$7,'18_WEIGHT_CONTROL'!$B$8))) | H11: =IF('90_CANON_CONF_SOURCE'!H11='18_WEIGHT_CONTROL'!$A$5,'18_WEIGHT_CONTROL'!$B$5,IF('90_CANON_CONF_SOURCE'!H11='18_WEIGHT_CONTROL'!$A$6,'18_WEIGHT_CONTROL'!$B$6,IF('90_CANON_CONF_SOURCE'!H11='18_WEIGHT_CONTROL'!$A$7,'18_WEIGHT_CONTROL'!$B$7,'18_WEIGHT_CONTROL'!$B$8))) | I11: =IF('90_CANON_CONF_SOURCE'!I11='18_WEIGHT_CONTROL'!$A$5,'18_WEIGHT_CONTROL'!$B$5,IF('90_CANON_CONF_SOURCE'!I11='18_WEIGHT_CONTROL'!$A$6,'18_WEIGHT_CONTROL'!$B$6,IF('90_CANON_CONF_SOURCE'!I11='18_WEIGHT_CONTROL'!$A$7,'18_WEIGHT_CONTROL'!$B$7,'18_WEIGHT_CONTROL'!$B$8))) | J11: =IF('90_CANON_CONF_SOURCE'!J11='18_WEIGHT_CONTROL'!$A$5,'18_WEIGHT_CONTROL'!$B$5,IF('90_CANON_CONF_SOURCE'!J11='18_WEIGHT_CONTROL'!$A$6,'18_WEIGHT_CONTROL'!$B$6,IF('90_CANON_CONF_SOURCE'!J11='18_WEIGHT_CONTROL'!$A$7,'18_WEIGHT_CONTROL'!$B$7,'18_WEIGHT_CONTROL'!$B$8))) | K11: =IF('90_CANON_CONF_SOURCE'!K11='18_WEIGHT_CONTROL'!$A$5,'18_WEIGHT_CONTROL'!$B$5,IF('90_CANON_CONF_SOURCE'!K11='18_WEIGHT_CONTROL'!$A$6,'18_WEIGHT_CONTROL'!$B$6,IF('90_CANON_CONF_SOURCE'!K11='18_WEIGHT_CONTROL'!$A$7,'18_WEIGHT_CONTROL'!$B$7,'18_WEIGHT_CONTROL'!$B$8))) | ... Y11: =IF('90_CANON_CONF_SOURCE'!Y11='18_WEIGHT_CONTROL'!$A$5,'18_WEIGHT_CONTROL'!$B$5,IF('90_CANON_CONF_SOURCE'!Y11='18_WEIGHT_CONTROL'!$A$6,'18_WEIGHT_CONTROL'!$B$6,IF('90_CANON_CONF_SOURCE'!Y11='18_WEIGHT_CONTROL'!$A$7,'18_WEIGHT_CONTROL'!$B$7,'18_WEIGHT_CONTROL'!$B$8))) | Z11: =IF('91_MOTIF_CONF_SOURCE'!D11='18_WEIGHT_CONTROL'!$A$5,'18_WEIGHT_CONTROL'!$B$5,IF('91_MOTIF_CONF_SOURCE'!D11='18_WEIGHT_CONTROL'!$A$6,'18_WEIGHT_CONTROL'!$B$6,IF('91_MOTIF_CONF_SOURCE'!D11='18_WEIGHT_CONTROL'!$A$7,'18_WEIGHT_CONTROL'!$B$7,'18_WEIGHT_CONTROL'!$B$8))) | AA11: =IF('91_MOTIF_CONF_SOURCE'!E11='18_WEIGHT_CONTROL'!$A$5,'18_WEIGHT_CONTROL'!$B$5,IF('91_MOTIF_CONF_SOURCE'!E11='18_WEIGHT_CONTROL'!$A$6,'18_WEIGHT_CONTROL'!$B$6,IF('91_MOTIF_CONF_SOURCE'!E11='18_WEIGHT_CONTROL'!$A$7,'18_WEIGHT_CONTROL'!$B$7,'18_WEIGHT_CONTROL'!$B$8))) | AB11: =IF('91_MOTIF_CONF_SOURCE'!F11='18_WEIGHT_CONTROL'!$A$5,'18_WEIGHT_CONTROL'!$B$5,IF('91_MOTIF_CONF_SOURCE'!F11='18_WEIGHT_CONTROL'!$A$6,'18_WEIGHT_CONTROL'!$B$6,IF('91_MOTIF_CONF_SOURCE'!F11='18_WEIGHT_CONTROL'!$A$7,'18_WEIGHT_CONTROL'!$B$7,'18_WEIGHT_CONTROL'!$B$8))) | AC11: =IF('91_MOTIF_CONF_SOURCE'!G11='18_WEIGHT_CONTROL'!$A$5,'18_WEIGHT_CONTROL'!$B$5,IF('91_MOTIF_CONF_SOURCE'!G11='18_WEIGHT_CONTROL'!$A$6,'18_WEIGHT_CONTROL'!$B$6,IF('91_MOTIF_CONF_SOURCE'!G11='18_WEIGHT_CONTROL'!$A$7,'18_WEIGHT_CONTROL'!$B$7,'18_WEIGHT_CONTROL'!$B$8))) | AD11: =IF('91_MOTIF_CONF_SOURCE'!H11='18_WEIGHT_CONTROL'!$A$5,'18_WEIGHT_CONTROL'!$B$5,IF('91_MOTIF_CONF_SOURCE'!H11='18_WEIGHT_CONTROL'!$A$6,'18_WEIGHT_CONTROL'!$B$6,IF('91_MOTIF_CONF_SOURCE'!H11='18_WEIGHT_CONTROL'!$A$7,'18_WEIGHT_CONTROL'!$B$7,'18_WEIGHT_CONTROL'!$B$8))) | AE11: =IF('91_MOTIF_CONF_SOURCE'!I11='18_WEIGHT_CONTROL'!$A$5,'18_WEIGHT_CONTROL'!$B$5,IF('91_MOTIF_CONF_SOURCE'!I11='18_WEIGHT_CONTROL'!$A$6,'18_WEIGHT_CONTROL'!$B$6,IF('91_MOTIF_CONF_SOURCE'!I11='18_WEIGHT_CONTROL'!$A$7,'18_WEIGHT_CONTROL'!$B$7,'18_WEIGHT_CONTROL'!$B$8))) | AF11: =IF('91_MOTIF_CONF_SOURCE'!J11='18_WEIGHT_CONTROL'!$A$5,'18_WEIGHT_CONTROL'!$B$5,IF('91_MOTIF_CONF_SOURCE'!J11='18_WEIGHT_CONTROL'!$A$6,'18_WEIGHT_CONTROL'!$B$6,IF('91_MOTIF_CONF_SOURCE'!J11='18_WEIGHT_CONTROL'!$A$7,'18_WEIGHT_CONTROL'!$B$7,'18_WEIGHT_CONTROL'!$B$8))) | AG11: =IF('91_MOTIF_CONF_SOURCE'!K11='18_WEIGHT_CONTROL'!$A$5,'18_WEIGHT_CONTROL'!$B$5,IF('91_MOTIF_CONF_SOURCE'!K11='18_WEIGHT_CONTROL'!$A$6,'18_WEIGHT_CONTROL'!$B$6,IF('91_MOTIF_CONF_SOURCE'!K11='18_WEIGHT_CONTROL'!$A$7,'18_WEIGHT_CONTROL'!$B$7,'18_WEIGHT_CONTROL'!$B$8))) | ... AR11: =IF('91_MOTIF_CONF_SOURCE'!V11='18_WEIGHT_CONTROL'!$A$5,'18_WEIGHT_CONTROL'!$B$5,IF('91_MOTIF_CONF_SOURCE'!V11='18_WEIGHT_CONTROL'!$A$6,'18_WEIGHT_CONTROL'!$B$6,IF('91_MOTIF_CONF_SOURCE'!V11='18_WEIGHT_CONTROL'!$A$7,'18_WEIGHT_CONTROL'!$B$7,'18_WEIGHT_CONTROL'!$B$8)))
A12: 8 | B12: 金星人 | C12: Venusian | D12: =IF('90_CANON_CONF_SOURCE'!D12='18_WEIGHT_CONTROL'!$A$5,'18_WEIGHT_CONTROL'!$B$5,IF('90_CANON_CONF_SOURCE'!D12='18_WEIGHT_CONTROL'!$A$6,'18_WEIGHT_CONTROL'!$B$6,IF('90_CANON_CONF_SOURCE'!D12='18_WEIGHT_CONTROL'!$A$7,'18_WEIGHT_CONTROL'!$B$7,'18_WEIGHT_CONTROL'!$B$8))) | E12: =IF('90_CANON_CONF_SOURCE'!E12='18_WEIGHT_CONTROL'!$A$5,'18_WEIGHT_CONTROL'!$B$5,IF('90_CANON_CONF_SOURCE'!E12='18_WEIGHT_CONTROL'!$A$6,'18_WEIGHT_CONTROL'!$B$6,IF('90_CANON_CONF_SOURCE'!E12='18_WEIGHT_CONTROL'!$A$7,'18_WEIGHT_CONTROL'!$B$7,'18_WEIGHT_CONTROL'!$B$8))) | F12: =IF('90_CANON_CONF_SOURCE'!F12='18_WEIGHT_CONTROL'!$A$5,'18_WEIGHT_CONTROL'!$B$5,IF('90_CANON_CONF_SOURCE'!F12='18_WEIGHT_CONTROL'!$A$6,'18_WEIGHT_CONTROL'!$B$6,IF('90_CANON_CONF_SOURCE'!F12='18_WEIGHT_CONTROL'!$A$7,'18_WEIGHT_CONTROL'!$B$7,'18_WEIGHT_CONTROL'!$B$8))) | G12: =IF('90_CANON_CONF_SOURCE'!G12='18_WEIGHT_CONTROL'!$A$5,'18_WEIGHT_CONTROL'!$B$5,IF('90_CANON_CONF_SOURCE'!G12='18_WEIGHT_CONTROL'!$A$6,'18_WEIGHT_CONTROL'!$B$6,IF('90_CANON_CONF_SOURCE'!G12='18_WEIGHT_CONTROL'!$A$7,'18_WEIGHT_CONTROL'!$B$7,'18_WEIGHT_CONTROL'!$B$8))) | H12: =IF('90_CANON_CONF_SOURCE'!H12='18_WEIGHT_CONTROL'!$A$5,'18_WEIGHT_CONTROL'!$B$5,IF('90_CANON_CONF_SOURCE'!H12='18_WEIGHT_CONTROL'!$A$6,'18_WEIGHT_CONTROL'!$B$6,IF('90_CANON_CONF_SOURCE'!H12='18_WEIGHT_CONTROL'!$A$7,'18_WEIGHT_CONTROL'!$B$7,'18_WEIGHT_CONTROL'!$B$8))) | I12: =IF('90_CANON_CONF_SOURCE'!I12='18_WEIGHT_CONTROL'!$A$5,'18_WEIGHT_CONTROL'!$B$5,IF('90_CANON_CONF_SOURCE'!I12='18_WEIGHT_CONTROL'!$A$6,'18_WEIGHT_CONTROL'!$B$6,IF('90_CANON_CONF_SOURCE'!I12='18_WEIGHT_CONTROL'!$A$7,'18_WEIGHT_CONTROL'!$B$7,'18_WEIGHT_CONTROL'!$B$8))) | J12: =IF('90_CANON_CONF_SOURCE'!J12='18_WEIGHT_CONTROL'!$A$5,'18_WEIGHT_CONTROL'!$B$5,IF('90_CANON_CONF_SOURCE'!J12='18_WEIGHT_CONTROL'!$A$6,'18_WEIGHT_CONTROL'!$B$6,IF('90_CANON_CONF_SOURCE'!J12='18_WEIGHT_CONTROL'!$A$7,'18_WEIGHT_CONTROL'!$B$7,'18_WEIGHT_CONTROL'!$B$8))) | K12: =IF('90_CANON_CONF_SOURCE'!K12='18_WEIGHT_CONTROL'!$A$5,'18_WEIGHT_CONTROL'!$B$5,IF('90_CANON_CONF_SOURCE'!K12='18_WEIGHT_CONTROL'!$A$6,'18_WEIGHT_CONTROL'!$B$6,IF('90_CANON_CONF_SOURCE'!K12='18_WEIGHT_CONTROL'!$A$7,'18_WEIGHT_CONTROL'!$B$7,'18_WEIGHT_CONTROL'!$B$8))) | ... Y12: =IF('90_CANON_CONF_SOURCE'!Y12='18_WEIGHT_CONTROL'!$A$5,'18_WEIGHT_CONTROL'!$B$5,IF('90_CANON_CONF_SOURCE'!Y12='18_WEIGHT_CONTROL'!$A$6,'18_WEIGHT_CONTROL'!$B$6,IF('90_CANON_CONF_SOURCE'!Y12='18_WEIGHT_CONTROL'!$A$7,'18_WEIGHT_CONTROL'!$B$7,'18_WEIGHT_CONTROL'!$B$8))) | Z12: =IF('91_MOTIF_CONF_SOURCE'!D12='18_WEIGHT_CONTROL'!$A$5,'18_WEIGHT_CONTROL'!$B$5,IF('91_MOTIF_CONF_SOURCE'!D12='18_WEIGHT_CONTROL'!$A$6,'18_WEIGHT_CONTROL'!$B$6,IF('91_MOTIF_CONF_SOURCE'!D12='18_WEIGHT_CONTROL'!$A$7,'18_WEIGHT_CONTROL'!$B$7,'18_WEIGHT_CONTROL'!$B$8))) | AA12: =IF('91_MOTIF_CONF_SOURCE'!E12='18_WEIGHT_CONTROL'!$A$5,'18_WEIGHT_CONTROL'!$B$5,IF('91_MOTIF_CONF_SOURCE'!E12='18_WEIGHT_CONTROL'!$A$6,'18_WEIGHT_CONTROL'!$B$6,IF('91_MOTIF_CONF_SOURCE'!E12='18_WEIGHT_CONTROL'!$A$7,'18_WEIGHT_CONTROL'!$B$7,'18_WEIGHT_CONTROL'!$B$8))) | AB12: =IF('91_MOTIF_CONF_SOURCE'!F12='18_WEIGHT_CONTROL'!$A$5,'18_WEIGHT_CONTROL'!$B$5,IF('91_MOTIF_CONF_SOURCE'!F12='18_WEIGHT_CONTROL'!$A$6,'18_WEIGHT_CONTROL'!$B$6,IF('91_MOTIF_CONF_SOURCE'!F12='18_WEIGHT_CONTROL'!$A$7,'18_WEIGHT_CONTROL'!$B$7,'18_WEIGHT_CONTROL'!$B$8))) | AC12: =IF('91_MOTIF_CONF_SOURCE'!G12='18_WEIGHT_CONTROL'!$A$5,'18_WEIGHT_CONTROL'!$B$5,IF('91_MOTIF_CONF_SOURCE'!G12='18_WEIGHT_CONTROL'!$A$6,'18_WEIGHT_CONTROL'!$B$6,IF('91_MOTIF_CONF_SOURCE'!G12='18_WEIGHT_CONTROL'!$A$7,'18_WEIGHT_CONTROL'!$B$7,'18_WEIGHT_CONTROL'!$B$8))) | AD12: =IF('91_MOTIF_CONF_SOURCE'!H12='18_WEIGHT_CONTROL'!$A$5,'18_WEIGHT_CONTROL'!$B$5,IF('91_MOTIF_CONF_SOURCE'!H12='18_WEIGHT_CONTROL'!$A$6,'18_WEIGHT_CONTROL'!$B$6,IF('91_MOTIF_CONF_SOURCE'!H12='18_WEIGHT_CONTROL'!$A$7,'18_WEIGHT_CONTROL'!$B$7,'18_WEIGHT_CONTROL'!$B$8))) | AE12: =IF('91_MOTIF_CONF_SOURCE'!I12='18_WEIGHT_CONTROL'!$A$5,'18_WEIGHT_CONTROL'!$B$5,IF('91_MOTIF_CONF_SOURCE'!I12='18_WEIGHT_CONTROL'!$A$6,'18_WEIGHT_CONTROL'!$B$6,IF('91_MOTIF_CONF_SOURCE'!I12='18_WEIGHT_CONTROL'!$A$7,'18_WEIGHT_CONTROL'!$B$7,'18_WEIGHT_CONTROL'!$B$8))) | AF12: =IF('91_MOTIF_CONF_SOURCE'!J12='18_WEIGHT_CONTROL'!$A$5,'18_WEIGHT_CONTROL'!$B$5,IF('91_MOTIF_CONF_SOURCE'!J12='18_WEIGHT_CONTROL'!$A$6,'18_WEIGHT_CONTROL'!$B$6,IF('91_MOTIF_CONF_SOURCE'!J12='18_WEIGHT_CONTROL'!$A$7,'18_WEIGHT_CONTROL'!$B$7,'18_WEIGHT_CONTROL'!$B$8))) | AG12: =IF('91_MOTIF_CONF_SOURCE'!K12='18_WEIGHT_CONTROL'!$A$5,'18_WEIGHT_CONTROL'!$B$5,IF('91_MOTIF_CONF_SOURCE'!K12='18_WEIGHT_CONTROL'!$A$6,'18_WEIGHT_CONTROL'!$B$6,IF('91_MOTIF_CONF_SOURCE'!K12='18_WEIGHT_CONTROL'!$A$7,'18_WEIGHT_CONTROL'!$B$7,'18_WEIGHT_CONTROL'!$B$8))) | ... AR12: =IF('91_MOTIF_CONF_SOURCE'!V12='18_WEIGHT_CONTROL'!$A$5,'18_WEIGHT_CONTROL'!$B$5,IF('91_MOTIF_CONF_SOURCE'!V12='18_WEIGHT_CONTROL'!$A$6,'18_WEIGHT_CONTROL'!$B$6,IF('91_MOTIF_CONF_SOURCE'!V12='18_WEIGHT_CONTROL'!$A$7,'18_WEIGHT_CONTROL'!$B$7,'18_WEIGHT_CONTROL'!$B$8)))
A13: 9 | B13: 哈達爾星人 | C13: Hadarian | D13: =IF('90_CANON_CONF_SOURCE'!D13='18_WEIGHT_CONTROL'!$A$5,'18_WEIGHT_CONTROL'!$B$5,IF('90_CANON_CONF_SOURCE'!D13='18_WEIGHT_CONTROL'!$A$6,'18_WEIGHT_CONTROL'!$B$6,IF('90_CANON_CONF_SOURCE'!D13='18_WEIGHT_CONTROL'!$A$7,'18_WEIGHT_CONTROL'!$B$7,'18_WEIGHT_CONTROL'!$B$8))) | E13: =IF('90_CANON_CONF_SOURCE'!E13='18_WEIGHT_CONTROL'!$A$5,'18_WEIGHT_CONTROL'!$B$5,IF('90_CANON_CONF_SOURCE'!E13='18_WEIGHT_CONTROL'!$A$6,'18_WEIGHT_CONTROL'!$B$6,IF('90_CANON_CONF_SOURCE'!E13='18_WEIGHT_CONTROL'!$A$7,'18_WEIGHT_CONTROL'!$B$7,'18_WEIGHT_CONTROL'!$B$8))) | F13: =IF('90_CANON_CONF_SOURCE'!F13='18_WEIGHT_CONTROL'!$A$5,'18_WEIGHT_CONTROL'!$B$5,IF('90_CANON_CONF_SOURCE'!F13='18_WEIGHT_CONTROL'!$A$6,'18_WEIGHT_CONTROL'!$B$6,IF('90_CANON_CONF_SOURCE'!F13='18_WEIGHT_CONTROL'!$A$7,'18_WEIGHT_CONTROL'!$B$7,'18_WEIGHT_CONTROL'!$B$8))) | G13: =IF('90_CANON_CONF_SOURCE'!G13='18_WEIGHT_CONTROL'!$A$5,'18_WEIGHT_CONTROL'!$B$5,IF('90_CANON_CONF_SOURCE'!G13='18_WEIGHT_CONTROL'!$A$6,'18_WEIGHT_CONTROL'!$B$6,IF('90_CANON_CONF_SOURCE'!G13='18_WEIGHT_CONTROL'!$A$7,'18_WEIGHT_CONTROL'!$B$7,'18_WEIGHT_CONTROL'!$B$8))) | H13: =IF('90_CANON_CONF_SOURCE'!H13='18_WEIGHT_CONTROL'!$A$5,'18_WEIGHT_CONTROL'!$B$5,IF('90_CANON_CONF_SOURCE'!H13='18_WEIGHT_CONTROL'!$A$6,'18_WEIGHT_CONTROL'!$B$6,IF('90_CANON_CONF_SOURCE'!H13='18_WEIGHT_CONTROL'!$A$7,'18_WEIGHT_CONTROL'!$B$7,'18_WEIGHT_CONTROL'!$B$8))) | I13: =IF('90_CANON_CONF_SOURCE'!I13='18_WEIGHT_CONTROL'!$A$5,'18_WEIGHT_CONTROL'!$B$5,IF('90_CANON_CONF_SOURCE'!I13='18_WEIGHT_CONTROL'!$A$6,'18_WEIGHT_CONTROL'!$B$6,IF('90_CANON_CONF_SOURCE'!I13='18_WEIGHT_CONTROL'!$A$7,'18_WEIGHT_CONTROL'!$B$7,'18_WEIGHT_CONTROL'!$B$8))) | J13: =IF('90_CANON_CONF_SOURCE'!J13='18_WEIGHT_CONTROL'!$A$5,'18_WEIGHT_CONTROL'!$B$5,IF('90_CANON_CONF_SOURCE'!J13='18_WEIGHT_CONTROL'!$A$6,'18_WEIGHT_CONTROL'!$B$6,IF('90_CANON_CONF_SOURCE'!J13='18_WEIGHT_CONTROL'!$A$7,'18_WEIGHT_CONTROL'!$B$7,'18_WEIGHT_CONTROL'!$B$8))) | K13: =IF('90_CANON_CONF_SOURCE'!K13='18_WEIGHT_CONTROL'!$A$5,'18_WEIGHT_CONTROL'!$B$5,IF('90_CANON_CONF_SOURCE'!K13='18_WEIGHT_CONTROL'!$A$6,'18_WEIGHT_CONTROL'!$B$6,IF('90_CANON_CONF_SOURCE'!K13='18_WEIGHT_CONTROL'!$A$7,'18_WEIGHT_CONTROL'!$B$7,'18_WEIGHT_CONTROL'!$B$8))) | ... Y13: =IF('90_CANON_CONF_SOURCE'!Y13='18_WEIGHT_CONTROL'!$A$5,'18_WEIGHT_CONTROL'!$B$5,IF('90_CANON_CONF_SOURCE'!Y13='18_WEIGHT_CONTROL'!$A$6,'18_WEIGHT_CONTROL'!$B$6,IF('90_CANON_CONF_SOURCE'!Y13='18_WEIGHT_CONTROL'!$A$7,'18_WEIGHT_CONTROL'!$B$7,'18_WEIGHT_CONTROL'!$B$8))) | Z13: =IF('91_MOTIF_CONF_SOURCE'!D13='18_WEIGHT_CONTROL'!$A$5,'18_WEIGHT_CONTROL'!$B$5,IF('91_MOTIF_CONF_SOURCE'!D13='18_WEIGHT_CONTROL'!$A$6,'18_WEIGHT_CONTROL'!$B$6,IF('91_MOTIF_CONF_SOURCE'!D13='18_WEIGHT_CONTROL'!$A$7,'18_WEIGHT_CONTROL'!$B$7,'18_WEIGHT_CONTROL'!$B$8))) | AA13: =IF('91_MOTIF_CONF_SOURCE'!E13='18_WEIGHT_CONTROL'!$A$5,'18_WEIGHT_CONTROL'!$B$5,IF('91_MOTIF_CONF_SOURCE'!E13='18_WEIGHT_CONTROL'!$A$6,'18_WEIGHT_CONTROL'!$B$6,IF('91_MOTIF_CONF_SOURCE'!E13='18_WEIGHT_CONTROL'!$A$7,'18_WEIGHT_CONTROL'!$B$7,'18_WEIGHT_CONTROL'!$B$8))) | AB13: =IF('91_MOTIF_CONF_SOURCE'!F13='18_WEIGHT_CONTROL'!$A$5,'18_WEIGHT_CONTROL'!$B$5,IF('91_MOTIF_CONF_SOURCE'!F13='18_WEIGHT_CONTROL'!$A$6,'18_WEIGHT_CONTROL'!$B$6,IF('91_MOTIF_CONF_SOURCE'!F13='18_WEIGHT_CONTROL'!$A$7,'18_WEIGHT_CONTROL'!$B$7,'18_WEIGHT_CONTROL'!$B$8))) | AC13: =IF('91_MOTIF_CONF_SOURCE'!G13='18_WEIGHT_CONTROL'!$A$5,'18_WEIGHT_CONTROL'!$B$5,IF('91_MOTIF_CONF_SOURCE'!G13='18_WEIGHT_CONTROL'!$A$6,'18_WEIGHT_CONTROL'!$B$6,IF('91_MOTIF_CONF_SOURCE'!G13='18_WEIGHT_CONTROL'!$A$7,'18_WEIGHT_CONTROL'!$B$7,'18_WEIGHT_CONTROL'!$B$8))) | AD13: =IF('91_MOTIF_CONF_SOURCE'!H13='18_WEIGHT_CONTROL'!$A$5,'18_WEIGHT_CONTROL'!$B$5,IF('91_MOTIF_CONF_SOURCE'!H13='18_WEIGHT_CONTROL'!$A$6,'18_WEIGHT_CONTROL'!$B$6,IF('91_MOTIF_CONF_SOURCE'!H13='18_WEIGHT_CONTROL'!$A$7,'18_WEIGHT_CONTROL'!$B$7,'18_WEIGHT_CONTROL'!$B$8))) | AE13: =IF('91_MOTIF_CONF_SOURCE'!I13='18_WEIGHT_CONTROL'!$A$5,'18_WEIGHT_CONTROL'!$B$5,IF('91_MOTIF_CONF_SOURCE'!I13='18_WEIGHT_CONTROL'!$A$6,'18_WEIGHT_CONTROL'!$B$6,IF('91_MOTIF_CONF_SOURCE'!I13='18_WEIGHT_CONTROL'!$A$7,'18_WEIGHT_CONTROL'!$B$7,'18_WEIGHT_CONTROL'!$B$8))) | AF13: =IF('91_MOTIF_CONF_SOURCE'!J13='18_WEIGHT_CONTROL'!$A$5,'18_WEIGHT_CONTROL'!$B$5,IF('91_MOTIF_CONF_SOURCE'!J13='18_WEIGHT_CONTROL'!$A$6,'18_WEIGHT_CONTROL'!$B$6,IF('91_MOTIF_CONF_SOURCE'!J13='18_WEIGHT_CONTROL'!$A$7,'18_WEIGHT_CONTROL'!$B$7,'18_WEIGHT_CONTROL'!$B$8))) | AG13: =IF('91_MOTIF_CONF_SOURCE'!K13='18_WEIGHT_CONTROL'!$A$5,'18_WEIGHT_CONTROL'!$B$5,IF('91_MOTIF_CONF_SOURCE'!K13='18_WEIGHT_CONTROL'!$A$6,'18_WEIGHT_CONTROL'!$B$6,IF('91_MOTIF_CONF_SOURCE'!K13='18_WEIGHT_CONTROL'!$A$7,'18_WEIGHT_CONTROL'!$B$7,'18_WEIGHT_CONTROL'!$B$8))) | ... AR13: =IF('91_MOTIF_CONF_SOURCE'!V13='18_WEIGHT_CONTROL'!$A$5,'18_WEIGHT_CONTROL'!$B$5,IF('91_MOTIF_CONF_SOURCE'!V13='18_WEIGHT_CONTROL'!$A$6,'18_WEIGHT_CONTROL'!$B$6,IF('91_MOTIF_CONF_SOURCE'!V13='18_WEIGHT_CONTROL'!$A$7,'18_WEIGHT_CONTROL'!$B$7,'18_WEIGHT_CONTROL'!$B$8)))
A14: 10 | B14: 北極星人 | C14: Polarian | D14: =IF('90_CANON_CONF_SOURCE'!D14='18_WEIGHT_CONTROL'!$A$5,'18_WEIGHT_CONTROL'!$B$5,IF('90_CANON_CONF_SOURCE'!D14='18_WEIGHT_CONTROL'!$A$6,'18_WEIGHT_CONTROL'!$B$6,IF('90_CANON_CONF_SOURCE'!D14='18_WEIGHT_CONTROL'!$A$7,'18_WEIGHT_CONTROL'!$B$7,'18_WEIGHT_CONTROL'!$B$8))) | E14: =IF('90_CANON_CONF_SOURCE'!E14='18_WEIGHT_CONTROL'!$A$5,'18_WEIGHT_CONTROL'!$B$5,IF('90_CANON_CONF_SOURCE'!E14='18_WEIGHT_CONTROL'!$A$6,'18_WEIGHT_CONTROL'!$B$6,IF('90_CANON_CONF_SOURCE'!E14='18_WEIGHT_CONTROL'!$A$7,'18_WEIGHT_CONTROL'!$B$7,'18_WEIGHT_CONTROL'!$B$8))) | F14: =IF('90_CANON_CONF_SOURCE'!F14='18_WEIGHT_CONTROL'!$A$5,'18_WEIGHT_CONTROL'!$B$5,IF('90_CANON_CONF_SOURCE'!F14='18_WEIGHT_CONTROL'!$A$6,'18_WEIGHT_CONTROL'!$B$6,IF('90_CANON_CONF_SOURCE'!F14='18_WEIGHT_CONTROL'!$A$7,'18_WEIGHT_CONTROL'!$B$7,'18_WEIGHT_CONTROL'!$B$8))) | G14: =IF('90_CANON_CONF_SOURCE'!G14='18_WEIGHT_CONTROL'!$A$5,'18_WEIGHT_CONTROL'!$B$5,IF('90_CANON_CONF_SOURCE'!G14='18_WEIGHT_CONTROL'!$A$6,'18_WEIGHT_CONTROL'!$B$6,IF('90_CANON_CONF_SOURCE'!G14='18_WEIGHT_CONTROL'!$A$7,'18_WEIGHT_CONTROL'!$B$7,'18_WEIGHT_CONTROL'!$B$8))) | H14: =IF('90_CANON_CONF_SOURCE'!H14='18_WEIGHT_CONTROL'!$A$5,'18_WEIGHT_CONTROL'!$B$5,IF('90_CANON_CONF_SOURCE'!H14='18_WEIGHT_CONTROL'!$A$6,'18_WEIGHT_CONTROL'!$B$6,IF('90_CANON_CONF_SOURCE'!H14='18_WEIGHT_CONTROL'!$A$7,'18_WEIGHT_CONTROL'!$B$7,'18_WEIGHT_CONTROL'!$B$8))) | I14: =IF('90_CANON_CONF_SOURCE'!I14='18_WEIGHT_CONTROL'!$A$5,'18_WEIGHT_CONTROL'!$B$5,IF('90_CANON_CONF_SOURCE'!I14='18_WEIGHT_CONTROL'!$A$6,'18_WEIGHT_CONTROL'!$B$6,IF('90_CANON_CONF_SOURCE'!I14='18_WEIGHT_CONTROL'!$A$7,'18_WEIGHT_CONTROL'!$B$7,'18_WEIGHT_CONTROL'!$B$8))) | J14: =IF('90_CANON_CONF_SOURCE'!J14='18_WEIGHT_CONTROL'!$A$5,'18_WEIGHT_CONTROL'!$B$5,IF('90_CANON_CONF_SOURCE'!J14='18_WEIGHT_CONTROL'!$A$6,'18_WEIGHT_CONTROL'!$B$6,IF('90_CANON_CONF_SOURCE'!J14='18_WEIGHT_CONTROL'!$A$7,'18_WEIGHT_CONTROL'!$B$7,'18_WEIGHT_CONTROL'!$B$8))) | K14: =IF('90_CANON_CONF_SOURCE'!K14='18_WEIGHT_CONTROL'!$A$5,'18_WEIGHT_CONTROL'!$B$5,IF('90_CANON_CONF_SOURCE'!K14='18_WEIGHT_CONTROL'!$A$6,'18_WEIGHT_CONTROL'!$B$6,IF('90_CANON_CONF_SOURCE'!K14='18_WEIGHT_CONTROL'!$A$7,'18_WEIGHT_CONTROL'!$B$7,'18_WEIGHT_CONTROL'!$B$8))) | ... Y14: =IF('90_CANON_CONF_SOURCE'!Y14='18_WEIGHT_CONTROL'!$A$5,'18_WEIGHT_CONTROL'!$B$5,IF('90_CANON_CONF_SOURCE'!Y14='18_WEIGHT_CONTROL'!$A$6,'18_WEIGHT_CONTROL'!$B$6,IF('90_CANON_CONF_SOURCE'!Y14='18_WEIGHT_CONTROL'!$A$7,'18_WEIGHT_CONTROL'!$B$7,'18_WEIGHT_CONTROL'!$B$8))) | Z14: =IF('91_MOTIF_CONF_SOURCE'!D14='18_WEIGHT_CONTROL'!$A$5,'18_WEIGHT_CONTROL'!$B$5,IF('91_MOTIF_CONF_SOURCE'!D14='18_WEIGHT_CONTROL'!$A$6,'18_WEIGHT_CONTROL'!$B$6,IF('91_MOTIF_CONF_SOURCE'!D14='18_WEIGHT_CONTROL'!$A$7,'18_WEIGHT_CONTROL'!$B$7,'18_WEIGHT_CONTROL'!$B$8))) | AA14: =IF('91_MOTIF_CONF_SOURCE'!E14='18_WEIGHT_CONTROL'!$A$5,'18_WEIGHT_CONTROL'!$B$5,IF('91_MOTIF_CONF_SOURCE'!E14='18_WEIGHT_CONTROL'!$A$6,'18_WEIGHT_CONTROL'!$B$6,IF('91_MOTIF_CONF_SOURCE'!E14='18_WEIGHT_CONTROL'!$A$7,'18_WEIGHT_CONTROL'!$B$7,'18_WEIGHT_CONTROL'!$B$8))) | AB14: =IF('91_MOTIF_CONF_SOURCE'!F14='18_WEIGHT_CONTROL'!$A$5,'18_WEIGHT_CONTROL'!$B$5,IF('91_MOTIF_CONF_SOURCE'!F14='18_WEIGHT_CONTROL'!$A$6,'18_WEIGHT_CONTROL'!$B$6,IF('91_MOTIF_CONF_SOURCE'!F14='18_WEIGHT_CONTROL'!$A$7,'18_WEIGHT_CONTROL'!$B$7,'18_WEIGHT_CONTROL'!$B$8))) | AC14: =IF('91_MOTIF_CONF_SOURCE'!G14='18_WEIGHT_CONTROL'!$A$5,'18_WEIGHT_CONTROL'!$B$5,IF('91_MOTIF_CONF_SOURCE'!G14='18_WEIGHT_CONTROL'!$A$6,'18_WEIGHT_CONTROL'!$B$6,IF('91_MOTIF_CONF_SOURCE'!G14='18_WEIGHT_CONTROL'!$A$7,'18_WEIGHT_CONTROL'!$B$7,'18_WEIGHT_CONTROL'!$B$8))) | AD14: =IF('91_MOTIF_CONF_SOURCE'!H14='18_WEIGHT_CONTROL'!$A$5,'18_WEIGHT_CONTROL'!$B$5,IF('91_MOTIF_CONF_SOURCE'!H14='18_WEIGHT_CONTROL'!$A$6,'18_WEIGHT_CONTROL'!$B$6,IF('91_MOTIF_CONF_SOURCE'!H14='18_WEIGHT_CONTROL'!$A$7,'18_WEIGHT_CONTROL'!$B$7,'18_WEIGHT_CONTROL'!$B$8))) | AE14: =IF('91_MOTIF_CONF_SOURCE'!I14='18_WEIGHT_CONTROL'!$A$5,'18_WEIGHT_CONTROL'!$B$5,IF('91_MOTIF_CONF_SOURCE'!I14='18_WEIGHT_CONTROL'!$A$6,'18_WEIGHT_CONTROL'!$B$6,IF('91_MOTIF_CONF_SOURCE'!I14='18_WEIGHT_CONTROL'!$A$7,'18_WEIGHT_CONTROL'!$B$7,'18_WEIGHT_CONTROL'!$B$8))) | AF14: =IF('91_MOTIF_CONF_SOURCE'!J14='18_WEIGHT_CONTROL'!$A$5,'18_WEIGHT_CONTROL'!$B$5,IF('91_MOTIF_CONF_SOURCE'!J14='18_WEIGHT_CONTROL'!$A$6,'18_WEIGHT_CONTROL'!$B$6,IF('91_MOTIF_CONF_SOURCE'!J14='18_WEIGHT_CONTROL'!$A$7,'18_WEIGHT_CONTROL'!$B$7,'18_WEIGHT_CONTROL'!$B$8))) | AG14: =IF('91_MOTIF_CONF_SOURCE'!K14='18_WEIGHT_CONTROL'!$A$5,'18_WEIGHT_CONTROL'!$B$5,IF('91_MOTIF_CONF_SOURCE'!K14='18_WEIGHT_CONTROL'!$A$6,'18_WEIGHT_CONTROL'!$B$6,IF('91_MOTIF_CONF_SOURCE'!K14='18_WEIGHT_CONTROL'!$A$7,'18_WEIGHT_CONTROL'!$B$7,'18_WEIGHT_CONTROL'!$B$8))) | ... AR14: =IF('91_MOTIF_CONF_SOURCE'!V14='18_WEIGHT_CONTROL'!$A$5,'18_WEIGHT_CONTROL'!$B$5,IF('91_MOTIF_CONF_SOURCE'!V14='18_WEIGHT_CONTROL'!$A$6,'18_WEIGHT_CONTROL'!$B$6,IF('91_MOTIF_CONF_SOURCE'!V14='18_WEIGHT_CONTROL'!$A$7,'18_WEIGHT_CONTROL'!$B$7,'18_WEIGHT_CONTROL'!$B$8)))
A15: 11 | B15: 半人馬座α星人 | C15: Alpha Centaurian | D15: =IF('90_CANON_CONF_SOURCE'!D15='18_WEIGHT_CONTROL'!$A$5,'18_WEIGHT_CONTROL'!$B$5,IF('90_CANON_CONF_SOURCE'!D15='18_WEIGHT_CONTROL'!$A$6,'18_WEIGHT_CONTROL'!$B$6,IF('90_CANON_CONF_SOURCE'!D15='18_WEIGHT_CONTROL'!$A$7,'18_WEIGHT_CONTROL'!$B$7,'18_WEIGHT_CONTROL'!$B$8))) | E15: =IF('90_CANON_CONF_SOURCE'!E15='18_WEIGHT_CONTROL'!$A$5,'18_WEIGHT_CONTROL'!$B$5,IF('90_CANON_CONF_SOURCE'!E15='18_WEIGHT_CONTROL'!$A$6,'18_WEIGHT_CONTROL'!$B$6,IF('90_CANON_CONF_SOURCE'!E15='18_WEIGHT_CONTROL'!$A$7,'18_WEIGHT_CONTROL'!$B$7,'18_WEIGHT_CONTROL'!$B$8))) | F15: =IF('90_CANON_CONF_SOURCE'!F15='18_WEIGHT_CONTROL'!$A$5,'18_WEIGHT_CONTROL'!$B$5,IF('90_CANON_CONF_SOURCE'!F15='18_WEIGHT_CONTROL'!$A$6,'18_WEIGHT_CONTROL'!$B$6,IF('90_CANON_CONF_SOURCE'!F15='18_WEIGHT_CONTROL'!$A$7,'18_WEIGHT_CONTROL'!$B$7,'18_WEIGHT_CONTROL'!$B$8))) | G15: =IF('90_CANON_CONF_SOURCE'!G15='18_WEIGHT_CONTROL'!$A$5,'18_WEIGHT_CONTROL'!$B$5,IF('90_CANON_CONF_SOURCE'!G15='18_WEIGHT_CONTROL'!$A$6,'18_WEIGHT_CONTROL'!$B$6,IF('90_CANON_CONF_SOURCE'!G15='18_WEIGHT_CONTROL'!$A$7,'18_WEIGHT_CONTROL'!$B$7,'18_WEIGHT_CONTROL'!$B$8))) | H15: =IF('90_CANON_CONF_SOURCE'!H15='18_WEIGHT_CONTROL'!$A$5,'18_WEIGHT_CONTROL'!$B$5,IF('90_CANON_CONF_SOURCE'!H15='18_WEIGHT_CONTROL'!$A$6,'18_WEIGHT_CONTROL'!$B$6,IF('90_CANON_CONF_SOURCE'!H15='18_WEIGHT_CONTROL'!$A$7,'18_WEIGHT_CONTROL'!$B$7,'18_WEIGHT_CONTROL'!$B$8))) | I15: =IF('90_CANON_CONF_SOURCE'!I15='18_WEIGHT_CONTROL'!$A$5,'18_WEIGHT_CONTROL'!$B$5,IF('90_CANON_CONF_SOURCE'!I15='18_WEIGHT_CONTROL'!$A$6,'18_WEIGHT_CONTROL'!$B$6,IF('90_CANON_CONF_SOURCE'!I15='18_WEIGHT_CONTROL'!$A$7,'18_WEIGHT_CONTROL'!$B$7,'18_WEIGHT_CONTROL'!$B$8))) | J15: =IF('90_CANON_CONF_SOURCE'!J15='18_WEIGHT_CONTROL'!$A$5,'18_WEIGHT_CONTROL'!$B$5,IF('90_CANON_CONF_SOURCE'!J15='18_WEIGHT_CONTROL'!$A$6,'18_WEIGHT_CONTROL'!$B$6,IF('90_CANON_CONF_SOURCE'!J15='18_WEIGHT_CONTROL'!$A$7,'18_WEIGHT_CONTROL'!$B$7,'18_WEIGHT_CONTROL'!$B$8))) | K15: =IF('90_CANON_CONF_SOURCE'!K15='18_WEIGHT_CONTROL'!$A$5,'18_WEIGHT_CONTROL'!$B$5,IF('90_CANON_CONF_SOURCE'!K15='18_WEIGHT_CONTROL'!$A$6,'18_WEIGHT_CONTROL'!$B$6,IF('90_CANON_CONF_SOURCE'!K15='18_WEIGHT_CONTROL'!$A$7,'18_WEIGHT_CONTROL'!$B$7,'18_WEIGHT_CONTROL'!$B$8))) | ... Y15: =IF('90_CANON_CONF_SOURCE'!Y15='18_WEIGHT_CONTROL'!$A$5,'18_WEIGHT_CONTROL'!$B$5,IF('90_CANON_CONF_SOURCE'!Y15='18_WEIGHT_CONTROL'!$A$6,'18_WEIGHT_CONTROL'!$B$6,IF('90_CANON_CONF_SOURCE'!Y15='18_WEIGHT_CONTROL'!$A$7,'18_WEIGHT_CONTROL'!$B$7,'18_WEIGHT_CONTROL'!$B$8))) | Z15: =IF('91_MOTIF_CONF_SOURCE'!D15='18_WEIGHT_CONTROL'!$A$5,'18_WEIGHT_CONTROL'!$B$5,IF('91_MOTIF_CONF_SOURCE'!D15='18_WEIGHT_CONTROL'!$A$6,'18_WEIGHT_CONTROL'!$B$6,IF('91_MOTIF_CONF_SOURCE'!D15='18_WEIGHT_CONTROL'!$A$7,'18_WEIGHT_CONTROL'!$B$7,'18_WEIGHT_CONTROL'!$B$8))) | AA15: =IF('91_MOTIF_CONF_SOURCE'!E15='18_WEIGHT_CONTROL'!$A$5,'18_WEIGHT_CONTROL'!$B$5,IF('91_MOTIF_CONF_SOURCE'!E15='18_WEIGHT_CONTROL'!$A$6,'18_WEIGHT_CONTROL'!$B$6,IF('91_MOTIF_CONF_SOURCE'!E15='18_WEIGHT_CONTROL'!$A$7,'18_WEIGHT_CONTROL'!$B$7,'18_WEIGHT_CONTROL'!$B$8))) | AB15: =IF('91_MOTIF_CONF_SOURCE'!F15='18_WEIGHT_CONTROL'!$A$5,'18_WEIGHT_CONTROL'!$B$5,IF('91_MOTIF_CONF_SOURCE'!F15='18_WEIGHT_CONTROL'!$A$6,'18_WEIGHT_CONTROL'!$B$6,IF('91_MOTIF_CONF_SOURCE'!F15='18_WEIGHT_CONTROL'!$A$7,'18_WEIGHT_CONTROL'!$B$7,'18_WEIGHT_CONTROL'!$B$8))) | AC15: =IF('91_MOTIF_CONF_SOURCE'!G15='18_WEIGHT_CONTROL'!$A$5,'18_WEIGHT_CONTROL'!$B$5,IF('91_MOTIF_CONF_SOURCE'!G15='18_WEIGHT_CONTROL'!$A$6,'18_WEIGHT_CONTROL'!$B$6,IF('91_MOTIF_CONF_SOURCE'!G15='18_WEIGHT_CONTROL'!$A$7,'18_WEIGHT_CONTROL'!$B$7,'18_WEIGHT_CONTROL'!$B$8))) | AD15: =IF('91_MOTIF_CONF_SOURCE'!H15='18_WEIGHT_CONTROL'!$A$5,'18_WEIGHT_CONTROL'!$B$5,IF('91_MOTIF_CONF_SOURCE'!H15='18_WEIGHT_CONTROL'!$A$6,'18_WEIGHT_CONTROL'!$B$6,IF('91_MOTIF_CONF_SOURCE'!H15='18_WEIGHT_CONTROL'!$A$7,'18_WEIGHT_CONTROL'!$B$7,'18_WEIGHT_CONTROL'!$B$8))) | AE15: =IF('91_MOTIF_CONF_SOURCE'!I15='18_WEIGHT_CONTROL'!$A$5,'18_WEIGHT_CONTROL'!$B$5,IF('91_MOTIF_CONF_SOURCE'!I15='18_WEIGHT_CONTROL'!$A$6,'18_WEIGHT_CONTROL'!$B$6,IF('91_MOTIF_CONF_SOURCE'!I15='18_WEIGHT_CONTROL'!$A$7,'18_WEIGHT_CONTROL'!$B$7,'18_WEIGHT_CONTROL'!$B$8))) | AF15: =IF('91_MOTIF_CONF_SOURCE'!J15='18_WEIGHT_CONTROL'!$A$5,'18_WEIGHT_CONTROL'!$B$5,IF('91_MOTIF_CONF_SOURCE'!J15='18_WEIGHT_CONTROL'!$A$6,'18_WEIGHT_CONTROL'!$B$6,IF('91_MOTIF_CONF_SOURCE'!J15='18_WEIGHT_CONTROL'!$A$7,'18_WEIGHT_CONTROL'!$B$7,'18_WEIGHT_CONTROL'!$B$8))) | AG15: =IF('91_MOTIF_CONF_SOURCE'!K15='18_WEIGHT_CONTROL'!$A$5,'18_WEIGHT_CONTROL'!$B$5,IF('91_MOTIF_CONF_SOURCE'!K15='18_WEIGHT_CONTROL'!$A$6,'18_WEIGHT_CONTROL'!$B$6,IF('91_MOTIF_CONF_SOURCE'!K15='18_WEIGHT_CONTROL'!$A$7,'18_WEIGHT_CONTROL'!$B$7,'18_WEIGHT_CONTROL'!$B$8))) | ... AR15: =IF('91_MOTIF_CONF_SOURCE'!V15='18_WEIGHT_CONTROL'!$A$5,'18_WEIGHT_CONTROL'!$B$5,IF('91_MOTIF_CONF_SOURCE'!V15='18_WEIGHT_CONTROL'!$A$6,'18_WEIGHT_CONTROL'!$B$6,IF('91_MOTIF_CONF_SOURCE'!V15='18_WEIGHT_CONTROL'!$A$7,'18_WEIGHT_CONTROL'!$B$7,'18_WEIGHT_CONTROL'!$B$8)))
A16: 12 | B16: 織女星人 | C16: Vegan | D16: =IF('90_CANON_CONF_SOURCE'!D16='18_WEIGHT_CONTROL'!$A$5,'18_WEIGHT_CONTROL'!$B$5,IF('90_CANON_CONF_SOURCE'!D16='18_WEIGHT_CONTROL'!$A$6,'18_WEIGHT_CONTROL'!$B$6,IF('90_CANON_CONF_SOURCE'!D16='18_WEIGHT_CONTROL'!$A$7,'18_WEIGHT_CONTROL'!$B$7,'18_WEIGHT_CONTROL'!$B$8))) | E16: =IF('90_CANON_CONF_SOURCE'!E16='18_WEIGHT_CONTROL'!$A$5,'18_WEIGHT_CONTROL'!$B$5,IF('90_CANON_CONF_SOURCE'!E16='18_WEIGHT_CONTROL'!$A$6,'18_WEIGHT_CONTROL'!$B$6,IF('90_CANON_CONF_SOURCE'!E16='18_WEIGHT_CONTROL'!$A$7,'18_WEIGHT_CONTROL'!$B$7,'18_WEIGHT_CONTROL'!$B$8))) | F16: =IF('90_CANON_CONF_SOURCE'!F16='18_WEIGHT_CONTROL'!$A$5,'18_WEIGHT_CONTROL'!$B$5,IF('90_CANON_CONF_SOURCE'!F16='18_WEIGHT_CONTROL'!$A$6,'18_WEIGHT_CONTROL'!$B$6,IF('90_CANON_CONF_SOURCE'!F16='18_WEIGHT_CONTROL'!$A$7,'18_WEIGHT_CONTROL'!$B$7,'18_WEIGHT_CONTROL'!$B$8))) | G16: =IF('90_CANON_CONF_SOURCE'!G16='18_WEIGHT_CONTROL'!$A$5,'18_WEIGHT_CONTROL'!$B$5,IF('90_CANON_CONF_SOURCE'!G16='18_WEIGHT_CONTROL'!$A$6,'18_WEIGHT_CONTROL'!$B$6,IF('90_CANON_CONF_SOURCE'!G16='18_WEIGHT_CONTROL'!$A$7,'18_WEIGHT_CONTROL'!$B$7,'18_WEIGHT_CONTROL'!$B$8))) | H16: =IF('90_CANON_CONF_SOURCE'!H16='18_WEIGHT_CONTROL'!$A$5,'18_WEIGHT_CONTROL'!$B$5,IF('90_CANON_CONF_SOURCE'!H16='18_WEIGHT_CONTROL'!$A$6,'18_WEIGHT_CONTROL'!$B$6,IF('90_CANON_CONF_SOURCE'!H16='18_WEIGHT_CONTROL'!$A$7,'18_WEIGHT_CONTROL'!$B$7,'18_WEIGHT_CONTROL'!$B$8))) | I16: =IF('90_CANON_CONF_SOURCE'!I16='18_WEIGHT_CONTROL'!$A$5,'18_WEIGHT_CONTROL'!$B$5,IF('90_CANON_CONF_SOURCE'!I16='18_WEIGHT_CONTROL'!$A$6,'18_WEIGHT_CONTROL'!$B$6,IF('90_CANON_CONF_SOURCE'!I16='18_WEIGHT_CONTROL'!$A$7,'18_WEIGHT_CONTROL'!$B$7,'18_WEIGHT_CONTROL'!$B$8))) | J16: =IF('90_CANON_CONF_SOURCE'!J16='18_WEIGHT_CONTROL'!$A$5,'18_WEIGHT_CONTROL'!$B$5,IF('90_CANON_CONF_SOURCE'!J16='18_WEIGHT_CONTROL'!$A$6,'18_WEIGHT_CONTROL'!$B$6,IF('90_CANON_CONF_SOURCE'!J16='18_WEIGHT_CONTROL'!$A$7,'18_WEIGHT_CONTROL'!$B$7,'18_WEIGHT_CONTROL'!$B$8))) | K16: =IF('90_CANON_CONF_SOURCE'!K16='18_WEIGHT_CONTROL'!$A$5,'18_WEIGHT_CONTROL'!$B$5,IF('90_CANON_CONF_SOURCE'!K16='18_WEIGHT_CONTROL'!$A$6,'18_WEIGHT_CONTROL'!$B$6,IF('90_CANON_CONF_SOURCE'!K16='18_WEIGHT_CONTROL'!$A$7,'18_WEIGHT_CONTROL'!$B$7,'18_WEIGHT_CONTROL'!$B$8))) | ... Y16: =IF('90_CANON_CONF_SOURCE'!Y16='18_WEIGHT_CONTROL'!$A$5,'18_WEIGHT_CONTROL'!$B$5,IF('90_CANON_CONF_SOURCE'!Y16='18_WEIGHT_CONTROL'!$A$6,'18_WEIGHT_CONTROL'!$B$6,IF('90_CANON_CONF_SOURCE'!Y16='18_WEIGHT_CONTROL'!$A$7,'18_WEIGHT_CONTROL'!$B$7,'18_WEIGHT_CONTROL'!$B$8))) | Z16: =IF('91_MOTIF_CONF_SOURCE'!D16='18_WEIGHT_CONTROL'!$A$5,'18_WEIGHT_CONTROL'!$B$5,IF('91_MOTIF_CONF_SOURCE'!D16='18_WEIGHT_CONTROL'!$A$6,'18_WEIGHT_CONTROL'!$B$6,IF('91_MOTIF_CONF_SOURCE'!D16='18_WEIGHT_CONTROL'!$A$7,'18_WEIGHT_CONTROL'!$B$7,'18_WEIGHT_CONTROL'!$B$8))) | AA16: =IF('91_MOTIF_CONF_SOURCE'!E16='18_WEIGHT_CONTROL'!$A$5,'18_WEIGHT_CONTROL'!$B$5,IF('91_MOTIF_CONF_SOURCE'!E16='18_WEIGHT_CONTROL'!$A$6,'18_WEIGHT_CONTROL'!$B$6,IF('91_MOTIF_CONF_SOURCE'!E16='18_WEIGHT_CONTROL'!$A$7,'18_WEIGHT_CONTROL'!$B$7,'18_WEIGHT_CONTROL'!$B$8))) | AB16: =IF('91_MOTIF_CONF_SOURCE'!F16='18_WEIGHT_CONTROL'!$A$5,'18_WEIGHT_CONTROL'!$B$5,IF('91_MOTIF_CONF_SOURCE'!F16='18_WEIGHT_CONTROL'!$A$6,'18_WEIGHT_CONTROL'!$B$6,IF('91_MOTIF_CONF_SOURCE'!F16='18_WEIGHT_CONTROL'!$A$7,'18_WEIGHT_CONTROL'!$B$7,'18_WEIGHT_CONTROL'!$B$8))) | AC16: =IF('91_MOTIF_CONF_SOURCE'!G16='18_WEIGHT_CONTROL'!$A$5,'18_WEIGHT_CONTROL'!$B$5,IF('91_MOTIF_CONF_SOURCE'!G16='18_WEIGHT_CONTROL'!$A$6,'18_WEIGHT_CONTROL'!$B$6,IF('91_MOTIF_CONF_SOURCE'!G16='18_WEIGHT_CONTROL'!$A$7,'18_WEIGHT_CONTROL'!$B$7,'18_WEIGHT_CONTROL'!$B$8))) | AD16: =IF('91_MOTIF_CONF_SOURCE'!H16='18_WEIGHT_CONTROL'!$A$5,'18_WEIGHT_CONTROL'!$B$5,IF('91_MOTIF_CONF_SOURCE'!H16='18_WEIGHT_CONTROL'!$A$6,'18_WEIGHT_CONTROL'!$B$6,IF('91_MOTIF_CONF_SOURCE'!H16='18_WEIGHT_CONTROL'!$A$7,'18_WEIGHT_CONTROL'!$B$7,'18_WEIGHT_CONTROL'!$B$8))) | AE16: =IF('91_MOTIF_CONF_SOURCE'!I16='18_WEIGHT_CONTROL'!$A$5,'18_WEIGHT_CONTROL'!$B$5,IF('91_MOTIF_CONF_SOURCE'!I16='18_WEIGHT_CONTROL'!$A$6,'18_WEIGHT_CONTROL'!$B$6,IF('91_MOTIF_CONF_SOURCE'!I16='18_WEIGHT_CONTROL'!$A$7,'18_WEIGHT_CONTROL'!$B$7,'18_WEIGHT_CONTROL'!$B$8))) | AF16: =IF('91_MOTIF_CONF_SOURCE'!J16='18_WEIGHT_CONTROL'!$A$5,'18_WEIGHT_CONTROL'!$B$5,IF('91_MOTIF_CONF_SOURCE'!J16='18_WEIGHT_CONTROL'!$A$6,'18_WEIGHT_CONTROL'!$B$6,IF('91_MOTIF_CONF_SOURCE'!J16='18_WEIGHT_CONTROL'!$A$7,'18_WEIGHT_CONTROL'!$B$7,'18_WEIGHT_CONTROL'!$B$8))) | AG16: =IF('91_MOTIF_CONF_SOURCE'!K16='18_WEIGHT_CONTROL'!$A$5,'18_WEIGHT_CONTROL'!$B$5,IF('91_MOTIF_CONF_SOURCE'!K16='18_WEIGHT_CONTROL'!$A$6,'18_WEIGHT_CONTROL'!$B$6,IF('91_MOTIF_CONF_SOURCE'!K16='18_WEIGHT_CONTROL'!$A$7,'18_WEIGHT_CONTROL'!$B$7,'18_WEIGHT_CONTROL'!$B$8))) | ... AR16: =IF('91_MOTIF_CONF_SOURCE'!V16='18_WEIGHT_CONTROL'!$A$5,'18_WEIGHT_CONTROL'!$B$5,IF('91_MOTIF_CONF_SOURCE'!V16='18_WEIGHT_CONTROL'!$A$6,'18_WEIGHT_CONTROL'!$B$6,IF('91_MOTIF_CONF_SOURCE'!V16='18_WEIGHT_CONTROL'!$A$7,'18_WEIGHT_CONTROL'!$B$7,'18_WEIGHT_CONTROL'!$B$8)))
... A27: 23 | B27: 地球源靈魂 | C27: Earth-Origin Soul | D27: =IF('90_CANON_CONF_SOURCE'!D27='18_WEIGHT_CONTROL'!$A$5,'18_WEIGHT_CONTROL'!$B$5,IF('90_CANON_CONF_SOURCE'!D27='18_WEIGHT_CONTROL'!$A$6,'18_WEIGHT_CONTROL'!$B$6,IF('90_CANON_CONF_SOURCE'!D27='18_WEIGHT_CONTROL'!$A$7,'18_WEIGHT_CONTROL'!$B$7,'18_WEIGHT_CONTROL'!$B$8))) | E27: =IF('90_CANON_CONF_SOURCE'!E27='18_WEIGHT_CONTROL'!$A$5,'18_WEIGHT_CONTROL'!$B$5,IF('90_CANON_CONF_SOURCE'!E27='18_WEIGHT_CONTROL'!$A$6,'18_WEIGHT_CONTROL'!$B$6,IF('90_CANON_CONF_SOURCE'!E27='18_WEIGHT_CONTROL'!$A$7,'18_WEIGHT_CONTROL'!$B$7,'18_WEIGHT_CONTROL'!$B$8))) | F27: =IF('90_CANON_CONF_SOURCE'!F27='18_WEIGHT_CONTROL'!$A$5,'18_WEIGHT_CONTROL'!$B$5,IF('90_CANON_CONF_SOURCE'!F27='18_WEIGHT_CONTROL'!$A$6,'18_WEIGHT_CONTROL'!$B$6,IF('90_CANON_CONF_SOURCE'!F27='18_WEIGHT_CONTROL'!$A$7,'18_WEIGHT_CONTROL'!$B$7,'18_WEIGHT_CONTROL'!$B$8))) | G27: =IF('90_CANON_CONF_SOURCE'!G27='18_WEIGHT_CONTROL'!$A$5,'18_WEIGHT_CONTROL'!$B$5,IF('90_CANON_CONF_SOURCE'!G27='18_WEIGHT_CONTROL'!$A$6,'18_WEIGHT_CONTROL'!$B$6,IF('90_CANON_CONF_SOURCE'!G27='18_WEIGHT_CONTROL'!$A$7,'18_WEIGHT_CONTROL'!$B$7,'18_WEIGHT_CONTROL'!$B$8))) | H27: =IF('90_CANON_CONF_SOURCE'!H27='18_WEIGHT_CONTROL'!$A$5,'18_WEIGHT_CONTROL'!$B$5,IF('90_CANON_CONF_SOURCE'!H27='18_WEIGHT_CONTROL'!$A$6,'18_WEIGHT_CONTROL'!$B$6,IF('90_CANON_CONF_SOURCE'!H27='18_WEIGHT_CONTROL'!$A$7,'18_WEIGHT_CONTROL'!$B$7,'18_WEIGHT_CONTROL'!$B$8))) | I27: =IF('90_CANON_CONF_SOURCE'!I27='18_WEIGHT_CONTROL'!$A$5,'18_WEIGHT_CONTROL'!$B$5,IF('90_CANON_CONF_SOURCE'!I27='18_WEIGHT_CONTROL'!$A$6,'18_WEIGHT_CONTROL'!$B$6,IF('90_CANON_CONF_SOURCE'!I27='18_WEIGHT_CONTROL'!$A$7,'18_WEIGHT_CONTROL'!$B$7,'18_WEIGHT_CONTROL'!$B$8))) | J27: =IF('90_CANON_CONF_SOURCE'!J27='18_WEIGHT_CONTROL'!$A$5,'18_WEIGHT_CONTROL'!$B$5,IF('90_CANON_CONF_SOURCE'!J27='18_WEIGHT_CONTROL'!$A$6,'18_WEIGHT_CONTROL'!$B$6,IF('90_CANON_CONF_SOURCE'!J27='18_WEIGHT_CONTROL'!$A$7,'18_WEIGHT_CONTROL'!$B$7,'18_WEIGHT_CONTROL'!$B$8))) | K27: =IF('90_CANON_CONF_SOURCE'!K27='18_WEIGHT_CONTROL'!$A$5,'18_WEIGHT_CONTROL'!$B$5,IF('90_CANON_CONF_SOURCE'!K27='18_WEIGHT_CONTROL'!$A$6,'18_WEIGHT_CONTROL'!$B$6,IF('90_CANON_CONF_SOURCE'!K27='18_WEIGHT_CONTROL'!$A$7,'18_WEIGHT_CONTROL'!$B$7,'18_WEIGHT_CONTROL'!$B$8))) | ... Y27: =IF('90_CANON_CONF_SOURCE'!Y27='18_WEIGHT_CONTROL'!$A$5,'18_WEIGHT_CONTROL'!$B$5,IF('90_CANON_CONF_SOURCE'!Y27='18_WEIGHT_CONTROL'!$A$6,'18_WEIGHT_CONTROL'!$B$6,IF('90_CANON_CONF_SOURCE'!Y27='18_WEIGHT_CONTROL'!$A$7,'18_WEIGHT_CONTROL'!$B$7,'18_WEIGHT_CONTROL'!$B$8))) | Z27: =IF('91_MOTIF_CONF_SOURCE'!D27='18_WEIGHT_CONTROL'!$A$5,'18_WEIGHT_CONTROL'!$B$5,IF('91_MOTIF_CONF_SOURCE'!D27='18_WEIGHT_CONTROL'!$A$6,'18_WEIGHT_CONTROL'!$B$6,IF('91_MOTIF_CONF_SOURCE'!D27='18_WEIGHT_CONTROL'!$A$7,'18_WEIGHT_CONTROL'!$B$7,'18_WEIGHT_CONTROL'!$B$8))) | AA27: =IF('91_MOTIF_CONF_SOURCE'!E27='18_WEIGHT_CONTROL'!$A$5,'18_WEIGHT_CONTROL'!$B$5,IF('91_MOTIF_CONF_SOURCE'!E27='18_WEIGHT_CONTROL'!$A$6,'18_WEIGHT_CONTROL'!$B$6,IF('91_MOTIF_CONF_SOURCE'!E27='18_WEIGHT_CONTROL'!$A$7,'18_WEIGHT_CONTROL'!$B$7,'18_WEIGHT_CONTROL'!$B$8))) | AB27: =IF('91_MOTIF_CONF_SOURCE'!F27='18_WEIGHT_CONTROL'!$A$5,'18_WEIGHT_CONTROL'!$B$5,IF('91_MOTIF_CONF_SOURCE'!F27='18_WEIGHT_CONTROL'!$A$6,'18_WEIGHT_CONTROL'!$B$6,IF('91_MOTIF_CONF_SOURCE'!F27='18_WEIGHT_CONTROL'!$A$7,'18_WEIGHT_CONTROL'!$B$7,'18_WEIGHT_CONTROL'!$B$8))) | AC27: =IF('91_MOTIF_CONF_SOURCE'!G27='18_WEIGHT_CONTROL'!$A$5,'18_WEIGHT_CONTROL'!$B$5,IF('91_MOTIF_CONF_SOURCE'!G27='18_WEIGHT_CONTROL'!$A$6,'18_WEIGHT_CONTROL'!$B$6,IF('91_MOTIF_CONF_SOURCE'!G27='18_WEIGHT_CONTROL'!$A$7,'18_WEIGHT_CONTROL'!$B$7,'18_WEIGHT_CONTROL'!$B$8))) | AD27: =IF('91_MOTIF_CONF_SOURCE'!H27='18_WEIGHT_CONTROL'!$A$5,'18_WEIGHT_CONTROL'!$B$5,IF('91_MOTIF_CONF_SOURCE'!H27='18_WEIGHT_CONTROL'!$A$6,'18_WEIGHT_CONTROL'!$B$6,IF('91_MOTIF_CONF_SOURCE'!H27='18_WEIGHT_CONTROL'!$A$7,'18_WEIGHT_CONTROL'!$B$7,'18_WEIGHT_CONTROL'!$B$8))) | AE27: =IF('91_MOTIF_CONF_SOURCE'!I27='18_WEIGHT_CONTROL'!$A$5,'18_WEIGHT_CONTROL'!$B$5,IF('91_MOTIF_CONF_SOURCE'!I27='18_WEIGHT_CONTROL'!$A$6,'18_WEIGHT_CONTROL'!$B$6,IF('91_MOTIF_CONF_SOURCE'!I27='18_WEIGHT_CONTROL'!$A$7,'18_WEIGHT_CONTROL'!$B$7,'18_WEIGHT_CONTROL'!$B$8))) | AF27: =IF('91_MOTIF_CONF_SOURCE'!J27='18_WEIGHT_CONTROL'!$A$5,'18_WEIGHT_CONTROL'!$B$5,IF('91_MOTIF_CONF_SOURCE'!J27='18_WEIGHT_CONTROL'!$A$6,'18_WEIGHT_CONTROL'!$B$6,IF('91_MOTIF_CONF_SOURCE'!J27='18_WEIGHT_CONTROL'!$A$7,'18_WEIGHT_CONTROL'!$B$7,'18_WEIGHT_CONTROL'!$B$8))) | AG27: =IF('91_MOTIF_CONF_SOURCE'!K27='18_WEIGHT_CONTROL'!$A$5,'18_WEIGHT_CONTROL'!$B$5,IF('91_MOTIF_CONF_SOURCE'!K27='18_WEIGHT_CONTROL'!$A$6,'18_WEIGHT_CONTROL'!$B$6,IF('91_MOTIF_CONF_SOURCE'!K27='18_WEIGHT_CONTROL'!$A$7,'18_WEIGHT_CONTROL'!$B$7,'18_WEIGHT_CONTROL'!$B$8))) | ... AR27: =IF('91_MOTIF_CONF_SOURCE'!V27='18_WEIGHT_CONTROL'!$A$5,'18_WEIGHT_CONTROL'!$B$5,IF('91_MOTIF_CONF_SOURCE'!V27='18_WEIGHT_CONTROL'!$A$6,'18_WEIGHT_CONTROL'!$B$6,IF('91_MOTIF_CONF_SOURCE'!V27='18_WEIGHT_CONTROL'!$A$7,'18_WEIGHT_CONTROL'!$B$7,'18_WEIGHT_CONTROL'!$B$8)))

Sheet 19_FEATURE_CONFIDENCE
A1: 41-Feature Global Evidence Confidence
A2: For absolute Global items only: confidence is averaged across nonzero lineage evidence. Neutral/zero cells do not lower a feature merely because “not defining” is uncertain.
A4: Feature | B4: Layer | C4: Scale | D4: Global evidence confidence | E4: Nonzero lineage n | F4: Source | G4: Interpretation
A5: D01 | B5: Core Process | C5: -1..+1 standardized | D5: =IFERROR(SUMPRODUCT(ABS('05_FEATURE_MODEL'!D$5:D$27),'92_FEATURE_CONF_NUMERIC'!D$5:D$27)/SUMPRODUCT(ABS('05_FEATURE_MODEL'!D$5:D$27)),'18_WEIGHT_CONTROL'!$B$8) | E5: =COUNTIF('05_FEATURE_MODEL'!D$5:D$27,"<>0") | F5: Frozen v4 cell-confidence matrix | G5: Used only when an item has no named target edge.
A6: D02 | B6: Core Process | C6: -1..+1 standardized | D6: =IFERROR(SUMPRODUCT(ABS('05_FEATURE_MODEL'!E$5:E$27),'92_FEATURE_CONF_NUMERIC'!E$5:E$27)/SUMPRODUCT(ABS('05_FEATURE_MODEL'!E$5:E$27)),'18_WEIGHT_CONTROL'!$B$8) | E6: =COUNTIF('05_FEATURE_MODEL'!E$5:E$27,"<>0") | F6: Frozen v4 cell-confidence matrix | G6: Used only when an item has no named target edge.
A7: D03 | B7: Core Process | C7: -1..+1 standardized | D7: =IFERROR(SUMPRODUCT(ABS('05_FEATURE_MODEL'!F$5:F$27),'92_FEATURE_CONF_NUMERIC'!F$5:F$27)/SUMPRODUCT(ABS('05_FEATURE_MODEL'!F$5:F$27)),'18_WEIGHT_CONTROL'!$B$8) | E7: =COUNTIF('05_FEATURE_MODEL'!F$5:F$27,"<>0") | F7: Frozen v4 cell-confidence matrix | G7: Used only when an item has no named target edge.
A8: D04 | B8: Core Process | C8: -1..+1 standardized | D8: =IFERROR(SUMPRODUCT(ABS('05_FEATURE_MODEL'!G$5:G$27),'92_FEATURE_CONF_NUMERIC'!G$5:G$27)/SUMPRODUCT(ABS('05_FEATURE_MODEL'!G$5:G$27)),'18_WEIGHT_CONTROL'!$B$8) | E8: =COUNTIF('05_FEATURE_MODEL'!G$5:G$27,"<>0") | F8: Frozen v4 cell-confidence matrix | G8: Used only when an item has no named target edge.
A9: D05 | B9: Core Process | C9: -1..+1 standardized | D9: =IFERROR(SUMPRODUCT(ABS('05_FEATURE_MODEL'!H$5:H$27),'92_FEATURE_CONF_NUMERIC'!H$5:H$27)/SUMPRODUCT(ABS('05_FEATURE_MODEL'!H$5:H$27)),'18_WEIGHT_CONTROL'!$B$8) | E9: =COUNTIF('05_FEATURE_MODEL'!H$5:H$27,"<>0") | F9: Frozen v4 cell-confidence matrix | G9: Used only when an item has no named target edge.
A10: D06 | B10: Core Process | C10: -1..+1 standardized | D10: =IFERROR(SUMPRODUCT(ABS('05_FEATURE_MODEL'!I$5:I$27),'92_FEATURE_CONF_NUMERIC'!I$5:I$27)/SUMPRODUCT(ABS('05_FEATURE_MODEL'!I$5:I$27)),'18_WEIGHT_CONTROL'!$B$8) | E10: =COUNTIF('05_FEATURE_MODEL'!I$5:I$27,"<>0") | F10: Frozen v4 cell-confidence matrix | G10: Used only when an item has no named target edge.
A11: D07 | B11: Core Process | C11: -1..+1 standardized | D11: =IFERROR(SUMPRODUCT(ABS('05_FEATURE_MODEL'!J$5:J$27),'92_FEATURE_CONF_NUMERIC'!J$5:J$27)/SUMPRODUCT(ABS('05_FEATURE_MODEL'!J$5:J$27)),'18_WEIGHT_CONTROL'!$B$8) | E11: =COUNTIF('05_FEATURE_MODEL'!J$5:J$27,"<>0") | F11: Frozen v4 cell-confidence matrix | G11: Used only when an item has no named target edge.
A12: D08 | B12: Context/Role salience | C12: 0..1 standardized | D12: =IFERROR(SUMPRODUCT(ABS('05_FEATURE_MODEL'!K$5:K$27),'92_FEATURE_CONF_NUMERIC'!K$5:K$27)/SUMPRODUCT(ABS('05_FEATURE_MODEL'!K$5:K$27)),'18_WEIGHT_CONTROL'!$B$8) | E12: =COUNTIF('05_FEATURE_MODEL'!K$5:K$27,"<>0") | F12: Frozen v4 cell-confidence matrix | G12: Used only when an item has no named target edge.
A13: D09 | B13: Core Process | C13: -1..+1 standardized | D13: =IFERROR(SUMPRODUCT(ABS('05_FEATURE_MODEL'!L$5:L$27),'92_FEATURE_CONF_NUMERIC'!L$5:L$27)/SUMPRODUCT(ABS('05_FEATURE_MODEL'!L$5:L$27)),'18_WEIGHT_CONTROL'!$B$8) | E13: =COUNTIF('05_FEATURE_MODEL'!L$5:L$27,"<>0") | F13: Frozen v4 cell-confidence matrix | G13: Used only when an item has no named target edge.
A14: D10 | B14: Core Process | C14: -1..+1 standardized | D14: =IFERROR(SUMPRODUCT(ABS('05_FEATURE_MODEL'!M$5:M$27),'92_FEATURE_CONF_NUMERIC'!M$5:M$27)/SUMPRODUCT(ABS('05_FEATURE_MODEL'!M$5:M$27)),'18_WEIGHT_CONTROL'!$B$8) | E14: =COUNTIF('05_FEATURE_MODEL'!M$5:M$27,"<>0") | F14: Frozen v4 cell-confidence matrix | G14: Used only when an item has no named target edge.
A15: D11 | B15: Core Process | C15: -1..+1 standardized | D15: =IFERROR(SUMPRODUCT(ABS('05_FEATURE_MODEL'!N$5:N$27),'92_FEATURE_CONF_NUMERIC'!N$5:N$27)/SUMPRODUCT(ABS('05_FEATURE_MODEL'!N$5:N$27)),'18_WEIGHT_CONTROL'!$B$8) | E15: =COUNTIF('05_FEATURE_MODEL'!N$5:N$27,"<>0") | F15: Frozen v4 cell-confidence matrix | G15: Used only when an item has no named target edge.
A16: D12 | B16: Core Process | C16: -1..+1 standardized | D16: =IFERROR(SUMPRODUCT(ABS('05_FEATURE_MODEL'!O$5:O$27),'92_FEATURE_CONF_NUMERIC'!O$5:O$27)/SUMPRODUCT(ABS('05_FEATURE_MODEL'!O$5:O$27)),'18_WEIGHT_CONTROL'!$B$8) | E16: =COUNTIF('05_FEATURE_MODEL'!O$5:O$27,"<>0") | F16: Frozen v4 cell-confidence matrix | G16: Used only when an item has no named target edge.
A17: D13 | B17: Core Process | C17: -1..+1 standardized | D17: =IFERROR(SUMPRODUCT(ABS('05_FEATURE_MODEL'!P$5:P$27),'92_FEATURE_CONF_NUMERIC'!P$5:P$27)/SUMPRODUCT(ABS('05_FEATURE_MODEL'!P$5:P$27)),'18_WEIGHT_CONTROL'!$B$8) | E17: =COUNTIF('05_FEATURE_MODEL'!P$5:P$27,"<>0") | F17: Frozen v4 cell-confidence matrix | G17: Used only when an item has no named target edge.
A18: D14 | B18: Core Process | C18: -1..+1 standardized | D18: =IFERROR(SUMPRODUCT(ABS('05_FEATURE_MODEL'!Q$5:Q$27),'92_FEATURE_CONF_NUMERIC'!Q$5:Q$27)/SUMPRODUCT(ABS('05_FEATURE_MODEL'!Q$5:Q$27)),'18_WEIGHT_CONTROL'!$B$8) | E18: =COUNTIF('05_FEATURE_MODEL'!Q$5:Q$27,"<>0") | F18: Frozen v4 cell-confidence matrix | G18: Used only when an item has no named target edge.
A19: D15 | B19: Core Process | C19: -1..+1 standardized | D19: =IFERROR(SUMPRODUCT(ABS('05_FEATURE_MODEL'!R$5:R$27),'92_FEATURE_CONF_NUMERIC'!R$5:R$27)/SUMPRODUCT(ABS('05_FEATURE_MODEL'!R$5:R$27)),'18_WEIGHT_CONTROL'!$B$8) | E19: =COUNTIF('05_FEATURE_MODEL'!R$5:R$27,"<>0") | F19: Frozen v4 cell-confidence matrix | G19: Used only when an item has no named target edge.
A20: D16 | B20: Context/Role salience | C20: 0..1 standardized | D20: =IFERROR(SUMPRODUCT(ABS('05_FEATURE_MODEL'!S$5:S$27),'92_FEATURE_CONF_NUMERIC'!S$5:S$27)/SUMPRODUCT(ABS('05_FEATURE_MODEL'!S$5:S$27)),'18_WEIGHT_CONTROL'!$B$8) | E20: =COUNTIF('05_FEATURE_MODEL'!S$5:S$27,"<>0") | F20: Frozen v4 cell-confidence matrix | G20: Used only when an item has no named target edge.
A21: D17 | B21: Context/Role salience | C21: 0..1 standardized | D21: =IFERROR(SUMPRODUCT(ABS('05_FEATURE_MODEL'!T$5:T$27),'92_FEATURE_CONF_NUMERIC'!T$5:T$27)/SUMPRODUCT(ABS('05_FEATURE_MODEL'!T$5:T$27)),'18_WEIGHT_CONTROL'!$B$8) | E21: =COUNTIF('05_FEATURE_MODEL'!T$5:T$27,"<>0") | F21: Frozen v4 cell-confidence matrix | G21: Used only when an item has no named target edge.
A22: D18 | B22: Context/Role salience | C22: 0..1 standardized | D22: =IFERROR(SUMPRODUCT(ABS('05_FEATURE_MODEL'!U$5:U$27),'92_FEATURE_CONF_NUMERIC'!U$5:U$27)/SUMPRODUCT(ABS('05_FEATURE_MODEL'!U$5:U$27)),'18_WEIGHT_CONTROL'!$B$8) | E22: =COUNTIF('05_FEATURE_MODEL'!U$5:U$27,"<>0") | F22: Frozen v4 cell-confidence matrix | G22: Used only when an item has no named target edge.
A23: D19 | B23: Context/Role salience | C23: 0..1 standardized | D23: =IFERROR(SUMPRODUCT(ABS('05_FEATURE_MODEL'!V$5:V$27),'92_FEATURE_CONF_NUMERIC'!V$5:V$27)/SUMPRODUCT(ABS('05_FEATURE_MODEL'!V$5:V$27)),'18_WEIGHT_CONTROL'!$B$8) | E23: =COUNTIF('05_FEATURE_MODEL'!V$5:V$27,"<>0") | F23: Frozen v4 cell-confidence matrix | G23: Used only when an item has no named target edge.
A24: D20 | B24: Core Process | C24: -1..+1 standardized | D24: =IFERROR(SUMPRODUCT(ABS('05_FEATURE_MODEL'!W$5:W$27),'92_FEATURE_CONF_NUMERIC'!W$5:W$27)/SUMPRODUCT(ABS('05_FEATURE_MODEL'!W$5:W$27)),'18_WEIGHT_CONTROL'!$B$8) | E24: =COUNTIF('05_FEATURE_MODEL'!W$5:W$27,"<>0") | F24: Frozen v4 cell-confidence matrix | G24: Used only when an item has no named target edge.
A25: D21 | B25: Core Process | C25: -1..+1 standardized | D25: =IFERROR(SUMPRODUCT(ABS('05_FEATURE_MODEL'!X$5:X$27),'92_FEATURE_CONF_NUMERIC'!X$5:X$27)/SUMPRODUCT(ABS('05_FEATURE_MODEL'!X$5:X$27)),'18_WEIGHT_CONTROL'!$B$8) | E25: =COUNTIF('05_FEATURE_MODEL'!X$5:X$27,"<>0") | F25: Frozen v4 cell-confidence matrix | G25: Used only when an item has no named target edge.
A26: D22 | B26: Origin/Belonging | C26: -1..+1 standardized | D26: =IFERROR(SUMPRODUCT(ABS('05_FEATURE_MODEL'!Y$5:Y$27),'92_FEATURE_CONF_NUMERIC'!Y$5:Y$27)/SUMPRODUCT(ABS('05_FEATURE_MODEL'!Y$5:Y$27)),'18_WEIGHT_CONTROL'!$B$8) | E26: =COUNTIF('05_FEATURE_MODEL'!Y$5:Y$27,"<>0") | F26: Frozen v4 cell-confidence matrix | G26: Used only when an item has no named target edge.
A27: M01 | B27: Motif | C27: 0..1 standardized | D27: =IFERROR(SUMPRODUCT(ABS('05_FEATURE_MODEL'!Z$5:Z$27),'92_FEATURE_CONF_NUMERIC'!Z$5:Z$27)/SUMPRODUCT(ABS('05_FEATURE_MODEL'!Z$5:Z$27)),'18_WEIGHT_CONTROL'!$B$8) | E27: =COUNTIF('05_FEATURE_MODEL'!Z$5:Z$27,"<>0") | F27: Frozen v4 cell-confidence matrix | G27: Motif absence is not negative evidence; only nonzero motif evidence contributes.
A28: M02 | B28: Motif | C28: 0..1 standardized | D28: =IFERROR(SUMPRODUCT(ABS('05_FEATURE_MODEL'!AA$5:AA$27),'92_FEATURE_CONF_NUMERIC'!AA$5:AA$27)/SUMPRODUCT(ABS('05_FEATURE_MODEL'!AA$5:AA$27)),'18_WEIGHT_CONTROL'!$B$8) | E28: =COUNTIF('05_FEATURE_MODEL'!AA$5:AA$27,"<>0") | F28: Frozen v4 cell-confidence matrix | G28: Motif absence is not negative evidence; only nonzero motif evidence contributes.
A29: M03 | B29: Motif | C29: 0..1 standardized | D29: =IFERROR(SUMPRODUCT(ABS('05_FEATURE_MODEL'!AB$5:AB$27),'92_FEATURE_CONF_NUMERIC'!AB$5:AB$27)/SUMPRODUCT(ABS('05_FEATURE_MODEL'!AB$5:AB$27)),'18_WEIGHT_CONTROL'!$B$8) | E29: =COUNTIF('05_FEATURE_MODEL'!AB$5:AB$27,"<>0") | F29: Frozen v4 cell-confidence matrix | G29: Motif absence is not negative evidence; only nonzero motif evidence contributes.
A30: M04 | B30: Motif | C30: 0..1 standardized | D30: =IFERROR(SUMPRODUCT(ABS('05_FEATURE_MODEL'!AC$5:AC$27),'92_FEATURE_CONF_NUMERIC'!AC$5:AC$27)/SUMPRODUCT(ABS('05_FEATURE_MODEL'!AC$5:AC$27)),'18_WEIGHT_CONTROL'!$B$8) | E30: =COUNTIF('05_FEATURE_MODEL'!AC$5:AC$27,"<>0") | F30: Frozen v4 cell-confidence matrix | G30: Motif absence is not negative evidence; only nonzero motif evidence contributes.
A31: M05 | B31: Motif | C31: 0..1 standardized | D31: =IFERROR(SUMPRODUCT(ABS('05_FEATURE_MODEL'!AD$5:AD$27),'92_FEATURE_CONF_NUMERIC'!AD$5:AD$27)/SUMPRODUCT(ABS('05_FEATURE_MODEL'!AD$5:AD$27)),'18_WEIGHT_CONTROL'!$B$8) | E31: =COUNTIF('05_FEATURE_MODEL'!AD$5:AD$27,"<>0") | F31: Frozen v4 cell-confidence matrix | G31: Motif absence is not negative evidence; only nonzero motif evidence contributes.
A32: M06 | B32: Motif | C32: 0..1 standardized | D32: =IFERROR(SUMPRODUCT(ABS('05_FEATURE_MODEL'!AE$5:AE$27),'92_FEATURE_CONF_NUMERIC'!AE$5:AE$27)/SUMPRODUCT(ABS('05_FEATURE_MODEL'!AE$5:AE$27)),'18_WEIGHT_CONTROL'!$B$8) | E32: =COUNTIF('05_FEATURE_MODEL'!AE$5:AE$27,"<>0") | F32: Frozen v4 cell-confidence matrix | G32: Motif absence is not negative evidence; only nonzero motif evidence contributes.
A33: M07 | B33: Motif | C33: 0..1 standardized | D33: =IFERROR(SUMPRODUCT(ABS('05_FEATURE_MODEL'!AF$5:AF$27),'92_FEATURE_CONF_NUMERIC'!AF$5:AF$27)/SUMPRODUCT(ABS('05_FEATURE_MODEL'!AF$5:AF$27)),'18_WEIGHT_CONTROL'!$B$8) | E33: =COUNTIF('05_FEATURE_MODEL'!AF$5:AF$27,"<>0") | F33: Frozen v4 cell-confidence matrix | G33: Motif absence is not negative evidence; only nonzero motif evidence contributes.
A34: M08 | B34: Motif | C34: 0..1 standardized | D34: =IFERROR(SUMPRODUCT(ABS('05_FEATURE_MODEL'!AG$5:AG$27),'92_FEATURE_CONF_NUMERIC'!AG$5:AG$27)/SUMPRODUCT(ABS('05_FEATURE_MODEL'!AG$5:AG$27)),'18_WEIGHT_CONTROL'!$B$8) | E34: =COUNTIF('05_FEATURE_MODEL'!AG$5:AG$27,"<>0") | F34: Frozen v4 cell-confidence matrix | G34: Motif absence is not negative evidence; only nonzero motif evidence contributes.
A35: M09 | B35: Motif | C35: 0..1 standardized | D35: =IFERROR(SUMPRODUCT(ABS('05_FEATURE_MODEL'!AH$5:AH$27),'92_FEATURE_CONF_NUMERIC'!AH$5:AH$27)/SUMPRODUCT(ABS('05_FEATURE_MODEL'!AH$5:AH$27)),'18_WEIGHT_CONTROL'!$B$8) | E35: =COUNTIF('05_FEATURE_MODEL'!AH$5:AH$27,"<>0") | F35: Frozen v4 cell-confidence matrix | G35: Motif absence is not negative evidence; only nonzero motif evidence contributes.
A36: M10 | B36: Motif | C36: 0..1 standardized | D36: =IFERROR(SUMPRODUCT(ABS('05_FEATURE_MODEL'!AI$5:AI$27),'92_FEATURE_CONF_NUMERIC'!AI$5:AI$27)/SUMPRODUCT(ABS('05_FEATURE_MODEL'!AI$5:AI$27)),'18_WEIGHT_CONTROL'!$B$8) | E36: =COUNTIF('05_FEATURE_MODEL'!AI$5:AI$27,"<>0") | F36: Frozen v4 cell-confidence matrix | G36: Motif absence is not negative evidence; only nonzero motif evidence contributes.
A37: M11 | B37: Motif | C37: 0..1 standardized | D37: =IFERROR(SUMPRODUCT(ABS('05_FEATURE_MODEL'!AJ$5:AJ$27),'92_FEATURE_CONF_NUMERIC'!AJ$5:AJ$27)/SUMPRODUCT(ABS('05_FEATURE_MODEL'!AJ$5:AJ$27)),'18_WEIGHT_CONTROL'!$B$8) | E37: =COUNTIF('05_FEATURE_MODEL'!AJ$5:AJ$27,"<>0") | F37: Frozen v4 cell-confidence matrix | G37: Motif absence is not negative evidence; only nonzero motif evidence contributes.
A38: M12 | B38: Motif | C38: 0..1 standardized | D38: =IFERROR(SUMPRODUCT(ABS('05_FEATURE_MODEL'!AK$5:AK$27),'92_FEATURE_CONF_NUMERIC'!AK$5:AK$27)/SUMPRODUCT(ABS('05_FEATURE_MODEL'!AK$5:AK$27)),'18_WEIGHT_CONTROL'!$B$8) | E38: =COUNTIF('05_FEATURE_MODEL'!AK$5:AK$27,"<>0") | F38: Frozen v4 cell-confidence matrix | G38: Motif absence is not negative evidence; only nonzero motif evidence contributes.
A39: M13 | B39: Motif | C39: 0..1 standardized | D39: =IFERROR(SUMPRODUCT(ABS('05_FEATURE_MODEL'!AL$5:AL$27),'92_FEATURE_CONF_NUMERIC'!AL$5:AL$27)/SUMPRODUCT(ABS('05_FEATURE_MODEL'!AL$5:AL$27)),'18_WEIGHT_CONTROL'!$B$8) | E39: =COUNTIF('05_FEATURE_MODEL'!AL$5:AL$27,"<>0") | F39: Frozen v4 cell-confidence matrix | G39: Motif absence is not negative evidence; only nonzero motif evidence contributes.
A40: M14 | B40: Motif | C40: 0..1 standardized | D40: =IFERROR(SUMPRODUCT(ABS('05_FEATURE_MODEL'!AM$5:AM$27),'92_FEATURE_CONF_NUMERIC'!AM$5:AM$27)/SUMPRODUCT(ABS('05_FEATURE_MODEL'!AM$5:AM$27)),'18_WEIGHT_CONTROL'!$B$8) | E40: =COUNTIF('05_FEATURE_MODEL'!AM$5:AM$27,"<>0") | F40: Frozen v4 cell-confidence matrix | G40: Motif absence is not negative evidence; only nonzero motif evidence contributes.
A41: M15 | B41: Motif | C41: 0..1 standardized | D41: =IFERROR(SUMPRODUCT(ABS('05_FEATURE_MODEL'!AN$5:AN$27),'92_FEATURE_CONF_NUMERIC'!AN$5:AN$27)/SUMPRODUCT(ABS('05_FEATURE_MODEL'!AN$5:AN$27)),'18_WEIGHT_CONTROL'!$B$8) | E41: =COUNTIF('05_FEATURE_MODEL'!AN$5:AN$27,"<>0") | F41: Frozen v4 cell-confidence matrix | G41: Motif absence is not negative evidence; only nonzero motif evidence contributes.
A42: M16 | B42: Motif | C42: 0..1 standardized | D42: =IFERROR(SUMPRODUCT(ABS('05_FEATURE_MODEL'!AO$5:AO$27),'92_FEATURE_CONF_NUMERIC'!AO$5:AO$27)/SUMPRODUCT(ABS('05_FEATURE_MODEL'!AO$5:AO$27)),'18_WEIGHT_CONTROL'!$B$8) | E42: =COUNTIF('05_FEATURE_MODEL'!AO$5:AO$27,"<>0") | F42: Frozen v4 cell-confidence matrix | G42: Motif absence is not negative evidence; only nonzero motif evidence contributes.
A43: M17 | B43: Motif | C43: 0..1 standardized | D43: =IFERROR(SUMPRODUCT(ABS('05_FEATURE_MODEL'!AP$5:AP$27),'92_FEATURE_CONF_NUMERIC'!AP$5:AP$27)/SUMPRODUCT(ABS('05_FEATURE_MODEL'!AP$5:AP$27)),'18_WEIGHT_CONTROL'!$B$8) | E43: =COUNTIF('05_FEATURE_MODEL'!AP$5:AP$27,"<>0") | F43: Frozen v4 cell-confidence matrix | G43: Motif absence is not negative evidence; only nonzero motif evidence contributes.
A44: M18 | B44: Motif | C44: 0..1 standardized | D44: =IFERROR(SUMPRODUCT(ABS('05_FEATURE_MODEL'!AQ$5:AQ$27),'92_FEATURE_CONF_NUMERIC'!AQ$5:AQ$27)/SUMPRODUCT(ABS('05_FEATURE_MODEL'!AQ$5:AQ$27)),'18_WEIGHT_CONTROL'!$B$8) | E44: =COUNTIF('05_FEATURE_MODEL'!AQ$5:AQ$27,"<>0") | F44: Frozen v4 cell-confidence matrix | G44: Motif absence is not negative evidence; only nonzero motif evidence contributes.
A45: M19 | B45: Motif | C45: 0..1 standardized | D45: =IFERROR(SUMPRODUCT(ABS('05_FEATURE_MODEL'!AR$5:AR$27),'92_FEATURE_CONF_NUMERIC'!AR$5:AR$27)/SUMPRODUCT(ABS('05_FEATURE_MODEL'!AR$5:AR$27)),'18_WEIGHT_CONTROL'!$B$8) | E45: =COUNTIF('05_FEATURE_MODEL'!AR$5:AR$27,"<>0") | F45: Frozen v4 cell-confidence matrix | G45: Motif absence is not negative evidence; only nonzero motif evidence contributes.

Sheet 93_TARGET_MEMBERSHIP
A1: Target Membership Helper
A4: Lineage | B4: G01 | C4: G02 | D4: G03 | E4: G04 | F4: G05 | G4: G06 | H4: G07 | I4: G08 | J4: G09 | K4: G10 | L4: G11 | M4: G12 | N4: G13 | O4: G14 | P4: G15 | Q4: G16 | R4: G17 | S4: G18 | T4: G19 | U4: G20 | V4: G21 | W4: G22 | X4: G23 | Y4: G24 | Z4: G25 | AA4: G26 | AB4: G27 | AC4: G28 | AD4: G29 | AE4: G30 | AF4: L01 | AG4: L02 | AH4: L03 | AI4: L04 | AJ4: L05 | AK4: L06 | AL4: L07 | AM4: L08 | AN4: L09 | AO4: L10 | AP4: L11 | AQ4: L12 | AR4: L13 | AS4: L14 | AT4: L15 | AU4: L16 | AV4: L17 | AW4: L18 | AX4: L19 | AY4: L20 | AZ4: L21 | BA4: L22 | BB4: L23 | BC4: L24 | BD4: L25 | BE4: L26 | BF4: L27 | BG4: L28 | BH4: L29 | BI4: L30 | BJ4: L31 | BK4: L32 | BL4: L33 | BM4: L34 | BN4: L35 | BO4: L36 | BP4: L37 | BQ4: L38 | BR4: A01 | BS4: A02 | BT4: A03 | BU4: A04 | BV4: A05 | BW4: A06 | BX4: A07 | BY4: A08 | BZ4: A09 | CA4: A10 | CB4: A11 | CC4: A12
